Workbook

Sheet Resumen
C1: usd PROMEDIO
A2: Efectivo | B2: 250000 | C2: 3850
A3: Cuenta Bancol | B3: 5019665
A4: pension voluntaria ahorro casa | B4: 102536491
A5: Investor trust 1200 | B5: =4855*C2 -> 18691750
A6: Investor trust 2400 | B6: =10280*C2 -> 39578000
A7: poliza pensiones skandia | B7: 12204069
A8: Fondo de emergencia lulo | B8: 585890
A9: Littio | B9: =56.6*C2 -> 217910
A10: Nequi | B10: 168222
A11: deuda | B11: =-6151674.16 -> -6151674.2
A12: Impuestos y Seguros Carro Moto
A13: NU (Viajes) | B13: 2619684
A19: TOTAL | B19: =SUM(B2:B18) -> 1.7572001e+08
A20: Diferencia | B20: =B19-GETPIVOTDATA("MONTO",$A$24) -> 2619684 | C20: =IF(B20=0,"Balanceado!", IF(B20<0,"Te falta $, ajusta!","Te sobra $, ajusta!")) -> Te sobra $, ajusta!
A24: Suma de MONTO | C24: MES
A25: CATEGORIA | B25: SUB CATEGORIA | C25: 1 A Limpiar | D25: A Ene | E25: B Feb | F25: C Mar | G25: D Abr | H25: E May | I25: F Jun | J25: G Jul | K25: H Ago | L25: I Sep | M25: J Oct | N25: K Nov | O25: L Dec | P25: Total
A26: AHORROS | B26: Fondo de Emergencia | D26: 0 | I26: 0 | J26: 0 | K26: 0 | L26: 0 | M26: 0 | N26: 0 | O26: 0 | P26: 0
B27: Efectivo | C27: 250000 | P27: 250000
B28: Cuenta Bancol | C28: 5019665 | P28: 5019665
B29: pension voluntaria ahorro casa | C29: 102536491 | P29: 102536491
B30: Investor trust 1200 | C30: 18691750 | P30: 18691750
B31: Investor trust 2400 | C31: 39578000 | P31: 39578000
B32: poliza pensiones skandia | C32: 12204069 | P32: 12204069
B33: Fondo de emergencia lulo | C33: 585890 | P33: 585890
B34: Litio | C34: 217910 | P34: 217910
B35: Nequi | C35: 168222 | P35: 168222
A36: AHORROS | C36: 179251997 | D36: 0 | I36: 0 | J36: 0 | K36: 0 | L36: 0 | M36: 0 | N36: 0 | O36: 0 | P36: 179251997
A38: REGALOS/ CARIDAD | B38: Regalos Navidad | C38: 0 | P38: 0
B39: Regalos cumpleaños | C39: 0 | P39: 0
A40: REGALOS/ CARIDAD | C40: 0 | P40: 0
A42: CASA | B42: Mantenimiento | C42: 0 | P42: 0
B43: Impuestos | C43: 0 | P43: 0
A44: CASA | C44: 0 | P44: 0
A46: SEGUROS | B46: Carro | C46: 0 | P46: 0
B47: Vida | C47: 0 | P47: 0
B48: Casa | C48: 0 | P48: 0
B49: Salud | C49: 0 | P49: 0
A50: SEGUROS | C50: 0 | P50: 0
A52: CUIDADO PERSONAL | B52: Ropa | C52: 0 | P52: 0
B53: Belleza | C53: 0 | P53: 0
A54: CUIDADO PERSONAL | C54: 0 | P54: 0
A56: ENTRETENIMIENTO | B56: Vacaciones | C56: 0 | P56: 0
A57: ENTRETENIMIENTO | C57: 0 | P57: 0
A59: HIJOS | B59: Ropa | C59: 0 | P59: 0
B60: Estudio | C60: 0 | P60: 0
B61: Utiles Escolares | C61: 0 | P61: 0
A62: HIJOS | C62: 0 | P62: 0
A64: MASCOTA | B64: Medicinas | C64: 0 | P64: 0
B65: Veterinario | C65: 0 | P65: 0
A66: MASCOTA | C66: 0 | P66: 0
A68: (en blanco) | B68: (en blanco)
A69: (en blanco)
C71: 0 | D71: 0 | E71: 0 | F71: 0 | G71: 0 | H71: 0 | I71: 0 | J71: 0 | K71: 0 | L71: 0 | M71: 0 | N71: 0 | O71: 0 | P71: 0
C72: 0 | D72: 0 | E72: 0 | F72: 0 | G72: 0 | H72: 0 | I72: 0 | J72: 0 | K72: 0 | L72: 0 | M72: 0 | N72: 0 | O72: 0 | P72: 0
A74: SALUD | B74: Medicinas | C74: 0 | P74: 0
B75: Dentista | C75: 0 | P75: 0
B76: Tratamientos | C76: 0 | P76: 0
A77: SALUD | C77: 0 | P77: 0
A79: TRANSPORTE | B79: Mantenimiento | C79: 0 | P79: 0
B80: Impuestos | C80: 0 | P80: 0
A81: TRANSPORTE | C81: 0 | P81: 0
A83: DEUDAS | B83: Deuda tarjeta Nu | C83: -6151674.2 | P83: -6151674.2
A84: DEUDAS | C84: -6151674.2 | P84: -6151674.2
A86: Total | C86: 1.7310032e+08 | D86: 0 | E86: 0 | F86: 0 | G86: 0 | H86: 0 | I86: 0 | J86: 0 | K86: 0 | L86: 0 | M86: 0 | N86: 0 | O86: 0 | P86: 1.7310032e+08

Sheet Plantilla Ppto
U1: =B13 -> Arriendo/Hipoteca
B2: PRESUPUESTO MENSUAL
B4: Ingreso Estimado | C4: Salario
C10: Total Ingreso Mensual | E10: =SUM(E4:E9) -> 0 | H10: Balance (Ingreso vs Presupuesto) | K10: =E10-SUM(D25,D36,D55,D65,D79,D88,D98,J25,J36,J55,J65,J88,J98,D108,J108,D46,J46,J79) -> 0 | M10: =IF(K10=0,"El presupuesto está listo","OJO! Tiene que sumar cero") -> El presupuesto está listo
B12: NECESIDADES BÁSICAS | C12: Ahorro | D12: Presupuesto | E12: Gasto | F12: Disponible | H12: AHORROS | I12: Ahorro | J12: Presupuesto | K12: Gasto | L12: Disponible
B13: Arriendo/Hipoteca | F13: =D13-E13 -> 0 | H13: Fondo de Emergencia | I13: SI | L13: =J13-K13 -> 0
B14: Telefono/ Celular | F14: =D14-E14 -> 0 | H14: Fondo de Pensión | I14: SI | L14: =J14-K14 -> 0
B15: Electricidad | F15: =D15-E15 -> 0 | H15: Fondo de Educación | I15: SI | L15: =J15-K15 -> 0
B16: Agua | F16: =D16-E16 -> 0 | H16: Cuota Inicial Casa | I16: SI | L16: =J16-K16 -> 0
B17: Gas | F17: =D17-E17 -> 0 | H17: Aporte a Capital | I17: SI | L17: =J17-K17 -> 0
B18: Cable/Internet | F18: =D18-E18 -> 0 | L18: =J18-K18 -> 0
B19: Super Mercado | F19: =D19-E19 -> 0 | L19: =J19-K19 -> 0
B20: Gasolina | F20: =D20-E20 -> 0 | L20: =J20-K20 -> 0
B21: Bus | F21: =D21-E21 -> 0 | L21: =J21-K21 -> 0
F22: =D22-E22 -> 0 | L22: =J22-K22 -> 0
F23: =D23-E23 -> 0 | L23: =J23-K23 -> 0
F24: =D24-E24 -> 0 | L24: =J24-K24 -> 0
B25: Subtotal | D25: =SUM(D13:D24) -> 0 | E25: =SUM(E13:E24) -> 0 | F25: =D25-E25 -> 0 | H25: Subtotal | J25: =SUM(J13:J24) -> 0 | K25: =SUM(K13:K24) -> 0 | L25: =J25-K25 -> 0
B27: DEUDAS | C27: Ahorro | D27: Presupuesto | E27: Gasto | F27: Disponible | H27: REGALOS/ CARIDAD | I27: Ahorro | J27: Presupuesto | K27: Gasto | L27: Disponible
B28: Deuda Carro | F28: =D28-E28 -> 0 | H28: Regalos Navidad | I28: SI | L28: =J28-K28 -> 0
B29: Deuda tarjeta 1 | F29: =D29-E29 -> 0 | H29: Regalos cumpleaños | I29: SI | L29: =J29-K29 -> 0
B30: Deuda tarjeta 2 | F30: =D30-E30 -> 0 | H30: Caridad | I30: SI | L30: =J30-K30 -> 0
B31: Deuda Estudio | F31: =D31-E31 -> 0 | L31: =J31-K31 -> 0
B32: Carro | F32: =D32-E32 -> 0 | L32: =J32-K32 -> 0
F33: =D33-E33 -> 0 | L33: =J33-K33 -> 0
F34: =D34-E34 -> 0 | L34: =J34-K34 -> 0
F35: =D35-E35 -> 0 | L35: =J35-K35 -> 0
B36: Subtotal | D36: =SUM(D28:D35) -> 0 | E36: =SUM(E28:E35) -> 0 | F36: =D36-E36 -> 0 | H36: Subtotal | J36: =SUM(J28:J35) -> 0 | K36: =SUM(K28:K35) -> 0 | L36: =J36-K36 -> 0
B38: CASA | C38: Ahorro | D38: Presupuesto | E38: Gasto | F38: Disponible | H38: TRANSPORTE | I38: Ahorro | J38: Presupuesto | K38: Gasto | L38: Disponible
B39: Limpieza | F39: =D39-E39 -> 0 | H39: Uber/taxi | L39: =J39-K39 -> 0
B40: Mantenimiento | F40: =D40-E40 -> 0 | H40: Estacionamiento | L40: =J40-K40 -> 0
B41: Muebles | F41: =D41-E41 -> 0 | H41: Mantenimiento | L41: =J41-K41 -> 0
B42: Impuestos | F42: =D42-E42 -> 0 | H42: Impuestos | L42: =J42-K42 -> 0
F43: =D43-E43 -> 0 | H43: Panapass/Peaje | L43: =J43-K43 -> 0
F44: =D44-E44 -> 0 | L44: =J44-K44 -> 0
F45: =D45-E45 -> 0 | L45: =J45-K45 -> 0
B46: Subtotal | D46: =SUM(D39:D45) -> 0 | E46: =SUM(E39:E45) -> 0 | F46: =D46-E46 -> 0 | H46: Subtotal | J46: =SUM(J39:J45) -> 0 | K46: =SUM(K39:K45) -> 0 | L46: =J46-K46 -> 0
B48: ALIMENTACIÓN | C48: Ahorro | D48: Presupuesto | E48: Gasto | F48: Disponible | H48: SEGUROS | I48: Ahorro | J48: Presupuesto | K48: Gasto | L48: Disponible
B49: Restaurantes | F49: =D49-E49 -> 0 | H49: Carro | L49: =J49-K49 -> 0
B50: Café/ Snacks | F50: =D50-E50 -> 0 | H50: Vida | L50: =J50-K50 -> 0
F51: =D51-E51 -> 0 | H51: Casa | L51: =J51-K51 -> 0
F52: =D52-E52 -> 0 | H52: Salud | L52: =J52-K52 -> 0
F53: =D53-E53 -> 0 | L53: =J53-K53 -> 0
F54: =D54-E54 -> 0 | L54: =J54-K54 -> 0
B55: Subtotal | D55: =SUM(D49:D54) -> 0 | E55: =SUM(E49:E54) -> 0 | F55: =D55-E55 -> 0 | H55: Subtotal | J55: =SUM(J49:J54) -> 0 | K55: =SUM(K49:K54) -> 0 | L55: =J55-K55 -> 0
B57: SALUD | C57: Ahorro | D57: Presupuesto | E57: Gasto | F57: Disponible | H57: CUIDADO PERSONAL | I57: Ahorro | J57: Presupuesto | K57: Gasto | L57: Disponible
B58: Medicinas | F58: =D58-E58 -> 0 | H58: Ropa | I58: SI | L58: =J58-K58 -> 0
B59: Dentista | F59: =D59-E59 -> 0 | H59: Belleza | L59: =J59-K59 -> 0
B60: Tratamientos | F60: =D60-E60 -> 0 | H60: Peluquería | L60: =J60-K60 -> 0
F61: =D61-E61 -> 0 | H61: Sastre | L61: =J61-K61 -> 0
F62: =D62-E62 -> 0 | H62: Tintorería | L62: =J62-K62 -> 0
F63: =D63-E63 -> 0 | L63: =J63-K63 -> 0
F64: =D64-E64 -> 0 | L64: =J64-K64 -> 0
B65: Subtotal | D65: =SUM(D58:D64) -> 0 | E65: =SUM(E58:E64) -> 0 | F65: =D65-E65 -> 0 | H65: Subtotal | J65: =SUM(J58:J64) -> 0 | K65: =SUM(K58:K64) -> 0 | L65: =J65-K65 -> 0
B67: ENTRETENIMIENTO | C67: Ahorro | D67: Presupuesto | E67: Gasto | F67: Disponible | H67: HIJOS | I67: Ahorro | J67: Presupuesto | K67: Gasto | L67: Diferencia
B68: Vacaciones | F68: =D68-E68 -> 0 | H68: Ropa | L68: =J68-K68 -> 0
B69: Rumba | F69: =D69-E69 -> 0 | H69: Estudio | L69: =J69-K69 -> 0
B70: Citas | F70: =D70-E70 -> 0 | H70: Utiles Escolares | L70: =J70-K70 -> 0
B71: Cine | F71: =D71-E71 -> 0 | H71: Niñera | L71: =J71-K71 -> 0
B72: Deporte | F72: =D72-E72 -> 0 | L72: =J72-K72 -> 0
B73: Netflix | F73: =D73-E73 -> 0 | L73: =J73-K73 -> 0
B74: Spotify | F74: =D74-E74 -> 0 | L74: =J74-K74 -> 0
F75: =D75-E75 -> 0 | L75: =J75-K75 -> 0
F76: =D76-E76 -> 0 | L76: =J76-K76 -> 0
F77: =D77-E77 -> 0 | L77: =J77-K77 -> 0
F78: =D78-E78 -> 0 | L78: =J78-K78 -> 0
B79: Subtotal | D79: =SUM(D68:D78) -> 0 | E79: =SUM(E68:E78) -> 0 | F79: =D79-E79 -> 0 | H79: Subtotal | J79: =SUM(J68:J78) -> 0 | K79: =SUM(K68:K78) -> 0 | L79: =J79-K79 -> 0
B81: MASCOTA | C81: Ahorro | D81: Presupuesto | E81: Gasto | F81: Disponible | H81: OTROS | I81: Ahorro | J81: Presupuesto | K81: Gasto | L81: Disponible
B82: Comida | F82: =D82-E82 -> 0 | L82: =J82-K82 -> 0
B83: Veterinario | F83: =D83-E83 -> 0 | L83: =J83-K83 -> 0
B84: Juguetes | F84: =D84-E84 -> 0 | L84: =J84-K84 -> 0
B85: Medicinas | F85: =D85-E85 -> 0 | L85: =J85-K85 -> 0
F86: =D86-E86 -> 0 | L86: =J86-K86 -> 0
F87: =D87-E87 -> 0 | L87: =J87-K87 -> 0
B88: Subtotal | D88: =SUM(D82:D87) -> 0 | E88: =SUM(E82:E87) -> 0 | F88: =D88-E88 -> 0 | H88: Subtotal | J88: =SUM(J82:J87) -> 0 | K88: =SUM(K82:K87) -> 0 | L88: =J88-K88 -> 0
B90: OTROS | C90: Ahorro | D90: Presupuesto | E90: Gasto | F90: Disponible | H90: OTROS | I90: Ahorro | J90: Presupuesto | K90: Gasto | L90: Disponible
F91: =D91-E91 -> 0 | L91: =J91-K91 -> 0
F92: =D92-E92 -> 0 | L92: =J92-K92 -> 0
F93: =D93-E93 -> 0 | L93: =J93-K93 -> 0
F94: =D94-E94 -> 0 | L94: =J94-K94 -> 0
F95: =D95-E95 -> 0 | L95: =J95-K95 -> 0
F96: =D96-E96 -> 0 | L96: =J96-K96 -> 0
F97: =D97-E97 -> 0 | L97: =J97-K97 -> 0
B98: Subtotal | D98: =SUM(D91:D97) -> 0 | E98: =SUM(E91:E97) -> 0 | F98: =D98-E98 -> 0 | H98: Subtotal | J98: =SUM(J91:J97) -> 0 | K98: =SUM(K91:K97) -> 0 | L98: =J98-K98 -> 0
B100: OTROS | C100: Ahorro | D100: Presupuesto | E100: Gasto | F100: Disponible | H100: OTROS | I100: Ahorro | J100: Presupuesto | K100: Gasto | L100: Disponible
F101: =D101-E101 -> 0 | L101: =J101-K101 -> 0
F102: =D102-E102 -> 0 | L102: =J102-K102 -> 0
F103: =D103-E103 -> 0 | L103: =J103-K103 -> 0
F104: =D104-E104 -> 0 | L104: =J104-K104 -> 0
F105: =D105-E105 -> 0 | L105: =J105-K105 -> 0
F106: =D106-E106 -> 0 | L106: =J106-K106 -> 0
F107: =D107-E107 -> 0 | L107: =J107-K107 -> 0
B108: Subtotal | D108: =SUM(D101:D107) -> 0 | E108: =SUM(E101:E107) -> 0 | F108: =D108-E108 -> 0 | H108: Subtotal | J108: =SUM(J101:J107) -> 0 | K108: =SUM(K101:K107) -> 0 | L108: =J108-K108 -> 0

Sheet Para proyectar
U1: =B13 -> Arriendo/Hipoteca
B2: PRESUPUESTO MENSUAL
B4: Ingreso Estimado | C4: Salario | E4: 9714500
C5: saldo mes anterior
C6: Efectivo
C7: nequi
C10: Total Ingreso Mensual | E10: =SUM(E4:E9) -> 9714500 | H10: Balance (Ingreso vs Presupuesto) | K10: =E10-SUM(D25,D36,D55,D65,D79,D88,D98,J25,J36,J55,J65,J88,J98,D108,J108,D46,J46,J79) -> 956 | M10: =IF(K10=0,"El presupuesto está listo","OJO! Tiene que sumar cero") -> OJO! Tiene que sumar cero
B12: NECESIDADES BÁSICAS | C12: Ahorro | D12: Presupuesto | E12: Gasto | F12: Disponible | H12: AHORROS | I12: Ahorro | J12: Presupuesto | K12: Gasto | L12: Disponible
B13: Arriendo/Hipoteca | D13: 2000000 | E13: =SUMIFS('Enero - registro gastos'!$D$3:$D$300,'Enero - registro gastos'!$E$3:$E$300,Ene!$B$12,'Enero - registro gastos'!$F$3:$F$300,Ene!B13) -> 0 | F13: =D13-E13 -> 2000000 | H13: Efectivo | I13: SI | K13: =SUMIFS('Enero - registro gastos'!$D$3:$D$300,'Enero - registro gastos'!$E$3:$E$300,Ene!$H$12,'Enero - registro gastos'!$F$3:$F$300,Ene!H13) -> 0 | L13: =J13-K13 -> 0
B14: Telefono/ Celular | D14: 78000 | E14: =SUMIFS('Enero - registro gastos'!$D$3:$D$300,'Enero - registro gastos'!$E$3:$E$300,Ene!$B$12,'Enero - registro gastos'!$F$3:$F$300,Ene!B14) -> 77988 | F14: =D14-E14 -> 12 | H14: Cuenta Bancol | I14: SI | K14: =SUMIFS('Enero - registro gastos'!$D$3:$D$300,'Enero - registro gastos'!$E$3:$E$300,Ene!$H$12,'Enero - registro gastos'!$F$3:$F$300,Ene!H14) -> 0 | L14: =J14-K14 -> 0
B15: Electricidad | D15: 50000 | E15: =SUMIFS('Enero - registro gastos'!$D$3:$D$300,'Enero - registro gastos'!$E$3:$E$300,Ene!$B$12,'Enero - registro gastos'!$F$3:$F$300,Ene!B15) -> 0 | F15: =D15-E15 -> 50000 | H15: pension voluntaria ahorro casa | I15: SI | J15: =100000+1250000 -> 1350000 | K15: =SUMIFS('Enero - registro gastos'!$D$3:$D$300,'Enero - registro gastos'!$E$3:$E$300,Ene!$H$12,'Enero - registro gastos'!$F$3:$F$300,Ene!H15) -> 0 | L15: =J15-K15 -> 1350000
B16: Agua | D16: 50000 | E16: =SUMIFS('Enero - registro gastos'!$D$3:$D$300,'Enero - registro gastos'!$E$3:$E$300,Ene!$B$12,'Enero - registro gastos'!$F$3:$F$300,Ene!B16) -> 0 | F16: =D16-E16 -> 50000 | H16: Investor trust 1200 | I16: SI | J16: =100*Resumen!C2 -> 385000 | K16: =SUMIFS('Enero - registro gastos'!$D$3:$D$300,'Enero - registro gastos'!$E$3:$E$300,Ene!$H$12,'Enero - registro gastos'!$F$3:$F$300,Ene!H16) -> 0 | L16: =J16-K16 -> 385000
B17: Gas | D17: 15000 | E17: =SUMIFS('Enero - registro gastos'!$D$3:$D$300,'Enero - registro gastos'!$E$3:$E$300,Ene!$B$12,'Enero - registro gastos'!$F$3:$F$300,Ene!B17) -> 0 | F17: =D17-E17 -> 15000 | H17: Investor trust 2400 | I17: SI | J17: =200*Resumen!C2 -> 770000 | K17: =SUMIFS('Enero - registro gastos'!$D$3:$D$300,'Enero - registro gastos'!$E$3:$E$300,Ene!$H$12,'Enero - registro gastos'!$F$3:$F$300,Ene!H17) -> 0 | L17: =J17-K17 -> 770000
B18: Cable/Internet | D18: 140000 | E18: =SUMIFS('Enero - registro gastos'!$D$3:$D$300,'Enero - registro gastos'!$E$3:$E$300,Ene!$B$12,'Enero - registro gastos'!$F$3:$F$300,Ene!B18) -> 142988 | F18: =D18-E18 -> -2988 | H18: poliza pensiones skandia | I18: SI | J18: 336000 | K18: =SUMIFS('Enero - registro gastos'!$D$3:$D$300,'Enero - registro gastos'!$E$3:$E$300,Ene!$H$12,'Enero - registro gastos'!$F$3:$F$300,Ene!H18) -> 0 | L18: =J18-K18 -> 336000
B19: Super Mercado | D19: 300000 | E19: =SUMIFS('Enero - registro gastos'!$D$3:$D$300,'Enero - registro gastos'!$E$3:$E$300,Ene!$B$12,'Enero - registro gastos'!$F$3:$F$300,Ene!B19) -> 0 | F19: =D19-E19 -> 300000 | H19: Fondo de emergencia lulo | I19: SI | J19: 200000 | K19: =SUMIFS('Enero - registro gastos'!$D$3:$D$300,'Enero - registro gastos'!$E$3:$E$300,Ene!$H$12,'Enero - registro gastos'!$F$3:$F$300,Ene!H19) -> 0 | L19: =J19-K19 -> 200000
B20: Gasolina | D20: 200000 | E20: =SUMIFS('Enero - registro gastos'!$D$3:$D$300,'Enero - registro gastos'!$E$3:$E$300,Ene!$B$12,'Enero - registro gastos'!$F$3:$F$300,Ene!B20) -> 0 | F20: =D20-E20 -> 200000 | H20: Littio | I20: SI | J20: 500000 | K20: =SUMIFS('Enero - registro gastos'!$D$3:$D$300,'Enero - registro gastos'!$E$3:$E$300,Ene!$H$12,'Enero - registro gastos'!$F$3:$F$300,Ene!H20) -> 0 | L20: =J20-K20 -> 500000
B21: Bus | E21: =SUMIFS('Enero - registro gastos'!$D$3:$D$300,'Enero - registro gastos'!$E$3:$E$300,Ene!$B$12,'Enero - registro gastos'!$F$3:$F$300,Ene!B21) -> 0 | F21: =D21-E21 -> 0 | H21: Nequi | I21: SI | J21: 500000 | K21: =SUMIFS('Enero - registro gastos'!$D$3:$D$300,'Enero - registro gastos'!$E$3:$E$300,Ene!$H$12,'Enero - registro gastos'!$F$3:$F$300,Ene!H21) -> 0 | L21: =J21-K21 -> 500000
E22: =SUMIFS('Enero - registro gastos'!$D$3:$D$300,'Enero - registro gastos'!$E$3:$E$300,Ene!$B$12,'Enero - registro gastos'!$F$3:$F$300,Ene!B22) -> 0 | F22: =D22-E22 -> 0 | H22: viajes varios | I22: SI | K22: =SUMIFS('Enero - registro gastos'!$D$3:$D$300,'Enero - registro gastos'!$E$3:$E$300,Ene!$H$12,'Enero - registro gastos'!$F$3:$F$300,Ene!H22) -> 0 | L22: =J22-K22 -> 0
E23: =SUMIFS('Enero - registro gastos'!$D$3:$D$300,'Enero - registro gastos'!$E$3:$E$300,Ene!$B$12,'Enero - registro gastos'!$F$3:$F$300,Ene!B23) -> 0 | F23: =D23-E23 -> 0 | H23: Viaje Japon | I23: SI | J23: 1000000 | K23: =SUMIFS('Enero - registro gastos'!$D$3:$D$300,'Enero - registro gastos'!$E$3:$E$300,Ene!$H$12,'Enero - registro gastos'!$F$3:$F$300,Ene!H23) -> 0 | L23: =J23-K23 -> 1000000
E24: =SUMIFS('Enero - registro gastos'!$D$3:$D$300,'Enero - registro gastos'!$E$3:$E$300,Ene!$B$12,'Enero - registro gastos'!$F$3:$F$300,Ene!B24) -> 0 | F24: =D24-E24 -> 0 | K24: =SUMIFS('Enero - registro gastos'!$D$3:$D$300,'Enero - registro gastos'!$E$3:$E$300,Ene!$H$12,'Enero - registro gastos'!$F$3:$F$300,Ene!H24) -> 0 | L24: =J24-K24 -> 0
B25: Subtotal | D25: =SUM(D13:D24) -> 2833000 | E25: =SUM(E13:E24) -> 220976 | F25: =D25-E25 -> 2612024 | H25: Subtotal | J25: =SUM(J13:J24) -> 5041000 | K25: =SUM(K13:K24) -> 0 | L25: =J25-K25 -> 5041000
B27: DEUDAS | C27: Ahorro | D27: Presupuesto | E27: Gasto | F27: Disponible | H27: REGALOS/ CARIDAD | I27: Ahorro | J27: Presupuesto | K27: Gasto | L27: Disponible
B28: Deuda Carro | E28: =SUMIFS('Enero - registro gastos'!$D$3:$D$300,'Enero - registro gastos'!$E$3:$E$300,Ene!$B$27,'Enero - registro gastos'!$F$3:$F$300,Ene!B28) -> 0 | F28: =D28-E28 -> 0 | H28: Regalos Navidad | K28: =SUMIFS('Enero - registro gastos'!$D$3:$D$300,'Enero - registro gastos'!$E$3:$E$300,Ene!$H$27,'Enero - registro gastos'!$F$3:$F$300,Ene!H28) -> 0 | L28: =J28-K28 -> 0
B29: Deuda tarjeta Un | E29: =SUMIFS('Enero - registro gastos'!$D$3:$D$300,'Enero - registro gastos'!$E$3:$E$300,Ene!$B$27,'Enero - registro gastos'!$F$3:$F$300,Ene!B29) -> 3917064.8 | F29: =D29-E29 -> -3917064.8 | H29: Regalos cumpleaños | J29: 150000 | K29: =SUMIFS('Enero - registro gastos'!$D$3:$D$300,'Enero - registro gastos'!$E$3:$E$300,Ene!$H$27,'Enero - registro gastos'!$F$3:$F$300,Ene!H29) -> 0 | L29: =J29-K29 -> 150000
B30: Deuda Banco de occidente | E30: =SUMIFS('Enero - registro gastos'!$D$3:$D$300,'Enero - registro gastos'!$E$3:$E$300,Ene!$B$27,'Enero - registro gastos'!$F$3:$F$300,Ene!B30) -> 0 | F30: =D30-E30 -> 0 | H30: Caridad | J30: 55000 | K30: =SUMIFS('Enero - registro gastos'!$D$3:$D$300,'Enero - registro gastos'!$E$3:$E$300,Ene!$H$27,'Enero - registro gastos'!$F$3:$F$300,Ene!H30) -> 55000 | L30: =J30-K30 -> 0
B31: Deuda Estudio | E31: =SUMIFS('Enero - registro gastos'!$D$3:$D$300,'Enero - registro gastos'!$E$3:$E$300,Ene!$B$27,'Enero - registro gastos'!$F$3:$F$300,Ene!B31) -> 0 | F31: =D31-E31 -> 0 | K31: =SUMIFS('Enero - registro gastos'!$D$3:$D$300,'Enero - registro gastos'!$E$3:$E$300,Ene!$H$27,'Enero - registro gastos'!$F$3:$F$300,Ene!H31) -> 0 | L31: =J31-K31 -> 0
B32: Carro | E32: =SUMIFS('Enero - registro gastos'!$D$3:$D$300,'Enero - registro gastos'!$E$3:$E$300,Ene!$B$27,'Enero - registro gastos'!$F$3:$F$300,Ene!B32) -> 0 | F32: =D32-E32 -> 0 | K32: =SUMIFS('Enero - registro gastos'!$D$3:$D$300,'Enero - registro gastos'!$E$3:$E$300,Ene!$H$27,'Enero - registro gastos'!$F$3:$F$300,Ene!H32) -> 0 | L32: =J32-K32 -> 0
E33: =SUMIFS('Enero - registro gastos'!$D$3:$D$300,'Enero - registro gastos'!$E$3:$E$300,Ene!$B$27,'Enero - registro gastos'!$F$3:$F$300,Ene!B33) -> 0 | F33: =D33-E33 -> 0 | K33: =SUMIFS('Enero - registro gastos'!$D$3:$D$300,'Enero - registro gastos'!$E$3:$E$300,Ene!$H$27,'Enero - registro gastos'!$F$3:$F$300,Ene!H33) -> 0 | L33: =J33-K33 -> 0
E34: =SUMIFS('Enero - registro gastos'!$D$3:$D$300,'Enero - registro gastos'!$E$3:$E$300,Ene!$B$27,'Enero - registro gastos'!$F$3:$F$300,Ene!B34) -> 0 | F34: =D34-E34 -> 0 | K34: =SUMIFS('Enero - registro gastos'!$D$3:$D$300,'Enero - registro gastos'!$E$3:$E$300,Ene!$H$27,'Enero - registro gastos'!$F$3:$F$300,Ene!H34) -> 0 | L34: =J34-K34 -> 0
E35: =SUMIFS('Enero - registro gastos'!$D$3:$D$300,'Enero - registro gastos'!$E$3:$E$300,Ene!$B$27,'Enero - registro gastos'!$F$3:$F$300,Ene!B35) -> 0 | F35: =D35-E35 -> 0 | K35: =SUMIFS('Enero - registro gastos'!$D$3:$D$300,'Enero - registro gastos'!$E$3:$E$300,Ene!$H$27,'Enero - registro gastos'!$F$3:$F$300,Ene!H35) -> 0 | L35: =J35-K35 -> 0
B36: Subtotal | D36: =SUM(D28:D35) -> 0 | E36: =SUM(E28:E35) -> 3917064.8 | F36: =D36-E36 -> -3917064.8 | H36: Subtotal | J36: =SUM(J28:J35) -> 205000 | K36: =SUM(K28:K35) -> 55000 | L36: =J36-K36 -> 150000
B38: CASA | C38: Ahorro | D38: Presupuesto | E38: Gasto | F38: Disponible | H38: TRANSPORTE | I38: Ahorro | J38: Presupuesto | K38: Gasto | L38: Disponible
B39: Limpieza | E39: =SUMIFS('Enero - registro gastos'!$D$3:$D$300,'Enero - registro gastos'!$E$3:$E$300,Ene!$B$38,'Enero - registro gastos'!$F$3:$F$300,Ene!B39) -> 0 | F39: =D39-E39 -> 0 | H39: Uber/taxi | J39: 95000 | K39: =SUMIFS('Enero - registro gastos'!$D$3:$D$300,'Enero - registro gastos'!$E$3:$E$300,Ene!$H$38,'Enero - registro gastos'!$F$3:$F$300,Ene!H39) -> 0 | L39: =J39-K39 -> 95000
B40: Mantenimiento | E40: =SUMIFS('Enero - registro gastos'!$D$3:$D$300,'Enero - registro gastos'!$E$3:$E$300,Ene!$B$38,'Enero - registro gastos'!$F$3:$F$300,Ene!B40) -> 0 | F40: =D40-E40 -> 0 | H40: Estacionamiento | K40: =SUMIFS('Enero - registro gastos'!$D$3:$D$300,'Enero - registro gastos'!$E$3:$E$300,Ene!$H$38,'Enero - registro gastos'!$F$3:$F$300,Ene!H40) -> 0 | L40: =J40-K40 -> 0
B41: Muebles | E41: =SUMIFS('Enero - registro gastos'!$D$3:$D$300,'Enero - registro gastos'!$E$3:$E$300,Ene!$B$38,'Enero - registro gastos'!$F$3:$F$300,Ene!B41) -> 0 | F41: =D41-E41 -> 0 | H41: Mantenimiento | K41: =SUMIFS('Enero - registro gastos'!$D$3:$D$300,'Enero - registro gastos'!$E$3:$E$300,Ene!$H$38,'Enero - registro gastos'!$F$3:$F$300,Ene!H41) -> 0 | L41: =J41-K41 -> 0
B42: Impuestos | E42: =SUMIFS('Enero - registro gastos'!$D$3:$D$300,'Enero - registro gastos'!$E$3:$E$300,Ene!$B$38,'Enero - registro gastos'!$F$3:$F$300,Ene!B42) -> 0 | F42: =D42-E42 -> 0 | H42: Impuestos | K42: =SUMIFS('Enero - registro gastos'!$D$3:$D$300,'Enero - registro gastos'!$E$3:$E$300,Ene!$H$38,'Enero - registro gastos'!$F$3:$F$300,Ene!H42) -> 0 | L42: =J42-K42 -> 0
E43: =SUMIFS('Enero - registro gastos'!$D$3:$D$300,'Enero - registro gastos'!$E$3:$E$300,Ene!$B$38,'Enero - registro gastos'!$F$3:$F$300,Ene!B43) -> 0 | F43: =D43-E43 -> 0 | H43: Panapass/Peaje | J43: 20000 | K43: =SUMIFS('Enero - registro gastos'!$D$3:$D$300,'Enero - registro gastos'!$E$3:$E$300,Ene!$H$38,'Enero - registro gastos'!$F$3:$F$300,Ene!H43) -> 0 | L43: =J43-K43 -> 20000
E44: =SUMIFS('Enero - registro gastos'!$D$3:$D$300,'Enero - registro gastos'!$E$3:$E$300,Ene!$B$38,'Enero - registro gastos'!$F$3:$F$300,Ene!B44) -> 0 | F44: =D44-E44 -> 0 | K44: =SUMIFS('Enero - registro gastos'!$D$3:$D$300,'Enero - registro gastos'!$E$3:$E$300,Ene!$H$38,'Enero - registro gastos'!$F$3:$F$300,Ene!H44) -> 0 | L44: =J44-K44 -> 0
E45: =SUMIFS('Enero - registro gastos'!$D$3:$D$300,'Enero - registro gastos'!$E$3:$E$300,Ene!$B$38,'Enero - registro gastos'!$F$3:$F$300,Ene!B45) -> 0 | F45: =D45-E45 -> 0 | K45: =SUMIFS('Enero - registro gastos'!$D$3:$D$300,'Enero - registro gastos'!$E$3:$E$300,Ene!$H$38,'Enero - registro gastos'!$F$3:$F$300,Ene!H45) -> 0 | L45: =J45-K45 -> 0
B46: Subtotal | D46: =SUM(D39:D45) -> 0 | E46: =SUM(E39:E45) -> 0 | F46: =D46-E46 -> 0 | H46: Subtotal | J46: =SUM(J39:J45) -> 115000 | K46: =SUM(K39:K45) -> 0 | L46: =J46-K46 -> 115000
B48: ALIMENTACIÓN | C48: Ahorro | D48: Presupuesto | E48: Gasto | F48: Disponible | H48: SEGUROS | I48: Ahorro | J48: Presupuesto | K48: Gasto | L48: Disponible
B49: Restaurantes | D49: 400000 | E49: =SUMIFS('Enero - registro gastos'!$D$3:$D$300,'Enero - registro gastos'!$E$3:$E$300,Ene!$B$48,'Enero - registro gastos'!$F$3:$F$300,Ene!B49) -> 150890 | F49: =D49-E49 -> 249110 | H49: Carro | K49: =SUMIFS('Enero - registro gastos'!$D$3:$D$300,'Enero - registro gastos'!$E$3:$E$300,Ene!$H$48,'Enero - registro gastos'!$F$3:$F$300,Ene!H49) -> 0 | L49: =J49-K49 -> 0
B50: Café/ Snacks | D50: 250000 | E50: =SUMIFS('Enero - registro gastos'!$D$3:$D$300,'Enero - registro gastos'!$E$3:$E$300,Ene!$B$48,'Enero - registro gastos'!$F$3:$F$300,Ene!B50) -> 0 | F50: =D50-E50 -> 250000 | H50: Vida | K50: =SUMIFS('Enero - registro gastos'!$D$3:$D$300,'Enero - registro gastos'!$E$3:$E$300,Ene!$H$48,'Enero - registro gastos'!$F$3:$F$300,Ene!H50) -> 0 | L50: =J50-K50 -> 0
B51: Rappi | D51: 300000 | E51: =SUMIFS('Enero - registro gastos'!$D$3:$D$300,'Enero - registro gastos'!$E$3:$E$300,Ene!$B$48,'Enero - registro gastos'!$F$3:$F$300,Ene!B51) -> 28650 | F51: =D51-E51 -> 271350 | H51: Casa | K51: =SUMIFS('Enero - registro gastos'!$D$3:$D$300,'Enero - registro gastos'!$E$3:$E$300,Ene!$H$48,'Enero - registro gastos'!$F$3:$F$300,Ene!H51) -> 0 | L51: =J51-K51 -> 0
E52: =SUMIFS('Enero - registro gastos'!$D$3:$D$300,'Enero - registro gastos'!$E$3:$E$300,Ene!$B$48,'Enero - registro gastos'!$F$3:$F$300,Ene!B52) -> 0 | F52: =D52-E52 -> 0 | H52: Salud | K52: =SUMIFS('Enero - registro gastos'!$D$3:$D$300,'Enero - registro gastos'!$E$3:$E$300,Ene!$H$48,'Enero - registro gastos'!$F$3:$F$300,Ene!H52) -> 0 | L52: =J52-K52 -> 0
E53: =SUMIFS('Enero - registro gastos'!$D$3:$D$300,'Enero - registro gastos'!$E$3:$E$300,Ene!$B$48,'Enero - registro gastos'!$F$3:$F$300,Ene!B53) -> 0 | F53: =D53-E53 -> 0 | K53: =SUMIFS('Enero - registro gastos'!$D$3:$D$300,'Enero - registro gastos'!$E$3:$E$300,Ene!$H$48,'Enero - registro gastos'!$F$3:$F$300,Ene!H53) -> 0 | L53: =J53-K53 -> 0
E54: =SUMIFS('Enero - registro gastos'!$D$3:$D$300,'Enero - registro gastos'!$E$3:$E$300,Ene!$B$48,'Enero - registro gastos'!$F$3:$F$300,Ene!B54) -> 0 | F54: =D54-E54 -> 0 | K54: =SUMIFS('Enero - registro gastos'!$D$3:$D$300,'Enero - registro gastos'!$E$3:$E$300,Ene!$H$48,'Enero - registro gastos'!$F$3:$F$300,Ene!H54) -> 0 | L54: =J54-K54 -> 0
B55: Subtotal | D55: =SUM(D49:D54) -> 950000 | E55: =SUM(E49:E54) -> 179540 | F55: =D55-E55 -> 770460 | H55: Subtotal | J55: =SUM(J49:J54) -> 0 | K55: =SUM(K49:K54) -> 0 | L55: =J55-K55 -> 0
B57: SALUD | C57: Ahorro | D57: Presupuesto | E57: Gasto | F57: Disponible | H57: CUIDADO PERSONAL | I57: Ahorro | J57: Presupuesto | K57: Gasto | L57: Disponible
B58: Medicinas | D58: 80000 | E58: =SUMIFS('Enero - registro gastos'!$D$3:$D$300,'Enero - registro gastos'!$E$3:$E$300,Ene!$B$57,'Enero - registro gastos'!$F$3:$F$300,Ene!B58) -> 0 | F58: =D58-E58 -> 80000 | H58: Ropa | K58: =SUMIFS('Enero - registro gastos'!$D$3:$D$300,'Enero - registro gastos'!$E$3:$E$300,Ene!$H$57,'Enero - registro gastos'!$F$3:$F$300,Ene!H58) -> 0 | L58: =J58-K58 -> 0
B59: Dentista | E59: =SUMIFS('Enero - registro gastos'!$D$3:$D$300,'Enero - registro gastos'!$E$3:$E$300,Ene!$B$57,'Enero - registro gastos'!$F$3:$F$300,Ene!B59) -> 0 | F59: =D59-E59 -> 0 | H59: Belleza | K59: =SUMIFS('Enero - registro gastos'!$D$3:$D$300,'Enero - registro gastos'!$E$3:$E$300,Ene!$H$57,'Enero - registro gastos'!$F$3:$F$300,Ene!H59) -> 0 | L59: =J59-K59 -> 0
B60: Tratamientos | E60: =SUMIFS('Enero - registro gastos'!$D$3:$D$300,'Enero - registro gastos'!$E$3:$E$300,Ene!$B$57,'Enero - registro gastos'!$F$3:$F$300,Ene!B60) -> 0 | F60: =D60-E60 -> 0 | H60: Peluquería | K60: =SUMIFS('Enero - registro gastos'!$D$3:$D$300,'Enero - registro gastos'!$E$3:$E$300,Ene!$H$57,'Enero - registro gastos'!$F$3:$F$300,Ene!H60) -> 0 | L60: =J60-K60 -> 0
E61: =SUMIFS('Enero - registro gastos'!$D$3:$D$300,'Enero - registro gastos'!$E$3:$E$300,Ene!$B$57,'Enero - registro gastos'!$F$3:$F$300,Ene!B61) -> 0 | F61: =D61-E61 -> 0 | H61: Sastre | K61: =SUMIFS('Enero - registro gastos'!$D$3:$D$300,'Enero - registro gastos'!$E$3:$E$300,Ene!$H$57,'Enero - registro gastos'!$F$3:$F$300,Ene!H61) -> 0 | L61: =J61-K61 -> 0
E62: =SUMIFS('Enero - registro gastos'!$D$3:$D$300,'Enero - registro gastos'!$E$3:$E$300,Ene!$B$57,'Enero - registro gastos'!$F$3:$F$300,Ene!B62) -> 0 | F62: =D62-E62 -> 0 | H62: Tintorería | K62: =SUMIFS('Enero - registro gastos'!$D$3:$D$300,'Enero - registro gastos'!$E$3:$E$300,Ene!$H$57,'Enero - registro gastos'!$F$3:$F$300,Ene!H62) -> 0 | L62: =J62-K62 -> 0
E63: =SUMIFS('Enero - registro gastos'!$D$3:$D$300,'Enero - registro gastos'!$E$3:$E$300,Ene!$B$57,'Enero - registro gastos'!$F$3:$F$300,Ene!B63) -> 0 | F63: =D63-E63 -> 0 | K63: =SUMIFS('Enero - registro gastos'!$D$3:$D$300,'Enero - registro gastos'!$E$3:$E$300,Ene!$H$57,'Enero - registro gastos'!$F$3:$F$300,Ene!H63) -> 0 | L63: =J63-K63 -> 0
E64: =SUMIFS('Enero - registro gastos'!$D$3:$D$300,'Enero - registro gastos'!$E$3:$E$300,Ene!$B$57,'Enero - registro gastos'!$F$3:$F$300,Ene!B64) -> 0 | F64: =D64-E64 -> 0 | K64: =SUMIFS('Enero - registro gastos'!$D$3:$D$300,'Enero - registro gastos'!$E$3:$E$300,Ene!$H$57,'Enero - registro gastos'!$F$3:$F$300,Ene!H64) -> 0 | L64: =J64-K64 -> 0
B65: Subtotal | D65: =SUM(D58:D64) -> 80000 | E65: =SUM(E58:E64) -> 0 | F65: =D65-E65 -> 80000 | H65: Subtotal | J65: =SUM(J58:J64) -> 0 | K65: =SUM(K58:K64) -> 0 | L65: =J65-K65 -> 0
B67: ENTRETENIMIENTO | C67: Ahorro | D67: Presupuesto | E67: Gasto | F67: Disponible | H67: HIJOS | I67: Ahorro | J67: Presupuesto | K67: Gasto | L67: Diferencia
B68: Vacaciones | E68: =SUMIFS('Enero - registro gastos'!$D$3:$D$300,'Enero - registro gastos'!$E$3:$E$300,Ene!$B$67,'Enero - registro gastos'!$F$3:$F$300,Ene!B68) -> 0 | F68: =D68-E68 -> 0 | H68: Ropa | K68: =SUMIFS('Enero - registro gastos'!$D$3:$D$300,'Enero - registro gastos'!$E$3:$E$300,Ene!$H$67,'Enero - registro gastos'!$F$3:$F$300,Ene!H68) -> 0 | L68: =J68-K68 -> 0
B69: Rumba | E69: =SUMIFS('Enero - registro gastos'!$D$3:$D$300,'Enero - registro gastos'!$E$3:$E$300,Ene!$B$67,'Enero - registro gastos'!$F$3:$F$300,Ene!B69) -> 0 | F69: =D69-E69 -> 0 | H69: Estudio | K69: =SUMIFS('Enero - registro gastos'!$D$3:$D$300,'Enero - registro gastos'!$E$3:$E$300,Ene!$H$67,'Enero - registro gastos'!$F$3:$F$300,Ene!H69) -> 0 | L69: =J69-K69 -> 0
B70: Citas | E70: =SUMIFS('Enero - registro gastos'!$D$3:$D$300,'Enero - registro gastos'!$E$3:$E$300,Ene!$B$67,'Enero - registro gastos'!$F$3:$F$300,Ene!B70) -> 0 | F70: =D70-E70 -> 0 | H70: Utiles Escolares | K70: =SUMIFS('Enero - registro gastos'!$D$3:$D$300,'Enero - registro gastos'!$E$3:$E$300,Ene!$H$67,'Enero - registro gastos'!$F$3:$F$300,Ene!H70) -> 0 | L70: =J70-K70 -> 0
B71: Cine | E71: =SUMIFS('Enero - registro gastos'!$D$3:$D$300,'Enero - registro gastos'!$E$3:$E$300,Ene!$B$67,'Enero - registro gastos'!$F$3:$F$300,Ene!B71) -> 244000 | F71: =D71-E71 -> -244000 | H71: Niñera | K71: =SUMIFS('Enero - registro gastos'!$D$3:$D$300,'Enero - registro gastos'!$E$3:$E$300,Ene!$H$67,'Enero - registro gastos'!$F$3:$F$300,Ene!H71) -> 0 | L71: =J71-K71 -> 0
B72: Deporte | D72: 150906 | E72: =SUMIFS('Enero - registro gastos'!$D$3:$D$300,'Enero - registro gastos'!$E$3:$E$300,Ene!$B$67,'Enero - registro gastos'!$F$3:$F$300,Ene!B72) -> 148241.73 | F72: =D72-E72 -> 2664.27 | K72: =SUMIFS('Enero - registro gastos'!$D$3:$D$300,'Enero - registro gastos'!$E$3:$E$300,Ene!$H$67,'Enero - registro gastos'!$F$3:$F$300,Ene!H72) -> 0 | L72: =J72-K72 -> 0
B73: Netflix | D73: 45000 | E73: =SUMIFS('Enero - registro gastos'!$D$3:$D$300,'Enero - registro gastos'!$E$3:$E$300,Ene!$B$67,'Enero - registro gastos'!$F$3:$F$300,Ene!B73) -> 44900 | F73: =D73-E73 -> 100 | K73: =SUMIFS('Enero - registro gastos'!$D$3:$D$300,'Enero - registro gastos'!$E$3:$E$300,Ene!$H$67,'Enero - registro gastos'!$F$3:$F$300,Ene!H73) -> 0 | L73: =J73-K73 -> 0
B74: Spotify | D74: 30500 | E74: =SUMIFS('Enero - registro gastos'!$D$3:$D$300,'Enero - registro gastos'!$E$3:$E$300,Ene!$B$67,'Enero - registro gastos'!$F$3:$F$300,Ene!B74) -> 0 | F74: =D74-E74 -> 30500 | K74: =SUMIFS('Enero - registro gastos'!$D$3:$D$300,'Enero - registro gastos'!$E$3:$E$300,Ene!$H$67,'Enero - registro gastos'!$F$3:$F$300,Ene!H74) -> 0 | L74: =J74-K74 -> 0
B75: google | D75: 9000 | E75: =SUMIFS('Enero - registro gastos'!$D$3:$D$300,'Enero - registro gastos'!$E$3:$E$300,Ene!$B$67,'Enero - registro gastos'!$F$3:$F$300,Ene!B75) -> 0 | F75: =D75-E75 -> 9000 | K75: =SUMIFS('Enero - registro gastos'!$D$3:$D$300,'Enero - registro gastos'!$E$3:$E$300,Ene!$H$67,'Enero - registro gastos'!$F$3:$F$300,Ene!H75) -> 0 | L75: =J75-K75 -> 0
E76: =SUMIFS('Enero - registro gastos'!$D$3:$D$300,'Enero - registro gastos'!$E$3:$E$300,Ene!$B$67,'Enero - registro gastos'!$F$3:$F$300,Ene!B76) -> 14950 | F76: =D76-E76 -> -14950 | K76: =SUMIFS('Enero - registro gastos'!$D$3:$D$300,'Enero - registro gastos'!$E$3:$E$300,Ene!$H$67,'Enero - registro gastos'!$F$3:$F$300,Ene!H76) -> 0 | L76: =J76-K76 -> 0
E77: =SUMIFS('Enero - registro gastos'!$D$3:$D$300,'Enero - registro gastos'!$E$3:$E$300,Ene!$B$67,'Enero - registro gastos'!$F$3:$F$300,Ene!B77) -> 12900 | F77: =D77-E77 -> -12900 | K77: =SUMIFS('Enero - registro gastos'!$D$3:$D$300,'Enero - registro gastos'!$E$3:$E$300,Ene!$H$67,'Enero - registro gastos'!$F$3:$F$300,Ene!H77) -> 0 | L77: =J77-K77 -> 0
E78: =SUMIFS('Enero - registro gastos'!$D$3:$D$300,'Enero - registro gastos'!$E$3:$E$300,Ene!$B$67,'Enero - registro gastos'!$F$3:$F$300,Ene!B78) -> 0 | F78: =D78-E78 -> 0 | K78: =SUMIFS('Enero - registro gastos'!$D$3:$D$300,'Enero - registro gastos'!$E$3:$E$300,Ene!$H$67,'Enero - registro gastos'!$F$3:$F$300,Ene!H78) -> 0 | L78: =J78-K78 -> 0
B79: Subtotal | D79: =SUM(D68:D78) -> 235406 | E79: =SUM(E68:E78) -> 464991.73 | F79: =D79-E79 -> -229585.73 | H79: Subtotal | J79: =SUM(J68:J78) -> 0 | K79: =SUM(K68:K78) -> 0 | L79: =J79-K79 -> 0
B81: MASCOTA | C81: Ahorro | D81: Presupuesto | E81: Gasto | F81: Disponible | H81: OTROS 1 | I81: Ahorro | J81: Presupuesto | K81: Gasto | L81: Disponible
B82: Comida | E82: =SUMIFS('Enero - registro gastos'!$D$3:$D$300,'Enero - registro gastos'!$E$3:$E$300,Ene!$B$81,'Enero - registro gastos'!$F$3:$F$300,Ene!B82) -> 0 | F82: =D82-E82 -> 0 | K82: =SUMIFS('Enero - registro gastos'!$D$3:$D$300,'Enero - registro gastos'!$E$3:$E$300,Ene!$H$81,'Enero - registro gastos'!$F$3:$F$300,Ene!H82) -> 0 | L82: =J82-K82 -> 0
B83: Veterinario | E83: =SUMIFS('Enero - registro gastos'!$D$3:$D$300,'Enero - registro gastos'!$E$3:$E$300,Ene!$B$81,'Enero - registro gastos'!$F$3:$F$300,Ene!B83) -> 0 | F83: =D83-E83 -> 0 | K83: =SUMIFS('Enero - registro gastos'!$D$3:$D$300,'Enero - registro gastos'!$E$3:$E$300,Ene!$H$81,'Enero - registro gastos'!$F$3:$F$300,Ene!H83) -> 0 | L83: =J83-K83 -> 0
B84: Juguetes | E84: =SUMIFS('Enero - registro gastos'!$D$3:$D$300,'Enero - registro gastos'!$E$3:$E$300,Ene!$B$81,'Enero - registro gastos'!$F$3:$F$300,Ene!B84) -> 0 | F84: =D84-E84 -> 0 | K84: =SUMIFS('Enero - registro gastos'!$D$3:$D$300,'Enero - registro gastos'!$E$3:$E$300,Ene!$H$81,'Enero - registro gastos'!$F$3:$F$300,Ene!H84) -> 0 | L84: =J84-K84 -> 0
B85: Medicinas | E85: =SUMIFS('Enero - registro gastos'!$D$3:$D$300,'Enero - registro gastos'!$E$3:$E$300,Ene!$B$81,'Enero - registro gastos'!$F$3:$F$300,Ene!B85) -> 0 | F85: =D85-E85 -> 0 | K85: =SUMIFS('Enero - registro gastos'!$D$3:$D$300,'Enero - registro gastos'!$E$3:$E$300,Ene!$H$81,'Enero - registro gastos'!$F$3:$F$300,Ene!H85) -> 0 | L85: =J85-K85 -> 0
E86: =SUMIFS('Enero - registro gastos'!$D$3:$D$300,'Enero - registro gastos'!$E$3:$E$300,Ene!$B$81,'Enero - registro gastos'!$F$3:$F$300,Ene!B86) -> 0 | F86: =D86-E86 -> 0 | K86: =SUMIFS('Enero - registro gastos'!$D$3:$D$300,'Enero - registro gastos'!$E$3:$E$300,Ene!$H$81,'Enero - registro gastos'!$F$3:$F$300,Ene!H86) -> 0 | L86: =J86-K86 -> 0
E87: =SUMIFS('Enero - registro gastos'!$D$3:$D$300,'Enero - registro gastos'!$E$3:$E$300,Ene!$B$81,'Enero - registro gastos'!$F$3:$F$300,Ene!B87) -> 0 | F87: =D87-E87 -> 0 | K87: =SUMIFS('Enero - registro gastos'!$D$3:$D$300,'Enero - registro gastos'!$E$3:$E$300,Ene!$H$81,'Enero - registro gastos'!$F$3:$F$300,Ene!H87) -> 0 | L87: =J87-K87 -> 0
B88: Subtotal | D88: =SUM(D82:D87) -> 0 | E88: =SUM(E82:E87) -> 0 | F88: =D88-E88 -> 0 | H88: Subtotal | J88: =SUM(J82:J87) -> 0 | K88: =SUM(K82:K87) -> 0 | L88: =J88-K88 -> 0
B90: OTROS 2 | C90: Ahorro | D90: Presupuesto | E90: Gasto | F90: Disponible | H90: OTROS 3 | I90: Ahorro | J90: Presupuesto | K90: Gasto | L90: Disponible
B91: OPENAI | D91: 74138 | E91: =SUMIFS('Enero - registro gastos'!$D$3:$D$300,'Enero - registro gastos'!$E$3:$E$300,Ene!$B$90,'Enero - registro gastos'!$F$3:$F$300,Ene!B91) -> 0 | F91: =D91-E91 -> 74138 | K91: =SUMIFS('Enero - registro gastos'!$D$3:$D$300,'Enero - registro gastos'!$E$3:$E$300,Ene!$H$90,'Enero - registro gastos'!$F$3:$F$300,Ene!H91) -> 0 | L91: =J91-K91 -> 0
B92: clases de canto | D92: =45000*4 -> 180000 | E92: =SUMIFS('Enero - registro gastos'!$D$3:$D$300,'Enero - registro gastos'!$E$3:$E$300,Ene!$B$90,'Enero - registro gastos'!$F$3:$F$300,Ene!B92) -> 0 | F92: =D92-E92 -> 180000 | K92: =SUMIFS('Enero - registro gastos'!$D$3:$D$300,'Enero - registro gastos'!$E$3:$E$300,Ene!$H$90,'Enero - registro gastos'!$F$3:$F$300,Ene!H92) -> 0 | L92: =J92-K92 -> 0
E93: =SUMIFS('Enero - registro gastos'!$D$3:$D$300,'Enero - registro gastos'!$E$3:$E$300,Ene!$B$90,'Enero - registro gastos'!$F$3:$F$300,Ene!B93) -> 0 | F93: =D93-E93 -> 0 | K93: =SUMIFS('Enero - registro gastos'!$D$3:$D$300,'Enero - registro gastos'!$E$3:$E$300,Ene!$H$90,'Enero - registro gastos'!$F$3:$F$300,Ene!H93) -> 0 | L93: =J93-K93 -> 0
E94: =SUMIFS('Enero - registro gastos'!$D$3:$D$300,'Enero - registro gastos'!$E$3:$E$300,Ene!$B$90,'Enero - registro gastos'!$F$3:$F$300,Ene!B94) -> 0 | F94: =D94-E94 -> 0 | K94: =SUMIFS('Enero - registro gastos'!$D$3:$D$300,'Enero - registro gastos'!$E$3:$E$300,Ene!$H$90,'Enero - registro gastos'!$F$3:$F$300,Ene!H94) -> 0 | L94: =J94-K94 -> 0
E95: =SUMIFS('Enero - registro gastos'!$D$3:$D$300,'Enero - registro gastos'!$E$3:$E$300,Ene!$B$90,'Enero - registro gastos'!$F$3:$F$300,Ene!B95) -> 0 | F95: =D95-E95 -> 0 | K95: =SUMIFS('Enero - registro gastos'!$D$3:$D$300,'Enero - registro gastos'!$E$3:$E$300,Ene!$H$90,'Enero - registro gastos'!$F$3:$F$300,Ene!H95) -> 0 | L95: =J95-K95 -> 0
E96: =SUMIFS('Enero - registro gastos'!$D$3:$D$300,'Enero - registro gastos'!$E$3:$E$300,Ene!$B$90,'Enero - registro gastos'!$F$3:$F$300,Ene!B96) -> 0 | F96: =D96-E96 -> 0 | K96: =SUMIFS('Enero - registro gastos'!$D$3:$D$300,'Enero - registro gastos'!$E$3:$E$300,Ene!$H$90,'Enero - registro gastos'!$F$3:$F$300,Ene!H96) -> 0 | L96: =J96-K96 -> 0
E97: =SUMIFS('Enero - registro gastos'!$D$3:$D$300,'Enero - registro gastos'!$E$3:$E$300,Ene!$B$90,'Enero - registro gastos'!$F$3:$F$300,Ene!B97) -> 0 | F97: =D97-E97 -> 0 | K97: =SUMIFS('Enero - registro gastos'!$D$3:$D$300,'Enero - registro gastos'!$E$3:$E$300,Ene!$H$90,'Enero - registro gastos'!$F$3:$F$300,Ene!H97) -> 0 | L97: =J97-K97 -> 0
B98: Subtotal | D98: =SUM(D91:D97) -> 254138 | E98: =SUM(E91:E97) -> 0 | F98: =D98-E98 -> 254138 | H98: Subtotal | J98: =SUM(J91:J97) -> 0 | K98: =SUM(K91:K97) -> 0 | L98: =J98-K98 -> 0
B100: OTROS 4 | C100: Ahorro | D100: Presupuesto | E100: Gasto | F100: Disponible | H100: OTROS 5 | I100: Ahorro | J100: Presupuesto | K100: Gasto | L100: Disponible
E101: =SUMIFS('Enero - registro gastos'!$D$3:$D$300,'Enero - registro gastos'!$E$3:$E$300,Ene!$B$100,'Enero - registro gastos'!$F$3:$F$300,Ene!B101) -> 0 | F101: =D101-E101 -> 0 | K101: =SUMIFS('Enero - registro gastos'!$D$3:$D$300,'Enero - registro gastos'!$E$3:$E$300,Ene!$H$100,'Enero - registro gastos'!$F$3:$F$300,Ene!H101) -> 0 | L101: =J101-K101 -> 0
E102: =SUMIFS('Enero - registro gastos'!$D$3:$D$300,'Enero - registro gastos'!$E$3:$E$300,Ene!$B$100,'Enero - registro gastos'!$F$3:$F$300,Ene!B102) -> 0 | F102: =D102-E102 -> 0 | K102: =SUMIFS('Enero - registro gastos'!$D$3:$D$300,'Enero - registro gastos'!$E$3:$E$300,Ene!$H$100,'Enero - registro gastos'!$F$3:$F$300,Ene!H102) -> 0 | L102: =J102-K102 -> 0
E103: =SUMIFS('Enero - registro gastos'!$D$3:$D$300,'Enero - registro gastos'!$E$3:$E$300,Ene!$B$100,'Enero - registro gastos'!$F$3:$F$300,Ene!B103) -> 0 | F103: =D103-E103 -> 0 | K103: =SUMIFS('Enero - registro gastos'!$D$3:$D$300,'Enero - registro gastos'!$E$3:$E$300,Ene!$H$100,'Enero - registro gastos'!$F$3:$F$300,Ene!H103) -> 0 | L103: =J103-K103 -> 0
E104: =SUMIFS('Enero - registro gastos'!$D$3:$D$300,'Enero - registro gastos'!$E$3:$E$300,Ene!$B$100,'Enero - registro gastos'!$F$3:$F$300,Ene!B104) -> 0 | F104: =D104-E104 -> 0 | K104: =SUMIFS('Enero - registro gastos'!$D$3:$D$300,'Enero - registro gastos'!$E$3:$E$300,Ene!$H$100,'Enero - registro gastos'!$F$3:$F$300,Ene!H104) -> 0 | L104: =J104-K104 -> 0
E105: =SUMIFS('Enero - registro gastos'!$D$3:$D$300,'Enero - registro gastos'!$E$3:$E$300,Ene!$B$100,'Enero - registro gastos'!$F$3:$F$300,Ene!B105) -> 0 | F105: =D105-E105 -> 0 | K105: =SUMIFS('Enero - registro gastos'!$D$3:$D$300,'Enero - registro gastos'!$E$3:$E$300,Ene!$H$100,'Enero - registro gastos'!$F$3:$F$300,Ene!H105) -> 0 | L105: =J105-K105 -> 0
E106: =SUMIFS('Enero - registro gastos'!$D$3:$D$300,'Enero - registro gastos'!$E$3:$E$300,Ene!$B$100,'Enero - registro gastos'!$F$3:$F$300,Ene!B106) -> 0 | F106: =D106-E106 -> 0 | K106: =SUMIFS('Enero - registro gastos'!$D$3:$D$300,'Enero - registro gastos'!$E$3:$E$300,Ene!$H$100,'Enero - registro gastos'!$F$3:$F$300,Ene!H106) -> 0 | L106: =J106-K106 -> 0
E107: =SUMIFS('Enero - registro gastos'!$D$3:$D$300,'Enero - registro gastos'!$E$3:$E$300,Ene!$B$100,'Enero - registro gastos'!$F$3:$F$300,Ene!B107) -> 0 | F107: =D107-E107 -> 0 | K107: =SUMIFS('Enero - registro gastos'!$D$3:$D$300,'Enero - registro gastos'!$E$3:$E$300,Ene!$H$100,'Enero - registro gastos'!$F$3:$F$300,Ene!H107) -> 0 | L107: =J107-K107 -> 0
B108: Subtotal | D108: =SUM(D101:D107) -> 0 | E108: =SUM(E101:E107) -> 0 | F108: =D108-E108 -> 0 | H108: Subtotal | J108: =SUM(J101:J107) -> 0 | K108: =SUM(K101:K107) -> 0 | L108: =J108-K108 -> 0

Sheet Limpieza
U1: =B13 -> Arriendo/Hipoteca
B2: PRESUPUESTO MENSUAL
B4: Ingreso Estimado | E4: =185403671+2619683.99 -> 1.8802335e+08
C10: Total Ingreso Mensual | E10: =SUM(E4:E9) -> 1.8802335e+08 | H10: Balance (Ingreso vs Presupuesto) | K10: =E10-SUM(D25,D36,D55,D65,D79,D88,D98,J25,J36,J55,J65,J88,J98,D108,J108,D46,J46,J79) -> 6151674 | M10: =IF(K10=0,"El presupuesto está listo","OJO! Tiene que sumar cero") -> OJO! Tiene que sumar cero
B12: NECESIDADES BÁSICAS | C12: Ahorro | D12: Presupuesto | E12: Gasto | F12: Disponible | H12: AHORROS | I12: Ahorro | J12: Presupuesto | K12: Gasto | L12: Disponible
B13: Arriendo/Hipoteca | F13: =D13-E13 -> 0 | H13: Efectivo | I13: SI | J13: 250000 | L13: =J13-K13 -> 250000
B14: Telefono/ Celular | F14: =D14-E14 -> 0 | H14: Cuenta Bancol | I14: SI | J14: 5019665 | L14: =J14-K14 -> 5019665
B15: Electricidad | F15: =D15-E15 -> 0 | H15: pension voluntaria ahorro casa | I15: SI | J15: 102536491 | L15: =J15-K15 -> 102536491
B16: Agua | F16: =D16-E16 -> 0 | H16: Investor trust 1200 | I16: SI | J16: 18691750 | L16: =J16-K16 -> 18691750
B17: Gas | F17: =D17-E17 -> 0 | H17: Investor trust 2400 | I17: SI | J17: 39578000 | L17: =J17-K17 -> 39578000
B18: Cable/Internet | F18: =D18-E18 -> 0 | H18: poliza pensiones skandia | I18: SI | J18: 12204069 | L18: =J18-K18 -> 12204069
B19: Super Mercado | F19: =D19-E19 -> 0 | H19: Fondo de emergencia lulo | I19: SI | J19: 585890 | L19: =J19-K19 -> 585890
B20: Gasolina | F20: =D20-E20 -> 0 | H20: Littio | I20: SI | J20: 217910 | L20: =J20-K20 -> 217910
B21: Bus | F21: =D21-E21 -> 0 | H21: Nequi | I21: SI | J21: 168222 | L21: =J21-K21 -> 168222
F22: =D22-E22 -> 0 | H22: NU (viajes) | I22: SI | J22: 2619684 | L22: =J22-K22 -> 2619684
F23: =D23-E23 -> 0 | L23: =J23-K23 -> 0
F24: =D24-E24 -> 0 | L24: =J24-K24 -> 0
B25: Subtotal | D25: =SUM(D13:D24) -> 0 | E25: =SUM(E13:E24) -> 0 | F25: =D25-E25 -> 0 | H25: Subtotal | J25: =SUM(J13:J24) -> 1.8187168e+08 | K25: =SUM(K13:K24) -> 0 | L25: =J25-K25 -> 1.8187168e+08
B27: DEUDAS | C27: Ahorro | D27: Presupuesto | E27: Gasto | F27: Disponible | H27: REGALOS/ CARIDAD | I27: Ahorro | J27: Presupuesto | K27: Gasto | L27: Disponible
B28: Deuda Carro | F28: =D28-E28 -> 0 | H28: Regalos Navidad | I28: SI | L28: =J28-K28 -> 0
B29: Deuda tarjeta Nu | C29: SI | E29: 6151674.2 | F29: =D29-E29 -> -6151674.2 | H29: Regalos cumpleaños | I29: SI | L29: =J29-K29 -> 0
B30: Deuda tarjeta 2 | F30: =D30-E30 -> 0 | H30: Caridad | L30: =J30-K30 -> 0
B31: Deuda Estudio | F31: =D31-E31 -> 0 | L31: =J31-K31 -> 0
B32: Carro | F32: =D32-E32 -> 0 | L32: =J32-K32 -> 0
F33: =D33-E33 -> 0 | L33: =J33-K33 -> 0
F34: =D34-E34 -> 0 | L34: =J34-K34 -> 0
F35: =D35-E35 -> 0 | L35: =J35-K35 -> 0
B36: Subtotal | D36: =SUM(D28:D35) -> 0 | E36: =SUM(E28:E35) -> 6151674.2 | F36: =D36-E36 -> -6151674.2 | H36: Subtotal | J36: =SUM(J28:J35) -> 0 | K36: =SUM(K28:K35) -> 0 | L36: =J36-K36 -> 0
B38: CASA | C38: Ahorro | D38: Presupuesto | E38: Gasto | F38: Disponible | H38: TRANSPORTE | I38: Ahorro | J38: Presupuesto | K38: Gasto | L38: Disponible
B39: Limpieza | F39: =D39-E39 -> 0 | H39: Uber/taxi | L39: =J39-K39 -> 0
B40: Mantenimiento | C40: SI | F40: =D40-E40 -> 0 | H40: Estacionamiento | L40: =J40-K40 -> 0
B41: Muebles | F41: =D41-E41 -> 0 | H41: Mantenimiento | I41: SI | L41: =J41-K41 -> 0
B42: Impuestos | C42: SI | F42: =D42-E42 -> 0 | H42: Impuestos | I42: SI | L42: =J42-K42 -> 0
F43: =D43-E43 -> 0 | H43: Panapass/Peaje | L43: =J43-K43 -> 0
F44: =D44-E44 -> 0 | L44: =J44-K44 -> 0
F45: =D45-E45 -> 0 | L45: =J45-K45 -> 0
B46: Subtotal | D46: =SUM(D39:D45) -> 0 | E46: =SUM(E39:E45) -> 0 | F46: =D46-E46 -> 0 | H46: Subtotal | J46: =SUM(J39:J45) -> 0 | K46: =SUM(K39:K45) -> 0 | L46: =J46-K46 -> 0
B48: ALIMENTACIÓN | C48: Ahorro | D48: Presupuesto | E48: Gasto | F48: Disponible | H48: SEGUROS | I48: Ahorro | J48: Presupuesto | K48: Gasto | L48: Disponible
B49: Restaurantes | F49: =D49-E49 -> 0 | H49: Carro | I49: SI | L49: =J49-K49 -> 0
B50: Café/ Snacks | F50: =D50-E50 -> 0 | H50: Vida | I50: SI | L50: =J50-K50 -> 0
F51: =D51-E51 -> 0 | H51: Casa | I51: SI | L51: =J51-K51 -> 0
F52: =D52-E52 -> 0 | H52: Salud | I52: SI | L52: =J52-K52 -> 0
F53: =D53-E53 -> 0 | L53: =J53-K53 -> 0
F54: =D54-E54 -> 0 | L54: =J54-K54 -> 0
B55: Subtotal | D55: =SUM(D49:D54) -> 0 | E55: =SUM(E49:E54) -> 0 | F55: =D55-E55 -> 0 | H55: Subtotal | J55: =SUM(J49:J54) -> 0 | K55: =SUM(K49:K54) -> 0 | L55: =J55-K55 -> 0
B57: SALUD | C57: Ahorro | D57: Presupuesto | E57: Gasto | F57: Disponible | H57: CUIDADO PERSONAL | I57: Ahorro | J57: Presupuesto | K57: Gasto | L57: Disponible
B58: Medicinas | C58: SI | F58: =D58-E58 -> 0 | H58: Ropa | I58: SI | L58: =J58-K58 -> 0
B59: Dentista | C59: SI | F59: =D59-E59 -> 0 | H59: Belleza | I59: SI | L59: =J59-K59 -> 0
B60: Tratamientos | C60: SI | F60: =D60-E60 -> 0 | H60: Peluquería | L60: =J60-K60 -> 0
F61: =D61-E61 -> 0 | H61: Sastre | L61: =J61-K61 -> 0
F62: =D62-E62 -> 0 | H62: Tintorería | L62: =J62-K62 -> 0
F63: =D63-E63 -> 0 | L63: =J63-K63 -> 0
F64: =D64-E64 -> 0 | L64: =J64-K64 -> 0
B65: Subtotal | D65: =SUM(D58:D64) -> 0 | E65: =SUM(E58:E64) -> 0 | F65: =D65-E65 -> 0 | H65: Subtotal | J65: =SUM(J58:J64) -> 0 | K65: =SUM(K58:K64) -> 0 | L65: =J65-K65 -> 0
B67: ENTRETENIMIENTO | C67: Ahorro | D67: Presupuesto | E67: Gasto | F67: Disponible | H67: HIJOS | I67: Ahorro | J67: Presupuesto | K67: Gasto | L67: Diferencia
B68: Vacaciones | C68: SI | F68: =D68-E68 -> 0 | H68: Ropa | I68: SI | L68: =J68-K68 -> 0
B69: Rumba | F69: =D69-E69 -> 0 | H69: Estudio | I69: SI | L69: =J69-K69 -> 0
B70: Citas | F70: =D70-E70 -> 0 | H70: Utiles Escolares | I70: SI | L70: =J70-K70 -> 0
B71: Cine | F71: =D71-E71 -> 0 | H71: Niñera | L71: =J71-K71 -> 0
B72: Deporte | F72: =D72-E72 -> 0 | L72: =J72-K72 -> 0
B73: Netflix | F73: =D73-E73 -> 0 | L73: =J73-K73 -> 0
B74: Spotify | F74: =D74-E74 -> 0 | L74: =J74-K74 -> 0
F75: =D75-E75 -> 0 | L75: =J75-K75 -> 0
F76: =D76-E76 -> 0 | L76: =J76-K76 -> 0
F77: =D77-E77 -> 0 | L77: =J77-K77 -> 0
F78: =D78-E78 -> 0 | L78: =J78-K78 -> 0
B79: Subtotal | D79: =SUM(D68:D78) -> 0 | E79: =SUM(E68:E78) -> 0 | F79: =D79-E79 -> 0 | H79: Subtotal | J79: =SUM(J68:J78) -> 0 | K79: =SUM(K68:K78) -> 0 | L79: =J79-K79 -> 0
B81: MASCOTA | C81: Ahorro | D81: Presupuesto | E81: Gasto | F81: Disponible | H81: OTROS | I81: Ahorro | J81: Presupuesto | K81: Gasto | L81: Disponible
B82: Comida | F82: =D82-E82 -> 0 | L82: =J82-K82 -> 0
B83: Veterinario | C83: SI | F83: =D83-E83 -> 0 | L83: =J83-K83 -> 0
B84: Juguetes | F84: =D84-E84 -> 0 | L84: =J84-K84 -> 0
B85: Medicinas | C85: SI | F85: =D85-E85 -> 0 | L85: =J85-K85 -> 0
F86: =D86-E86 -> 0 | L86: =J86-K86 -> 0
F87: =D87-E87 -> 0 | L87: =J87-K87 -> 0
B88: Subtotal | D88: =SUM(D82:D87) -> 0 | E88: =SUM(E82:E87) -> 0 | F88: =D88-E88 -> 0 | H88: Subtotal | J88: =SUM(J82:J87) -> 0 | K88: =SUM(K82:K87) -> 0 | L88: =J88-K88 -> 0
B90: OTROS | C90: Ahorro | D90: Presupuesto | E90: Gasto | F90: Disponible | H90: OTROS | I90: Ahorro | J90: Presupuesto | K90: Gasto | L90: Disponible
F91: =D91-E91 -> 0 | L91: =J91-K91 -> 0
F92: =D92-E92 -> 0 | L92: =J92-K92 -> 0
F93: =D93-E93 -> 0 | L93: =J93-K93 -> 0
F94: =D94-E94 -> 0 | L94: =J94-K94 -> 0
F95: =D95-E95 -> 0 | L95: =J95-K95 -> 0
F96: =D96-E96 -> 0 | L96: =J96-K96 -> 0
F97: =D97-E97 -> 0 | L97: =J97-K97 -> 0
B98: Subtotal | D98: =SUM(D91:D97) -> 0 | E98: =SUM(E91:E97) -> 0 | F98: =D98-E98 -> 0 | H98: Subtotal | J98: =SUM(J91:J97) -> 0 | K98: =SUM(K91:K97) -> 0 | L98: =J98-K98 -> 0
B100: OTROS | C100: Ahorro | D100: Presupuesto | E100: Gasto | F100: Disponible | H100: OTROS | I100: Ahorro | J100: Presupuesto | K100: Gasto | L100: Disponible
F101: =D101-E101 -> 0 | L101: =J101-K101 -> 0
F102: =D102-E102 -> 0 | L102: =J102-K102 -> 0
F103: =D103-E103 -> 0 | L103: =J103-K103 -> 0
F104: =D104-E104 -> 0 | L104: =J104-K104 -> 0
F105: =D105-E105 -> 0 | L105: =J105-K105 -> 0
F106: =D106-E106 -> 0 | L106: =J106-K106 -> 0
F107: =D107-E107 -> 0 | L107: =J107-K107 -> 0
B108: Subtotal | D108: =SUM(D101:D107) -> 0 | E108: =SUM(E101:E107) -> 0 | F108: =D108-E108 -> 0 | H108: Subtotal | J108: =SUM(J101:J107) -> 0 | K108: =SUM(K101:K107) -> 0 | L108: =J108-K108 -> 0

Sheet Ene
U1: =B13 -> Arriendo/Hipoteca
B2: PRESUPUESTO MENSUAL
B4: Ingreso Estimado | C4: Salario | E4: 9714500
C5: saldo mes anterior | E5: 5074509 | H5: lulo 2531710
C6: Efectivo | E6: 100000
C7: nequi | E7: 100000
C8: Pago Tita | E8: 400000
C10: Total Ingreso Mensual | E10: =SUM(E4:E9) -> 15389009 | H10: Balance (Ingreso vs Presupuesto) | K10: =E10-SUM(D25,D36,D55,D65,D79,D88,D98,J25,J36,J55,J65,J88,J98,D108,J108,D46,J46,J79) -> 0 | M10: =IF(K10=0,"El presupuesto está listo","OJO! Tiene que sumar cero") -> El presupuesto está listo
B12: NECESIDADES BÁSICAS | C12: Ahorro | D12: Presupuesto | E12: Gasto | F12: Disponible | H12: AHORROS | I12: Ahorro | J12: Presupuesto | K12: Gasto | L12: Disponible
B13: Arriendo/Hipoteca | E13: =SUMIFS('Enero - registro gastos'!$D$3:$D$300,'Enero - registro gastos'!$E$3:$E$300,Ene!$B$12,'Enero - registro gastos'!$F$3:$F$300,Ene!B13) -> 0 | F13: =D13-E13 -> 0 | H13: Efectivo | I13: SI | J13: 400000 | K13: =SUMIFS('Enero - registro gastos'!$D$3:$D$300,'Enero - registro gastos'!$E$3:$E$300,Ene!$H$12,'Enero - registro gastos'!$F$3:$F$300,Ene!H13) -> 0 | L13: =J13-K13 -> 400000
B14: Telefono/ Celular | D14: 78000 | E14: =SUMIFS('Enero - registro gastos'!$D$3:$D$300,'Enero - registro gastos'!$E$3:$E$300,Ene!$B$12,'Enero - registro gastos'!$F$3:$F$300,Ene!B14) -> 77988 | F14: =D14-E14 -> 12 | H14: Cuenta Bancol | I14: SI | K14: =SUMIFS('Enero - registro gastos'!$D$3:$D$300,'Enero - registro gastos'!$E$3:$E$300,Ene!$H$12,'Enero - registro gastos'!$F$3:$F$300,Ene!H14) -> 0 | L14: =J14-K14 -> 0
B15: Electricidad | E15: =SUMIFS('Enero - registro gastos'!$D$3:$D$300,'Enero - registro gastos'!$E$3:$E$300,Ene!$B$12,'Enero - registro gastos'!$F$3:$F$300,Ene!B15) -> 0 | F15: =D15-E15 -> 0 | H15: pension voluntaria ahorro casa | I15: SI | J15: =100000+1750000 -> 1850000 | K15: =SUMIFS('Enero - registro gastos'!$D$3:$D$300,'Enero - registro gastos'!$E$3:$E$300,Ene!$H$12,'Enero - registro gastos'!$F$3:$F$300,Ene!H15) -> 0 | L15: =J15-K15 -> 1850000
B16: Agua | E16: =SUMIFS('Enero - registro gastos'!$D$3:$D$300,'Enero - registro gastos'!$E$3:$E$300,Ene!$B$12,'Enero - registro gastos'!$F$3:$F$300,Ene!B16) -> 0 | F16: =D16-E16 -> 0 | H16: Investor trust 1200 | I16: SI | J16: =100*Resumen!C2 -> 385000 | K16: =SUMIFS('Enero - registro gastos'!$D$3:$D$300,'Enero - registro gastos'!$E$3:$E$300,Ene!$H$12,'Enero - registro gastos'!$F$3:$F$300,Ene!H16) -> 0 | L16: =J16-K16 -> 385000
B17: Gas | D17: 15000 | E17: =SUMIFS('Enero - registro gastos'!$D$3:$D$300,'Enero - registro gastos'!$E$3:$E$300,Ene!$B$12,'Enero - registro gastos'!$F$3:$F$300,Ene!B17) -> 0 | F17: =D17-E17 -> 15000 | H17: Investor trust 2400 | I17: SI | J17: =200*Resumen!C2 -> 770000 | K17: =SUMIFS('Enero - registro gastos'!$D$3:$D$300,'Enero - registro gastos'!$E$3:$E$300,Ene!$H$12,'Enero - registro gastos'!$F$3:$F$300,Ene!H17) -> 0 | L17: =J17-K17 -> 770000
B18: Cable/Internet | D18: 140000 | E18: =SUMIFS('Enero - registro gastos'!$D$3:$D$300,'Enero - registro gastos'!$E$3:$E$300,Ene!$B$12,'Enero - registro gastos'!$F$3:$F$300,Ene!B18) -> 142988 | F18: =D18-E18 -> -2988 | H18: poliza pensiones skandia | I18: SI | J18: 336000 | K18: =SUMIFS('Enero - registro gastos'!$D$3:$D$300,'Enero - registro gastos'!$E$3:$E$300,Ene!$H$12,'Enero - registro gastos'!$F$3:$F$300,Ene!H18) -> 0 | L18: =J18-K18 -> 336000
B19: Super Mercado | D19: 300000 | E19: =SUMIFS('Enero - registro gastos'!$D$3:$D$300,'Enero - registro gastos'!$E$3:$E$300,Ene!$B$12,'Enero - registro gastos'!$F$3:$F$300,Ene!B19) -> 0 | F19: =D19-E19 -> 300000 | H19: Fondo de emergencia lulo | I19: SI | J19: 0 | K19: =SUMIFS('Enero - registro gastos'!$D$3:$D$300,'Enero - registro gastos'!$E$3:$E$300,Ene!$H$12,'Enero - registro gastos'!$F$3:$F$300,Ene!H19) -> 0 | L19: =J19-K19 -> 0
B20: Gasolina | D20: 200000 | E20: =SUMIFS('Enero - registro gastos'!$D$3:$D$300,'Enero - registro gastos'!$E$3:$E$300,Ene!$B$12,'Enero - registro gastos'!$F$3:$F$300,Ene!B20) -> 0 | F20: =D20-E20 -> 200000 | H20: Littio | I20: SI | J20: 100000 | K20: =SUMIFS('Enero - registro gastos'!$D$3:$D$300,'Enero - registro gastos'!$E$3:$E$300,Ene!$H$12,'Enero - registro gastos'!$F$3:$F$300,Ene!H20) -> 0 | L20: =J20-K20 -> 100000
B21: Bus | E21: =SUMIFS('Enero - registro gastos'!$D$3:$D$300,'Enero - registro gastos'!$E$3:$E$300,Ene!$B$12,'Enero - registro gastos'!$F$3:$F$300,Ene!B21) -> 0 | F21: =D21-E21 -> 0 | H21: Nequi | I21: SI | K21: =SUMIFS('Enero - registro gastos'!$D$3:$D$300,'Enero - registro gastos'!$E$3:$E$300,Ene!$H$12,'Enero - registro gastos'!$F$3:$F$300,Ene!H21) -> 0 | L21: =J21-K21 -> 0
E22: =SUMIFS('Enero - registro gastos'!$D$3:$D$300,'Enero - registro gastos'!$E$3:$E$300,Ene!$B$12,'Enero - registro gastos'!$F$3:$F$300,Ene!B22) -> 0 | F22: =D22-E22 -> 0 | H22: viajes varios | I22: SI | J22: 300000 | K22: =SUMIFS('Enero - registro gastos'!$D$3:$D$300,'Enero - registro gastos'!$E$3:$E$300,Ene!$H$12,'Enero - registro gastos'!$F$3:$F$300,Ene!H22) -> 0 | L22: =J22-K22 -> 300000
E23: =SUMIFS('Enero - registro gastos'!$D$3:$D$300,'Enero - registro gastos'!$E$3:$E$300,Ene!$B$12,'Enero - registro gastos'!$F$3:$F$300,Ene!B23) -> 0 | F23: =D23-E23 -> 0 | H23: Viaje Japon lulo | I23: SI | J23: 1331710 | K23: =SUMIFS('Enero - registro gastos'!$D$3:$D$300,'Enero - registro gastos'!$E$3:$E$300,Ene!$H$12,'Enero - registro gastos'!$F$3:$F$300,Ene!H23) -> 0 | L23: =J23-K23 -> 1331710
E24: =SUMIFS('Enero - registro gastos'!$D$3:$D$300,'Enero - registro gastos'!$E$3:$E$300,Ene!$B$12,'Enero - registro gastos'!$F$3:$F$300,Ene!B24) -> 0 | F24: =D24-E24 -> 0 | H24: Viaje Estados unidos lulo | I24: SI | J24: =1727928 -> 1727928 | K24: =SUMIFS('Enero - registro gastos'!$D$3:$D$300,'Enero - registro gastos'!$E$3:$E$300,Ene!$H$12,'Enero - registro gastos'!$F$3:$F$300,Ene!H24) -> 0 | L24: =J24-K24 -> 1727928
B25: Subtotal | D25: =SUM(D13:D24) -> 733000 | E25: =SUM(E13:E24) -> 220976 | F25: =D25-E25 -> 512024 | H25: Subtotal | J25: =SUM(J13:J24) -> 7200638 | K25: =SUM(K13:K24) -> 0 | L25: =J25-K25 -> 7200638
B27: DEUDAS | C27: Ahorro | D27: Presupuesto | E27: Gasto | F27: Disponible | H27: REGALOS/ CARIDAD | I27: Ahorro | J27: Presupuesto | K27: Gasto | L27: Disponible
B28: Deuda Carro | E28: =SUMIFS('Enero - registro gastos'!$D$3:$D$300,'Enero - registro gastos'!$E$3:$E$300,Ene!$B$27,'Enero - registro gastos'!$F$3:$F$300,Ene!B28) -> 0 | F28: =D28-E28 -> 0 | H28: Regalos Navidad | K28: =SUMIFS('Enero - registro gastos'!$D$3:$D$300,'Enero - registro gastos'!$E$3:$E$300,Ene!$H$27,'Enero - registro gastos'!$F$3:$F$300,Ene!H28) -> 0 | L28: =J28-K28 -> 0
B29: Deuda tarjeta Un | D29: 3917065 | E29: =SUMIFS('Enero - registro gastos'!$D$3:$D$300,'Enero - registro gastos'!$E$3:$E$300,Ene!$B$27,'Enero - registro gastos'!$F$3:$F$300,Ene!B29) -> 3917064.8 | F29: =D29-E29 -> 0.2 | H29: Regalos cumpleaños | J29: 150000 | K29: =SUMIFS('Enero - registro gastos'!$D$3:$D$300,'Enero - registro gastos'!$E$3:$E$300,Ene!$H$27,'Enero - registro gastos'!$F$3:$F$300,Ene!H29) -> 0 | L29: =J29-K29 -> 150000
B30: Deuda Banco de occidente | E30: =SUMIFS('Enero - registro gastos'!$D$3:$D$300,'Enero - registro gastos'!$E$3:$E$300,Ene!$B$27,'Enero - registro gastos'!$F$3:$F$300,Ene!B30) -> 0 | F30: =D30-E30 -> 0 | H30: Caridad | J30: 55000 | K30: =SUMIFS('Enero - registro gastos'!$D$3:$D$300,'Enero - registro gastos'!$E$3:$E$300,Ene!$H$27,'Enero - registro gastos'!$F$3:$F$300,Ene!H30) -> 55000 | L30: =J30-K30 -> 0
B31: Deuda Estudio | E31: =SUMIFS('Enero - registro gastos'!$D$3:$D$300,'Enero - registro gastos'!$E$3:$E$300,Ene!$B$27,'Enero - registro gastos'!$F$3:$F$300,Ene!B31) -> 0 | F31: =D31-E31 -> 0 | K31: =SUMIFS('Enero - registro gastos'!$D$3:$D$300,'Enero - registro gastos'!$E$3:$E$300,Ene!$H$27,'Enero - registro gastos'!$F$3:$F$300,Ene!H31) -> 0 | L31: =J31-K31 -> 0
B32: Carro | E32: =SUMIFS('Enero - registro gastos'!$D$3:$D$300,'Enero - registro gastos'!$E$3:$E$300,Ene!$B$27,'Enero - registro gastos'!$F$3:$F$300,Ene!B32) -> 0 | F32: =D32-E32 -> 0 | K32: =SUMIFS('Enero - registro gastos'!$D$3:$D$300,'Enero - registro gastos'!$E$3:$E$300,Ene!$H$27,'Enero - registro gastos'!$F$3:$F$300,Ene!H32) -> 0 | L32: =J32-K32 -> 0
E33: =SUMIFS('Enero - registro gastos'!$D$3:$D$300,'Enero - registro gastos'!$E$3:$E$300,Ene!$B$27,'Enero - registro gastos'!$F$3:$F$300,Ene!B33) -> 0 | F33: =D33-E33 -> 0 | K33: =SUMIFS('Enero - registro gastos'!$D$3:$D$300,'Enero - registro gastos'!$E$3:$E$300,Ene!$H$27,'Enero - registro gastos'!$F$3:$F$300,Ene!H33) -> 0 | L33: =J33-K33 -> 0
E34: =SUMIFS('Enero - registro gastos'!$D$3:$D$300,'Enero - registro gastos'!$E$3:$E$300,Ene!$B$27,'Enero - registro gastos'!$F$3:$F$300,Ene!B34) -> 0 | F34: =D34-E34 -> 0 | K34: =SUMIFS('Enero - registro gastos'!$D$3:$D$300,'Enero - registro gastos'!$E$3:$E$300,Ene!$H$27,'Enero - registro gastos'!$F$3:$F$300,Ene!H34) -> 0 | L34: =J34-K34 -> 0
E35: =SUMIFS('Enero - registro gastos'!$D$3:$D$300,'Enero - registro gastos'!$E$3:$E$300,Ene!$B$27,'Enero - registro gastos'!$F$3:$F$300,Ene!B35) -> 0 | F35: =D35-E35 -> 0 | K35: =SUMIFS('Enero - registro gastos'!$D$3:$D$300,'Enero - registro gastos'!$E$3:$E$300,Ene!$H$27,'Enero - registro gastos'!$F$3:$F$300,Ene!H35) -> 0 | L35: =J35-K35 -> 0
B36: Subtotal | D36: =SUM(D28:D35) -> 3917065 | E36: =SUM(E28:E35) -> 3917064.8 | F36: =D36-E36 -> 0.2 | H36: Subtotal | J36: =SUM(J28:J35) -> 205000 | K36: =SUM(K28:K35) -> 55000 | L36: =J36-K36 -> 150000
B38: CASA | C38: Ahorro | D38: Presupuesto | E38: Gasto | F38: Disponible | H38: TRANSPORTE | I38: Ahorro | J38: Presupuesto | K38: Gasto | L38: Disponible
B39: Limpieza | E39: =SUMIFS('Enero - registro gastos'!$D$3:$D$300,'Enero - registro gastos'!$E$3:$E$300,Ene!$B$38,'Enero - registro gastos'!$F$3:$F$300,Ene!B39) -> 0 | F39: =D39-E39 -> 0 | H39: Uber/taxi | K39: =SUMIFS('Enero - registro gastos'!$D$3:$D$300,'Enero - registro gastos'!$E$3:$E$300,Ene!$H$38,'Enero - registro gastos'!$F$3:$F$300,Ene!H39) -> 0 | L39: =J39-K39 -> 0
B40: Mantenimiento | E40: =SUMIFS('Enero - registro gastos'!$D$3:$D$300,'Enero - registro gastos'!$E$3:$E$300,Ene!$B$38,'Enero - registro gastos'!$F$3:$F$300,Ene!B40) -> 0 | F40: =D40-E40 -> 0 | H40: Estacionamiento | K40: =SUMIFS('Enero - registro gastos'!$D$3:$D$300,'Enero - registro gastos'!$E$3:$E$300,Ene!$H$38,'Enero - registro gastos'!$F$3:$F$300,Ene!H40) -> 0 | L40: =J40-K40 -> 0
B41: Muebles | E41: =SUMIFS('Enero - registro gastos'!$D$3:$D$300,'Enero - registro gastos'!$E$3:$E$300,Ene!$B$38,'Enero - registro gastos'!$F$3:$F$300,Ene!B41) -> 0 | F41: =D41-E41 -> 0 | H41: Mantenimiento | K41: =SUMIFS('Enero - registro gastos'!$D$3:$D$300,'Enero - registro gastos'!$E$3:$E$300,Ene!$H$38,'Enero - registro gastos'!$F$3:$F$300,Ene!H41) -> 0 | L41: =J41-K41 -> 0
B42: Impuestos | E42: =SUMIFS('Enero - registro gastos'!$D$3:$D$300,'Enero - registro gastos'!$E$3:$E$300,Ene!$B$38,'Enero - registro gastos'!$F$3:$F$300,Ene!B42) -> 0 | F42: =D42-E42 -> 0 | H42: Impuestos lulo | I42: SI | J42: 500000 | K42: =SUMIFS('Enero - registro gastos'!$D$3:$D$300,'Enero - registro gastos'!$E$3:$E$300,Ene!$H$38,'Enero - registro gastos'!$F$3:$F$300,Ene!H42) -> 0 | L42: =J42-K42 -> 500000
E43: =SUMIFS('Enero - registro gastos'!$D$3:$D$300,'Enero - registro gastos'!$E$3:$E$300,Ene!$B$38,'Enero - registro gastos'!$F$3:$F$300,Ene!B43) -> 0 | F43: =D43-E43 -> 0 | H43: Panapass/Peaje | J43: 20000 | K43: =SUMIFS('Enero - registro gastos'!$D$3:$D$300,'Enero - registro gastos'!$E$3:$E$300,Ene!$H$38,'Enero - registro gastos'!$F$3:$F$300,Ene!H43) -> 0 | L43: =J43-K43 -> 20000
E44: =SUMIFS('Enero - registro gastos'!$D$3:$D$300,'Enero - registro gastos'!$E$3:$E$300,Ene!$B$38,'Enero - registro gastos'!$F$3:$F$300,Ene!B44) -> 0 | F44: =D44-E44 -> 0 | K44: =SUMIFS('Enero - registro gastos'!$D$3:$D$300,'Enero - registro gastos'!$E$3:$E$300,Ene!$H$38,'Enero - registro gastos'!$F$3:$F$300,Ene!H44) -> 0 | L44: =J44-K44 -> 0
E45: =SUMIFS('Enero - registro gastos'!$D$3:$D$300,'Enero - registro gastos'!$E$3:$E$300,Ene!$B$38,'Enero - registro gastos'!$F$3:$F$300,Ene!B45) -> 0 | F45: =D45-E45 -> 0 | K45: =SUMIFS('Enero - registro gastos'!$D$3:$D$300,'Enero - registro gastos'!$E$3:$E$300,Ene!$H$38,'Enero - registro gastos'!$F$3:$F$300,Ene!H45) -> 0 | L45: =J45-K45 -> 0
B46: Subtotal | D46: =SUM(D39:D45) -> 0 | E46: =SUM(E39:E45) -> 0 | F46: =D46-E46 -> 0 | H46: Subtotal | J46: =SUM(J39:J45) -> 520000 | K46: =SUM(K39:K45) -> 0 | L46: =J46-K46 -> 520000
B48: ALIMENTACIÓN | C48: Ahorro | D48: Presupuesto | E48: Gasto | F48: Disponible | H48: SEGUROS | I48: Ahorro | J48: Presupuesto | K48: Gasto | L48: Disponible
B49: Restaurantes | D49: 400000 | E49: =SUMIFS('Enero - registro gastos'!$D$3:$D$300,'Enero - registro gastos'!$E$3:$E$300,Ene!$B$48,'Enero - registro gastos'!$F$3:$F$300,Ene!B49) -> 150890 | F49: =D49-E49 -> 249110 | H49: Carro lulo | I49: SI | J49: 500000 | K49: =SUMIFS('Enero - registro gastos'!$D$3:$D$300,'Enero - registro gastos'!$E$3:$E$300,Ene!$H$48,'Enero - registro gastos'!$F$3:$F$300,Ene!H49) -> 0 | L49: =J49-K49 -> 500000
B50: Café/ Snacks | E50: =SUMIFS('Enero - registro gastos'!$D$3:$D$300,'Enero - registro gastos'!$E$3:$E$300,Ene!$B$48,'Enero - registro gastos'!$F$3:$F$300,Ene!B50) -> 0 | F50: =D50-E50 -> 0 | H50: Vida | K50: =SUMIFS('Enero - registro gastos'!$D$3:$D$300,'Enero - registro gastos'!$E$3:$E$300,Ene!$H$48,'Enero - registro gastos'!$F$3:$F$300,Ene!H50) -> 0 | L50: =J50-K50 -> 0
B51: Rappi | D51: 300000 | E51: =SUMIFS('Enero - registro gastos'!$D$3:$D$300,'Enero - registro gastos'!$E$3:$E$300,Ene!$B$48,'Enero - registro gastos'!$F$3:$F$300,Ene!B51) -> 28650 | F51: =D51-E51 -> 271350 | H51: Casa | K51: =SUMIFS('Enero - registro gastos'!$D$3:$D$300,'Enero - registro gastos'!$E$3:$E$300,Ene!$H$48,'Enero - registro gastos'!$F$3:$F$300,Ene!H51) -> 0 | L51: =J51-K51 -> 0
E52: =SUMIFS('Enero - registro gastos'!$D$3:$D$300,'Enero - registro gastos'!$E$3:$E$300,Ene!$B$48,'Enero - registro gastos'!$F$3:$F$300,Ene!B52) -> 0 | F52: =D52-E52 -> 0 | H52: Salud | K52: =SUMIFS('Enero - registro gastos'!$D$3:$D$300,'Enero - registro gastos'!$E$3:$E$300,Ene!$H$48,'Enero - registro gastos'!$F$3:$F$300,Ene!H52) -> 0 | L52: =J52-K52 -> 0
E53: =SUMIFS('Enero - registro gastos'!$D$3:$D$300,'Enero - registro gastos'!$E$3:$E$300,Ene!$B$48,'Enero - registro gastos'!$F$3:$F$300,Ene!B53) -> 0 | F53: =D53-E53 -> 0 | K53: =SUMIFS('Enero - registro gastos'!$D$3:$D$300,'Enero - registro gastos'!$E$3:$E$300,Ene!$H$48,'Enero - registro gastos'!$F$3:$F$300,Ene!H53) -> 0 | L53: =J53-K53 -> 0
E54: =SUMIFS('Enero - registro gastos'!$D$3:$D$300,'Enero - registro gastos'!$E$3:$E$300,Ene!$B$48,'Enero - registro gastos'!$F$3:$F$300,Ene!B54) -> 0 | F54: =D54-E54 -> 0 | K54: =SUMIFS('Enero - registro gastos'!$D$3:$D$300,'Enero - registro gastos'!$E$3:$E$300,Ene!$H$48,'Enero - registro gastos'!$F$3:$F$300,Ene!H54) -> 0 | L54: =J54-K54 -> 0
B55: Subtotal | D55: =SUM(D49:D54) -> 700000 | E55: =SUM(E49:E54) -> 179540 | F55: =D55-E55 -> 520460 | H55: Subtotal | J55: =SUM(J49:J54) -> 500000 | K55: =SUM(K49:K54) -> 0 | L55: =J55-K55 -> 500000
B57: SALUD | C57: Ahorro | D57: Presupuesto | E57: Gasto | F57: Disponible | H57: CUIDADO PERSONAL | I57: Ahorro | J57: Presupuesto | K57: Gasto | L57: Disponible
B58: Medicinas | D58: 80000 | E58: =SUMIFS('Enero - registro gastos'!$D$3:$D$300,'Enero - registro gastos'!$E$3:$E$300,Ene!$B$57,'Enero - registro gastos'!$F$3:$F$300,Ene!B58) -> 0 | F58: =D58-E58 -> 80000 | H58: Ropa | K58: =SUMIFS('Enero - registro gastos'!$D$3:$D$300,'Enero - registro gastos'!$E$3:$E$300,Ene!$H$57,'Enero - registro gastos'!$F$3:$F$300,Ene!H58) -> 0 | L58: =J58-K58 -> 0
B59: Dentista | E59: =SUMIFS('Enero - registro gastos'!$D$3:$D$300,'Enero - registro gastos'!$E$3:$E$300,Ene!$B$57,'Enero - registro gastos'!$F$3:$F$300,Ene!B59) -> 0 | F59: =D59-E59 -> 0 | H59: Belleza | K59: =SUMIFS('Enero - registro gastos'!$D$3:$D$300,'Enero - registro gastos'!$E$3:$E$300,Ene!$H$57,'Enero - registro gastos'!$F$3:$F$300,Ene!H59) -> 0 | L59: =J59-K59 -> 0
B60: Tratamientos | E60: =SUMIFS('Enero - registro gastos'!$D$3:$D$300,'Enero - registro gastos'!$E$3:$E$300,Ene!$B$57,'Enero - registro gastos'!$F$3:$F$300,Ene!B60) -> 0 | F60: =D60-E60 -> 0 | H60: Peluquería | K60: =SUMIFS('Enero - registro gastos'!$D$3:$D$300,'Enero - registro gastos'!$E$3:$E$300,Ene!$H$57,'Enero - registro gastos'!$F$3:$F$300,Ene!H60) -> 0 | L60: =J60-K60 -> 0
E61: =SUMIFS('Enero - registro gastos'!$D$3:$D$300,'Enero - registro gastos'!$E$3:$E$300,Ene!$B$57,'Enero - registro gastos'!$F$3:$F$300,Ene!B61) -> 0 | F61: =D61-E61 -> 0 | H61: Sastre | K61: =SUMIFS('Enero - registro gastos'!$D$3:$D$300,'Enero - registro gastos'!$E$3:$E$300,Ene!$H$57,'Enero - registro gastos'!$F$3:$F$300,Ene!H61) -> 0 | L61: =J61-K61 -> 0
E62: =SUMIFS('Enero - registro gastos'!$D$3:$D$300,'Enero - registro gastos'!$E$3:$E$300,Ene!$B$57,'Enero - registro gastos'!$F$3:$F$300,Ene!B62) -> 0 | F62: =D62-E62 -> 0 | H62: Tintorería | K62: =SUMIFS('Enero - registro gastos'!$D$3:$D$300,'Enero - registro gastos'!$E$3:$E$300,Ene!$H$57,'Enero - registro gastos'!$F$3:$F$300,Ene!H62) -> 0 | L62: =J62-K62 -> 0
E63: =SUMIFS('Enero - registro gastos'!$D$3:$D$300,'Enero - registro gastos'!$E$3:$E$300,Ene!$B$57,'Enero - registro gastos'!$F$3:$F$300,Ene!B63) -> 0 | F63: =D63-E63 -> 0 | K63: =SUMIFS('Enero - registro gastos'!$D$3:$D$300,'Enero - registro gastos'!$E$3:$E$300,Ene!$H$57,'Enero - registro gastos'!$F$3:$F$300,Ene!H63) -> 0 | L63: =J63-K63 -> 0
E64: =SUMIFS('Enero - registro gastos'!$D$3:$D$300,'Enero - registro gastos'!$E$3:$E$300,Ene!$B$57,'Enero - registro gastos'!$F$3:$F$300,Ene!B64) -> 0 | F64: =D64-E64 -> 0 | K64: =SUMIFS('Enero - registro gastos'!$D$3:$D$300,'Enero - registro gastos'!$E$3:$E$300,Ene!$H$57,'Enero - registro gastos'!$F$3:$F$300,Ene!H64) -> 0 | L64: =J64-K64 -> 0
B65: Subtotal | D65: =SUM(D58:D64) -> 80000 | E65: =SUM(E58:E64) -> 0 | F65: =D65-E65 -> 80000 | H65: Subtotal | J65: =SUM(J58:J64) -> 0 | K65: =SUM(K58:K64) -> 0 | L65: =J65-K65 -> 0
B67: ENTRETENIMIENTO | C67: Ahorro | D67: Presupuesto | E67: Gasto | F67: Disponible | H67: HIJOS | I67: Ahorro | J67: Presupuesto | K67: Gasto | L67: Diferencia
B68: Vacaciones | E68: =SUMIFS('Enero - registro gastos'!$D$3:$D$300,'Enero - registro gastos'!$E$3:$E$300,Ene!$B$67,'Enero - registro gastos'!$F$3:$F$300,Ene!B68) -> 0 | F68: =D68-E68 -> 0 | H68: Ropa | K68: =SUMIFS('Enero - registro gastos'!$D$3:$D$300,'Enero - registro gastos'!$E$3:$E$300,Ene!$H$67,'Enero - registro gastos'!$F$3:$F$300,Ene!H68) -> 0 | L68: =J68-K68 -> 0
B69: Rumba | E69: =SUMIFS('Enero - registro gastos'!$D$3:$D$300,'Enero - registro gastos'!$E$3:$E$300,Ene!$B$67,'Enero - registro gastos'!$F$3:$F$300,Ene!B69) -> 0 | F69: =D69-E69 -> 0 | H69: Estudio | K69: =SUMIFS('Enero - registro gastos'!$D$3:$D$300,'Enero - registro gastos'!$E$3:$E$300,Ene!$H$67,'Enero - registro gastos'!$F$3:$F$300,Ene!H69) -> 0 | L69: =J69-K69 -> 0
B70: Citas | E70: =SUMIFS('Enero - registro gastos'!$D$3:$D$300,'Enero - registro gastos'!$E$3:$E$300,Ene!$B$67,'Enero - registro gastos'!$F$3:$F$300,Ene!B70) -> 0 | F70: =D70-E70 -> 0 | H70: Utiles Escolares | K70: =SUMIFS('Enero - registro gastos'!$D$3:$D$300,'Enero - registro gastos'!$E$3:$E$300,Ene!$H$67,'Enero - registro gastos'!$F$3:$F$300,Ene!H70) -> 0 | L70: =J70-K70 -> 0
B71: Cine | E71: =SUMIFS('Enero - registro gastos'!$D$3:$D$300,'Enero - registro gastos'!$E$3:$E$300,Ene!$B$67,'Enero - registro gastos'!$F$3:$F$300,Ene!B71) -> 244000 | F71: =D71-E71 -> -244000 | H71: Niñera | K71: =SUMIFS('Enero - registro gastos'!$D$3:$D$300,'Enero - registro gastos'!$E$3:$E$300,Ene!$H$67,'Enero - registro gastos'!$F$3:$F$300,Ene!H71) -> 0 | L71: =J71-K71 -> 0
B72: Deporte | D72: 150906 | E72: =SUMIFS('Enero - registro gastos'!$D$3:$D$300,'Enero - registro gastos'!$E$3:$E$300,Ene!$B$67,'Enero - registro gastos'!$F$3:$F$300,Ene!B72) -> 148241.73 | F72: =D72-E72 -> 2664.27 | K72: =SUMIFS('Enero - registro gastos'!$D$3:$D$300,'Enero - registro gastos'!$E$3:$E$300,Ene!$H$67,'Enero - registro gastos'!$F$3:$F$300,Ene!H72) -> 0 | L72: =J72-K72 -> 0
B73: Netflix | D73: 45000 | E73: =SUMIFS('Enero - registro gastos'!$D$3:$D$300,'Enero - registro gastos'!$E$3:$E$300,Ene!$B$67,'Enero - registro gastos'!$F$3:$F$300,Ene!B73) -> 44900 | F73: =D73-E73 -> 100 | K73: =SUMIFS('Enero - registro gastos'!$D$3:$D$300,'Enero - registro gastos'!$E$3:$E$300,Ene!$H$67,'Enero - registro gastos'!$F$3:$F$300,Ene!H73) -> 0 | L73: =J73-K73 -> 0
B74: Spotify | D74: 30500 | E74: =SUMIFS('Enero - registro gastos'!$D$3:$D$300,'Enero - registro gastos'!$E$3:$E$300,Ene!$B$67,'Enero - registro gastos'!$F$3:$F$300,Ene!B74) -> 0 | F74: =D74-E74 -> 30500 | K74: =SUMIFS('Enero - registro gastos'!$D$3:$D$300,'Enero - registro gastos'!$E$3:$E$300,Ene!$H$67,'Enero - registro gastos'!$F$3:$F$300,Ene!H74) -> 0 | L74: =J74-K74 -> 0
B75: google | D75: 9000 | E75: =SUMIFS('Enero - registro gastos'!$D$3:$D$300,'Enero - registro gastos'!$E$3:$E$300,Ene!$B$67,'Enero - registro gastos'!$F$3:$F$300,Ene!B75) -> 0 | F75: =D75-E75 -> 9000 | K75: =SUMIFS('Enero - registro gastos'!$D$3:$D$300,'Enero - registro gastos'!$E$3:$E$300,Ene!$H$67,'Enero - registro gastos'!$F$3:$F$300,Ene!H75) -> 0 | L75: =J75-K75 -> 0
B76: hbo | D76: 25000 | E76: =SUMIFS('Enero - registro gastos'!$D$3:$D$300,'Enero - registro gastos'!$E$3:$E$300,Ene!$B$67,'Enero - registro gastos'!$F$3:$F$300,Ene!B76) -> 14950 | F76: =D76-E76 -> 10050 | K76: =SUMIFS('Enero - registro gastos'!$D$3:$D$300,'Enero - registro gastos'!$E$3:$E$300,Ene!$H$67,'Enero - registro gastos'!$F$3:$F$300,Ene!H76) -> 0 | L76: =J76-K76 -> 0
B77: Apple cloud | D77: 12900 | E77: =SUMIFS('Enero - registro gastos'!$D$3:$D$300,'Enero - registro gastos'!$E$3:$E$300,Ene!$B$67,'Enero - registro gastos'!$F$3:$F$300,Ene!B77) -> 12900 | F77: =D77-E77 -> 0 | K77: =SUMIFS('Enero - registro gastos'!$D$3:$D$300,'Enero - registro gastos'!$E$3:$E$300,Ene!$H$67,'Enero - registro gastos'!$F$3:$F$300,Ene!H77) -> 0 | L77: =J77-K77 -> 0
E78: =SUMIFS('Enero - registro gastos'!$D$3:$D$300,'Enero - registro gastos'!$E$3:$E$300,Ene!$B$67,'Enero - registro gastos'!$F$3:$F$300,Ene!B78) -> 0 | F78: =D78-E78 -> 0 | K78: =SUMIFS('Enero - registro gastos'!$D$3:$D$300,'Enero - registro gastos'!$E$3:$E$300,Ene!$H$67,'Enero - registro gastos'!$F$3:$F$300,Ene!H78) -> 0 | L78: =J78-K78 -> 0
B79: Subtotal | D79: =SUM(D68:D78) -> 273306 | E79: =SUM(E68:E78) -> 464991.73 | F79: =D79-E79 -> -191685.73 | H79: Subtotal | J79: =SUM(J68:J78) -> 0 | K79: =SUM(K68:K78) -> 0 | L79: =J79-K79 -> 0
B81: MASCOTA | C81: Ahorro | D81: Presupuesto | E81: Gasto | F81: Disponible | H81: VIAJES | I81: Ahorro | J81: Presupuesto | K81: Gasto | L81: Disponible
B82: Comida | E82: =SUMIFS('Enero - registro gastos'!$D$3:$D$300,'Enero - registro gastos'!$E$3:$E$300,Ene!$B$81,'Enero - registro gastos'!$F$3:$F$300,Ene!B82) -> 0 | F82: =D82-E82 -> 0 | H82: Meddlin | J82: 1000000 | K82: =SUMIFS('Enero - registro gastos'!$D$3:$D$300,'Enero - registro gastos'!$E$3:$E$300,Ene!$H$81,'Enero - registro gastos'!$F$3:$F$300,Ene!H82) -> 0 | L82: =J82-K82 -> 1000000
B83: Veterinario | E83: =SUMIFS('Enero - registro gastos'!$D$3:$D$300,'Enero - registro gastos'!$E$3:$E$300,Ene!$B$81,'Enero - registro gastos'!$F$3:$F$300,Ene!B83) -> 0 | F83: =D83-E83 -> 0 | K83: =SUMIFS('Enero - registro gastos'!$D$3:$D$300,'Enero - registro gastos'!$E$3:$E$300,Ene!$H$81,'Enero - registro gastos'!$F$3:$F$300,Ene!H83) -> 0 | L83: =J83-K83 -> 0
B84: Juguetes | E84: =SUMIFS('Enero - registro gastos'!$D$3:$D$300,'Enero - registro gastos'!$E$3:$E$300,Ene!$B$81,'Enero - registro gastos'!$F$3:$F$300,Ene!B84) -> 0 | F84: =D84-E84 -> 0 | K84: =SUMIFS('Enero - registro gastos'!$D$3:$D$300,'Enero - registro gastos'!$E$3:$E$300,Ene!$H$81,'Enero - registro gastos'!$F$3:$F$300,Ene!H84) -> 0 | L84: =J84-K84 -> 0
B85: Medicinas | E85: =SUMIFS('Enero - registro gastos'!$D$3:$D$300,'Enero - registro gastos'!$E$3:$E$300,Ene!$B$81,'Enero - registro gastos'!$F$3:$F$300,Ene!B85) -> 0 | F85: =D85-E85 -> 0 | K85: =SUMIFS('Enero - registro gastos'!$D$3:$D$300,'Enero - registro gastos'!$E$3:$E$300,Ene!$H$81,'Enero - registro gastos'!$F$3:$F$300,Ene!H85) -> 0 | L85: =J85-K85 -> 0
E86: =SUMIFS('Enero - registro gastos'!$D$3:$D$300,'Enero - registro gastos'!$E$3:$E$300,Ene!$B$81,'Enero - registro gastos'!$F$3:$F$300,Ene!B86) -> 0 | F86: =D86-E86 -> 0 | K86: =SUMIFS('Enero - registro gastos'!$D$3:$D$300,'Enero - registro gastos'!$E$3:$E$300,Ene!$H$81,'Enero - registro gastos'!$F$3:$F$300,Ene!H86) -> 0 | L86: =J86-K86 -> 0
E87: =SUMIFS('Enero - registro gastos'!$D$3:$D$300,'Enero - registro gastos'!$E$3:$E$300,Ene!$B$81,'Enero - registro gastos'!$F$3:$F$300,Ene!B87) -> 0 | F87: =D87-E87 -> 0 | K87: =SUMIFS('Enero - registro gastos'!$D$3:$D$300,'Enero - registro gastos'!$E$3:$E$300,Ene!$H$81,'Enero - registro gastos'!$F$3:$F$300,Ene!H87) -> 0 | L87: =J87-K87 -> 0
B88: Subtotal | D88: =SUM(D82:D87) -> 0 | E88: =SUM(E82:E87) -> 0 | F88: =D88-E88 -> 0 | H88: Subtotal | J88: =SUM(J82:J87) -> 1000000 | K88: =SUM(K82:K87) -> 0 | L88: =J88-K88 -> 1000000
B90: OTROS 2 | C90: Ahorro | D90: Presupuesto | E90: Gasto | F90: Disponible | H90: OTROS 3 | I90: Ahorro | J90: Presupuesto | K90: Gasto | L90: Disponible
B91: OPENAI | D91: 80000 | E91: =SUMIFS('Enero - registro gastos'!$D$3:$D$300,'Enero - registro gastos'!$E$3:$E$300,Ene!$B$90,'Enero - registro gastos'!$F$3:$F$300,Ene!B91) -> 0 | F91: =D91-E91 -> 80000 | K91: =SUMIFS('Enero - registro gastos'!$D$3:$D$300,'Enero - registro gastos'!$E$3:$E$300,Ene!$H$90,'Enero - registro gastos'!$F$3:$F$300,Ene!H91) -> 0 | L91: =J91-K91 -> 0
B92: clases de canto | D92: =45000*4 -> 180000 | E92: =SUMIFS('Enero - registro gastos'!$D$3:$D$300,'Enero - registro gastos'!$E$3:$E$300,Ene!$B$90,'Enero - registro gastos'!$F$3:$F$300,Ene!B92) -> 0 | F92: =D92-E92 -> 180000 | K92: =SUMIFS('Enero - registro gastos'!$D$3:$D$300,'Enero - registro gastos'!$E$3:$E$300,Ene!$H$90,'Enero - registro gastos'!$F$3:$F$300,Ene!H92) -> 0 | L92: =J92-K92 -> 0
E93: =SUMIFS('Enero - registro gastos'!$D$3:$D$300,'Enero - registro gastos'!$E$3:$E$300,Ene!$B$90,'Enero - registro gastos'!$F$3:$F$300,Ene!B93) -> 0 | F93: =D93-E93 -> 0 | K93: =SUMIFS('Enero - registro gastos'!$D$3:$D$300,'Enero - registro gastos'!$E$3:$E$300,Ene!$H$90,'Enero - registro gastos'!$F$3:$F$300,Ene!H93) -> 0 | L93: =J93-K93 -> 0
E94: =SUMIFS('Enero - registro gastos'!$D$3:$D$300,'Enero - registro gastos'!$E$3:$E$300,Ene!$B$90,'Enero - registro gastos'!$F$3:$F$300,Ene!B94) -> 0 | F94: =D94-E94 -> 0 | K94: =SUMIFS('Enero - registro gastos'!$D$3:$D$300,'Enero - registro gastos'!$E$3:$E$300,Ene!$H$90,'Enero - registro gastos'!$F$3:$F$300,Ene!H94) -> 0 | L94: =J94-K94 -> 0
E95: =SUMIFS('Enero - registro gastos'!$D$3:$D$300,'Enero - registro gastos'!$E$3:$E$300,Ene!$B$90,'Enero - registro gastos'!$F$3:$F$300,Ene!B95) -> 0 | F95: =D95-E95 -> 0 | K95: =SUMIFS('Enero - registro gastos'!$D$3:$D$300,'Enero - registro gastos'!$E$3:$E$300,Ene!$H$90,'Enero - registro gastos'!$F$3:$F$300,Ene!H95) -> 0 | L95: =J95-K95 -> 0
E96: =SUMIFS('Enero - registro gastos'!$D$3:$D$300,'Enero - registro gastos'!$E$3:$E$300,Ene!$B$90,'Enero - registro gastos'!$F$3:$F$300,Ene!B96) -> 0 | F96: =D96-E96 -> 0 | K96: =SUMIFS('Enero - registro gastos'!$D$3:$D$300,'Enero - registro gastos'!$E$3:$E$300,Ene!$H$90,'Enero - registro gastos'!$F$3:$F$300,Ene!H96) -> 0 | L96: =J96-K96 -> 0
E97: =SUMIFS('Enero - registro gastos'!$D$3:$D$300,'Enero - registro gastos'!$E$3:$E$300,Ene!$B$90,'Enero - registro gastos'!$F$3:$F$300,Ene!B97) -> 0 | F97: =D97-E97 -> 0 | K97: =SUMIFS('Enero - registro gastos'!$D$3:$D$300,'Enero - registro gastos'!$E$3:$E$300,Ene!$H$90,'Enero - registro gastos'!$F$3:$F$300,Ene!H97) -> 0 | L97: =J97-K97 -> 0
B98: Subtotal | D98: =SUM(D91:D97) -> 260000 | E98: =SUM(E91:E97) -> 0 | F98: =D98-E98 -> 260000 | H98: Subtotal | J98: =SUM(J91:J97) -> 0 | K98: =SUM(K91:K97) -> 0 | L98: =J98-K98 -> 0
B100: OTROS 4 | C100: Ahorro | D100: Presupuesto | E100: Gasto | F100: Disponible | H100: OTROS 5 | I100: Ahorro | J100: Presupuesto | K100: Gasto | L100: Disponible
E101: =SUMIFS('Enero - registro gastos'!$D$3:$D$300,'Enero - registro gastos'!$E$3:$E$300,Ene!$B$100,'Enero - registro gastos'!$F$3:$F$300,Ene!B101) -> 0 | F101: =D101-E101 -> 0 | K101: =SUMIFS('Enero - registro gastos'!$D$3:$D$300,'Enero - registro gastos'!$E$3:$E$300,Ene!$H$100,'Enero - registro gastos'!$F$3:$F$300,Ene!H101) -> 0 | L101: =J101-K101 -> 0
E102: =SUMIFS('Enero - registro gastos'!$D$3:$D$300,'Enero - registro gastos'!$E$3:$E$300,Ene!$B$100,'Enero - registro gastos'!$F$3:$F$300,Ene!B102) -> 0 | F102: =D102-E102 -> 0 | K102: =SUMIFS('Enero - registro gastos'!$D$3:$D$300,'Enero - registro gastos'!$E$3:$E$300,Ene!$H$100,'Enero - registro gastos'!$F$3:$F$300,Ene!H102) -> 0 | L102: =J102-K102 -> 0
E103: =SUMIFS('Enero - registro gastos'!$D$3:$D$300,'Enero - registro gastos'!$E$3:$E$300,Ene!$B$100,'Enero - registro gastos'!$F$3:$F$300,Ene!B103) -> 0 | F103: =D103-E103 -> 0 | K103: =SUMIFS('Enero - registro gastos'!$D$3:$D$300,'Enero - registro gastos'!$E$3:$E$300,Ene!$H$100,'Enero - registro gastos'!$F$3:$F$300,Ene!H103) -> 0 | L103: =J103-K103 -> 0
E104: =SUMIFS('Enero - registro gastos'!$D$3:$D$300,'Enero - registro gastos'!$E$3:$E$300,Ene!$B$100,'Enero - registro gastos'!$F$3:$F$300,Ene!B104) -> 0 | F104: =D104-E104 -> 0 | K104: =SUMIFS('Enero - registro gastos'!$D$3:$D$300,'Enero - registro gastos'!$E$3:$E$300,Ene!$H$100,'Enero - registro gastos'!$F$3:$F$300,Ene!H104) -> 0 | L104: =J104-K104 -> 0
E105: =SUMIFS('Enero - registro gastos'!$D$3:$D$300,'Enero - registro gastos'!$E$3:$E$300,Ene!$B$100,'Enero - registro gastos'!$F$3:$F$300,Ene!B105) -> 0 | F105: =D105-E105 -> 0 | K105: =SUMIFS('Enero - registro gastos'!$D$3:$D$300,'Enero - registro gastos'!$E$3:$E$300,Ene!$H$100,'Enero - registro gastos'!$F$3:$F$300,Ene!H105) -> 0 | L105: =J105-K105 -> 0
E106: =SUMIFS('Enero - registro gastos'!$D$3:$D$300,'Enero - registro gastos'!$E$3:$E$300,Ene!$B$100,'Enero - registro gastos'!$F$3:$F$300,Ene!B106) -> 0 | F106: =D106-E106 -> 0 | K106: =SUMIFS('Enero - registro gastos'!$D$3:$D$300,'Enero - registro gastos'!$E$3:$E$300,Ene!$H$100,'Enero - registro gastos'!$F$3:$F$300,Ene!H106) -> 0 | L106: =J106-K106 -> 0
E107: =SUMIFS('Enero - registro gastos'!$D$3:$D$300,'Enero - registro gastos'!$E$3:$E$300,Ene!$B$100,'Enero - registro gastos'!$F$3:$F$300,Ene!B107) -> 0 | F107: =D107-E107 -> 0 | K107: =SUMIFS('Enero - registro gastos'!$D$3:$D$300,'Enero - registro gastos'!$E$3:$E$300,Ene!$H$100,'Enero - registro gastos'!$F$3:$F$300,Ene!H107) -> 0 | L107: =J107-K107 -> 0
B108: Subtotal | D108: =SUM(D101:D107) -> 0 | E108: =SUM(E101:E107) -> 0 | F108: =D108-E108 -> 0 | H108: Subtotal | J108: =SUM(J101:J107) -> 0 | K108: =SUM(K101:K107) -> 0 | L108: =J108-K108 -> 0

Sheet Enero - registro gastos
B2: Fecha | C2: Compra | D2: Valor | E2: Categoría | F2: Sub Categoría | J2: Categoría
B3: 45658 | C3: Transferencia a Andrés BBC y Ramen | D3: 63000 | E3: ALIMENTACIÓN | F3: Restaurantes | H3: =E3&F3 -> ALIMENTACIÓNRestaurantes | I3: =IFERROR(VLOOKUP(H3,$AP:$AQ,2,FALSE),"Error") -> ALIMENTACIÓNRestaurantes | J3: =IF(I3="Error","Revisa tu subcategoria",IF(I3=H3,"Es correcto",IF(H3="blanco","",""))) -> Es correcto | AN3: CATEGORÍA | AO3: SUBCATEGORIA
B4: 45659 | C4: Tabla de Quesos | D4: 54270 | E4: ALIMENTACIÓN | F4: Restaurantes | H4: =E4&F4 -> ALIMENTACIÓNRestaurantes | I4: =IFERROR(VLOOKUP(H4,$AP:$AQ,2,FALSE),"Error") -> ALIMENTACIÓNRestaurantes | J4: =IF(I4="Error","Revisa tu subcategoria",IF(I4=H4,"Es correcto",IF(H4="blanco","",""))) -> Es correcto | AN4: =Ene!$B$12 -> NECESIDADES BÁSICAS | AO4: =Ene!B13 -> Arriendo/Hipoteca | AP4: =AN4&AO4 -> NECESIDADES BÁSICASArriendo/Hipoteca | AQ4: =AP4 -> NECESIDADES BÁSICASArriendo/Hipoteca
B5: 45660 | C5: papitas y cositas | D5: =28620+5000 -> 33620 | E5: ALIMENTACIÓN | F5: Restaurantes | H5: =E5&F5 -> ALIMENTACIÓNRestaurantes | I5: =IFERROR(VLOOKUP(H5,$AP:$AQ,2,FALSE),"Error") -> ALIMENTACIÓNRestaurantes | J5: =IF(I5="Error","Revisa tu subcategoria",IF(I5=H5,"Es correcto",IF(H5="blanco","",""))) -> Es correcto | AN5: =Ene!$B$12 -> NECESIDADES BÁSICAS | AO5: =Ene!B14 -> Telefono/ Celular | AP5: =AN5&AO5 -> NECESIDADES BÁSICASTelefono/ Celular | AQ5: =AP5 -> NECESIDADES BÁSICASTelefono/ Celular
B6: 45660 | C6: Cobro automatico | D6: 55000 | E6: REGALOS/ CARIDAD | F6: Caridad | H6: =E6&F6 -> REGALOS/ CARIDADCaridad | I6: =IFERROR(VLOOKUP(H6,$AP:$AQ,2,FALSE),"Error") -> REGALOS/ CARIDADCaridad | J6: =IF(I6="Error","Revisa tu subcategoria",IF(I6=H6,"Es correcto",IF(H6="blanco","",""))) -> Es correcto | AN6: =Ene!$B$12 -> NECESIDADES BÁSICAS | AO6: =Ene!B15 -> Electricidad | AP6: =AN6&AO6 -> NECESIDADES BÁSICASElectricidad | AQ6: =AP6 -> NECESIDADES BÁSICASElectricidad
B7: 45660 | C7: Cobro automatico | D7: 14950 | E7: ENTRETENIMIENTO | F7: hbo | H7: =E7&F7 -> ENTRETENIMIENTOhbo | I7: =IFERROR(VLOOKUP(H7,$AP:$AQ,2,FALSE),"Error") -> ENTRETENIMIENTOhbo | J7: =IF(I7="Error","Revisa tu subcategoria",IF(I7=H7,"Es correcto",IF(H7="blanco","",""))) -> Es correcto | AN7: =Ene!$B$12 -> NECESIDADES BÁSICAS | AO7: =Ene!B16 -> Agua | AP7: =AN7&AO7 -> NECESIDADES BÁSICASAgua | AQ7: =AP7 -> NECESIDADES BÁSICASAgua
B8: 45660 | C8: Cobro automatico | D8: 44900 | E8: ENTRETENIMIENTO | F8: Netflix | H8: =E8&F8 -> ENTRETENIMIENTONetflix | I8: =IFERROR(VLOOKUP(H8,$AP:$AQ,2,FALSE),"Error") -> ENTRETENIMIENTONetflix | J8: =IF(H8=I8,"Es correcto","Revisa tu subcategoria") -> Es correcto | AN8: =Ene!$B$12 -> NECESIDADES BÁSICAS | AO8: =Ene!B17 -> Gas | AP8: =AN8&AO8 -> NECESIDADES BÁSICASGas | AQ8: =AP8 -> NECESIDADES BÁSICASGas
B9: 45660 | C9: Pago mes | D9: 142988 | E9: NECESIDADES BÁSICAS | F9: Cable/Internet | H9: =E9&F9 -> NECESIDADES BÁSICASCable/Internet | I9: =IFERROR(VLOOKUP(H9,$AP:$AQ,2,FALSE),"Error") -> NECESIDADES BÁSICASCable/Internet | J9: =IF(H9=I9,"Es correcto","Revisa tu subcategoria") -> Es correcto | AN9: =Ene!$B$12 -> NECESIDADES BÁSICAS | AO9: =Ene!B18 -> Cable/Internet | AP9: =AN9&AO9 -> NECESIDADES BÁSICASCable/Internet | AQ9: =AP9 -> NECESIDADES BÁSICASCable/Internet
B10: 45660 | C10: Pago mes | D10: 148241.73 | E10: ENTRETENIMIENTO | F10: Deporte | H10: =E10&F10 -> ENTRETENIMIENTODeporte | I10: =IFERROR(VLOOKUP(H10,$AP:$AQ,2,FALSE),"Error") -> ENTRETENIMIENTODeporte | J10: =IF(H10=I10,"Es correcto","Revisa tu subcategoria") -> Es correcto | AN10: =Ene!$B$12 -> NECESIDADES BÁSICAS | AO10: =Ene!B19 -> Super Mercado | AP10: =AN10&AO10 -> NECESIDADES BÁSICASSuper Mercado | AQ10: =AP10 -> NECESIDADES BÁSICASSuper Mercado
B11: 45660 | C11: Pago mes | D11: 77988 | E11: NECESIDADES BÁSICAS | F11: Telefono/ Celular | H11: =E11&F11 -> NECESIDADES BÁSICASTelefono/ Celular | I11: =IFERROR(VLOOKUP(H11,$AP:$AQ,2,FALSE),"Error") -> NECESIDADES BÁSICASTelefono/ Celular | J11: =IF(H11=I11,"Es correcto","Revisa tu subcategoria") -> Es correcto | AN11: =Ene!$B$12 -> NECESIDADES BÁSICAS | AO11: =Ene!B20 -> Gasolina | AP11: =AN11&AO11 -> NECESIDADES BÁSICASGasolina | AQ11: =AP11 -> NECESIDADES BÁSICASGasolina
B12: 45660 | C12: Pago mes | D12: 28650 | E12: ALIMENTACIÓN | F12: Rappi | H12: =E12&F12 -> ALIMENTACIÓNRappi | I12: =IFERROR(VLOOKUP(H12,$AP:$AQ,2,FALSE),"Error") -> ALIMENTACIÓNRappi | J12: =IF(H12=I12,"Es correcto","Revisa tu subcategoria") -> Es correcto | AN12: =Ene!$B$12 -> NECESIDADES BÁSICAS | AO12: =Ene!B21 -> Bus | AP12: =AN12&AO12 -> NECESIDADES BÁSICASBus | AQ12: =AP12 -> NECESIDADES BÁSICASBus
B13: 45661 | C13: Deudas Nu | D13: 3917064.8 | E13: DEUDAS | F13: Deuda tarjeta Un | H13: =E13&F13 -> DEUDASDeuda tarjeta Un | I13: =IFERROR(VLOOKUP(H13,$AP:$AQ,2,FALSE),"Error") -> DEUDASDeuda tarjeta Un | J13: =IF(H13=I13,"Es correcto","Revisa tu subcategoria") -> Es correcto | AN13: =Ene!$B$12 -> NECESIDADES BÁSICAS | AO13: =Ene!B22 -> 0 | AP13: =AN13&AO13 -> NECESIDADES BÁSICAS0 | AQ13: =AP13 -> NECESIDADES BÁSICAS0
B14: 45661 | C14: Apple | D14: 12900 | E14: ENTRETENIMIENTO | F14: Apple cloud | H14: =E14&F14 -> ENTRETENIMIENTOApple cloud | I14: =IFERROR(VLOOKUP(H14,$AP:$AQ,2,FALSE),"Error") -> ENTRETENIMIENTOApple cloud | J14: =IF(H14=I14,"Es correcto","Revisa tu subcategoria") -> Es correcto | AN14: =Ene!$B$12 -> NECESIDADES BÁSICAS | AO14: =Ene!B23 -> 0 | AP14: =AN14&AO14 -> NECESIDADES BÁSICAS0 | AQ14: =AP14 -> NECESIDADES BÁSICAS0
B15: 45659 | C15: Cine Avatar | D15: 144000 | E15: ENTRETENIMIENTO | F15: Cine | H15: =E15&F15 -> ENTRETENIMIENTOCine | I15: =IFERROR(VLOOKUP(H15,$AP:$AQ,2,FALSE),"Error") -> ENTRETENIMIENTOCine | J15: =IF(H15=I15,"Es correcto","Revisa tu subcategoria") -> Es correcto | AN15: =Ene!$B$12 -> NECESIDADES BÁSICAS | AO15: =Ene!B24 -> 0 | AP15: =AN15&AO15 -> NECESIDADES BÁSICAS0 | AQ15: =AP15 -> NECESIDADES BÁSICAS0
B16: 45663 | C16: Cine Zootopia | D16: 100000 | E16: ENTRETENIMIENTO | F16: Cine | H16: =E16&F16 -> ENTRETENIMIENTOCine | I16: =IFERROR(VLOOKUP(H16,$AP:$AQ,2,FALSE),"Error") -> ENTRETENIMIENTOCine | J16: =IF(H16=I16,"Es correcto","Revisa tu subcategoria") -> Es correcto | AN16: =Ene!$H$12 -> AHORROS | AO16: =Ene!H13 -> Efectivo | AP16: =AN16&AO16 -> AHORROSEfectivo | AQ16: =AP16 -> AHORROSEfectivo
H17: =E17&F17 | I17: =IFERROR(VLOOKUP(H17,$AP:$AQ,2,FALSE),"Error") -> Error | J17: =IF(H17=I17,"Es correcto","Revisa tu subcategoria") -> Revisa tu subcategoria | AN17: =Ene!$H$12 -> AHORROS | AO17: =Ene!H14 -> Cuenta Bancol | AP17: =AN17&AO17 -> AHORROSCuenta Bancol | AQ17: =AP17 -> AHORROSCuenta Bancol
H18: =E18&F18 | I18: =IFERROR(VLOOKUP(H18,$AP:$AQ,2,FALSE),"Error") -> Error | J18: =IF(H18=I18,"Es correcto","Revisa tu subcategoria") -> Revisa tu subcategoria | AN18: =Ene!$H$12 -> AHORROS | AO18: =Ene!H15 -> pension voluntaria ahorro casa | AP18: =AN18&AO18 -> AHORROSpension voluntaria ahorro casa | AQ18: =AP18 -> AHORROSpension voluntaria ahorro casa
H19: =E19&F19 | I19: =IFERROR(VLOOKUP(H19,$AP:$AQ,2,FALSE),"Error") -> Error | J19: =IF(H19=I19,"Es correcto","Revisa tu subcategoria") -> Revisa tu subcategoria | AN19: =Ene!$H$12 -> AHORROS | AO19: =Ene!H16 -> Investor trust 1200 | AP19: =AN19&AO19 -> AHORROSInvestor trust 1200 | AQ19: =AP19 -> AHORROSInvestor trust 1200
H20: =E20&F20 | I20: =IFERROR(VLOOKUP(H20,$AP:$AQ,2,FALSE),"Error") -> Error | J20: =IF(H20=I20,"Es correcto","Revisa tu subcategoria") -> Revisa tu subcategoria | AN20: =Ene!$H$12 -> AHORROS | AO20: =Ene!H17 -> Investor trust 2400 | AP20: =AN20&AO20 -> AHORROSInvestor trust 2400 | AQ20: =AP20 -> AHORROSInvestor trust 2400
H21: =E21&F21 | I21: =IFERROR(VLOOKUP(H21,$AP:$AQ,2,FALSE),"Error") -> Error | J21: =IF(H21=I21,"Es correcto","Revisa tu subcategoria") -> Revisa tu subcategoria | AN21: =Ene!$H$12 -> AHORROS | AO21: =Ene!H18 -> poliza pensiones skandia | AP21: =AN21&AO21 -> AHORROSpoliza pensiones skandia | AQ21: =AP21 -> AHORROSpoliza pensiones skandia
H22: =E22&F22 | I22: =IFERROR(VLOOKUP(H22,$AP:$AQ,2,FALSE),"Error") -> Error | J22: =IF(H22=I22,"Es correcto","Revisa tu subcategoria") -> Revisa tu subcategoria | AN22: =Ene!$H$12 -> AHORROS | AO22: =Ene!H19 -> Fondo de emergencia lulo | AP22: =AN22&AO22 -> AHORROSFondo de emergencia lulo | AQ22: =AP22 -> AHORROSFondo de emergencia lulo
H23: =E23&F23 | I23: =IFERROR(VLOOKUP(H23,$AP:$AQ,2,FALSE),"Error") -> Error | J23: =IF(H23=I23,"Es correcto","Revisa tu subcategoria") -> Revisa tu subcategoria | AN23: =Ene!$H$12 -> AHORROS | AO23: =Ene!H20 -> Littio | AP23: =AN23&AO23 -> AHORROSLittio | AQ23: =AP23 -> AHORROSLittio
H24: =E24&F24 | I24: =IFERROR(VLOOKUP(H24,$AP:$AQ,2,FALSE),"Error") -> Error | J24: =IF(H24=I24,"Es correcto","Revisa tu subcategoria") -> Revisa tu subcategoria | AN24: =Ene!$H$12 -> AHORROS | AO24: =Ene!H21 -> Nequi | AP24: =AN24&AO24 -> AHORROSNequi | AQ24: =AP24 -> AHORROSNequi
H25: =E25&F25 | I25: =IFERROR(VLOOKUP(H25,$AP:$AQ,2,FALSE),"Error") -> Error | J25: =IF(H25=I25,"Es correcto","Revisa tu subcategoria") -> Revisa tu subcategoria | AN25: =Ene!$H$12 -> AHORROS | AO25: =Ene!H22 -> viajes varios | AP25: =AN25&AO25 -> AHORROSviajes varios | AQ25: =AP25 -> AHORROSviajes varios
H26: =E26&F26 | I26: =IFERROR(VLOOKUP(H26,$AP:$AQ,2,FALSE),"Error") -> Error | J26: =IF(H26=I26,"Es correcto","Revisa tu subcategoria") -> Revisa tu subcategoria | AN26: =Ene!$H$12 -> AHORROS | AO26: =Ene!H23 -> Viaje Japon lulo | AP26: =AN26&AO26 -> AHORROSViaje Japon lulo | AQ26: =AP26 -> AHORROSViaje Japon lulo
H27: =E27&F27 | I27: =IFERROR(VLOOKUP(H27,$AP:$AQ,2,FALSE),"Error") -> Error | J27: =IF(H27=I27,"Es correcto","Revisa tu subcategoria") -> Revisa tu subcategoria | AN27: =Ene!$H$12 -> AHORROS | AO27: =Ene!H24 -> Viaje Estados unidos lulo | AP27: =AN27&AO27 -> AHORROSViaje Estados unidos lulo | AQ27: =AP27 -> AHORROSViaje Estados unidos lulo
H28: =E28&F28 | I28: =IFERROR(VLOOKUP(H28,$AP:$AQ,2,FALSE),"Error") -> Error | J28: =IF(H28=I28,"Es correcto","Revisa tu subcategoria") -> Revisa tu subcategoria | AN28: =Ene!$B$27 -> DEUDAS | AO28: =Ene!B28 -> Deuda Carro | AP28: =AN28&AO28 -> DEUDASDeuda Carro | AQ28: =AP28 -> DEUDASDeuda Carro
H29: =E29&F29 | I29: =IFERROR(VLOOKUP(H29,$AP:$AQ,2,FALSE),"Error") -> Error | J29: =IF(H29=I29,"Es correcto","Revisa tu subcategoria") -> Revisa tu subcategoria | AN29: =Ene!$B$27 -> DEUDAS | AO29: =Ene!B29 -> Deuda tarjeta Un | AP29: =AN29&AO29 -> DEUDASDeuda tarjeta Un | AQ29: =AP29 -> DEUDASDeuda tarjeta Un
H30: =E30&F30 | I30: =IFERROR(VLOOKUP(H30,$AP:$AQ,2,FALSE),"Error") -> Error | J30: =IF(H30=I30,"Es correcto","Revisa tu subcategoria") -> Revisa tu subcategoria | AN30: =Ene!$B$27 -> DEUDAS | AO30: =Ene!B30 -> Deuda Banco de occidente | AP30: =AN30&AO30 -> DEUDASDeuda Banco de occidente | AQ30: =AP30 -> DEUDASDeuda Banco de occidente
H31: =E31&F31 | I31: =IFERROR(VLOOKUP(H31,$AP:$AQ,2,FALSE),"Error") -> Error | J31: =IF(H31=I31,"Es correcto","Revisa tu subcategoria") -> Revisa tu subcategoria | AN31: =Ene!$B$27 -> DEUDAS | AO31: =Ene!B31 -> Deuda Estudio | AP31: =AN31&AO31 -> DEUDASDeuda Estudio | AQ31: =AP31 -> DEUDASDeuda Estudio
H32: =E32&F32 | I32: =IFERROR(VLOOKUP(H32,$AP:$AQ,2,FALSE),"Error") -> Error | J32: =IF(H32=I32,"Es correcto","Revisa tu subcategoria") -> Revisa tu subcategoria | AN32: =Ene!$B$27 -> DEUDAS | AO32: =Ene!B32 -> Carro | AP32: =AN32&AO32 -> DEUDASCarro | AQ32: =AP32 -> DEUDASCarro
H33: =E33&F33 | I33: =IFERROR(VLOOKUP(H33,$AP:$AQ,2,FALSE),"Error") -> Error | J33: =IF(H33=I33,"Es correcto","Revisa tu subcategoria") -> Revisa tu subcategoria | AN33: =Ene!$B$27 -> DEUDAS | AO33: =Ene!B33 -> 0 | AP33: =AN33&AO33 -> DEUDAS0 | AQ33: =AP33 -> DEUDAS0
H34: =E34&F34 | I34: =IFERROR(VLOOKUP(H34,$AP:$AQ,2,FALSE),"Error") -> Error | J34: =IF(H34=I34,"Es correcto","Revisa tu subcategoria") -> Revisa tu subcategoria | AN34: =Ene!$B$27 -> DEUDAS | AO34: =Ene!B34 -> 0 | AP34: =AN34&AO34 -> DEUDAS0 | AQ34: =AP34 -> DEUDAS0
H35: =E35&F35 | I35: =IFERROR(VLOOKUP(H35,$AP:$AQ,2,FALSE),"Error") -> Error | J35: =IF(H35=I35,"Es correcto","Revisa tu subcategoria") -> Revisa tu subcategoria | AN35: =Ene!$B$27 -> DEUDAS | AO35: =Ene!B35 -> 0 | AP35: =AN35&AO35 -> DEUDAS0 | AQ35: =AP35 -> DEUDAS0
H36: =E36&F36 | I36: =IFERROR(VLOOKUP(H36,$AP:$AQ,2,FALSE),"Error") -> Error | J36: =IF(H36=I36,"Es correcto","Revisa tu subcategoria") -> Revisa tu subcategoria | AN36: =Ene!$H$27 -> REGALOS/ CARIDAD | AO36: =Ene!H28 -> Regalos Navidad | AP36: =AN36&AO36 -> REGALOS/ CARIDADRegalos Navidad | AQ36: =AP36 -> REGALOS/ CARIDADRegalos Navidad
H37: =E37&F37 | I37: =IFERROR(VLOOKUP(H37,$AP:$AQ,2,FALSE),"Error") -> Error | J37: =IF(H37=I37,"Es correcto","Revisa tu subcategoria") -> Revisa tu subcategoria | AN37: =Ene!$H$27 -> REGALOS/ CARIDAD | AO37: =Ene!H29 -> Regalos cumpleaños | AP37: =AN37&AO37 -> REGALOS/ CARIDADRegalos cumpleaños | AQ37: =AP37 -> REGALOS/ CARIDADRegalos cumpleaños
H38: =E38&F38 | I38: =IFERROR(VLOOKUP(H38,$AP:$AQ,2,FALSE),"Error") -> Error | J38: =IF(H38=I38,"Es correcto","Revisa tu subcategoria") -> Revisa tu subcategoria | AN38: =Ene!$H$27 -> REGALOS/ CARIDAD | AO38: =Ene!H30 -> Caridad | AP38: =AN38&AO38 -> REGALOS/ CARIDADCaridad | AQ38: =AP38 -> REGALOS/ CARIDADCaridad
H39: =E39&F39 | I39: =IFERROR(VLOOKUP(H39,$AP:$AQ,2,FALSE),"Error") -> Error | J39: =IF(H39=I39,"Es correcto","Revisa tu subcategoria") -> Revisa tu subcategoria | AN39: =Ene!$H$27 -> REGALOS/ CARIDAD | AO39: =Ene!H31 -> 0 | AP39: =AN39&AO39 -> REGALOS/ CARIDAD0 | AQ39: =AP39 -> REGALOS/ CARIDAD0
H40: =E40&F40 | I40: =IFERROR(VLOOKUP(H40,$AP:$AQ,2,FALSE),"Error") -> Error | J40: =IF(H40=I40,"Es correcto","Revisa tu subcategoria") -> Revisa tu subcategoria | AN40: =Ene!$H$27 -> REGALOS/ CARIDAD | AO40: =Ene!H32 -> 0 | AP40: =AN40&AO40 -> REGALOS/ CARIDAD0 | AQ40: =AP40 -> REGALOS/ CARIDAD0
H41: =E41&F41 | I41: =IFERROR(VLOOKUP(H41,$AP:$AQ,2,FALSE),"Error") -> Error | J41: =IF(H41=I41,"Es correcto","Revisa tu subcategoria") -> Revisa tu subcategoria | AN41: =Ene!$H$27 -> REGALOS/ CARIDAD | AO41: =Ene!H33 -> 0 | AP41: =AN41&AO41 -> REGALOS/ CARIDAD0 | AQ41: =AP41 -> REGALOS/ CARIDAD0
H42: =E42&F42 | I42: =IFERROR(VLOOKUP(H42,$AP:$AQ,2,FALSE),"Error") -> Error | J42: =IF(H42=I42,"Es correcto","Revisa tu subcategoria") -> Revisa tu subcategoria | AN42: =Ene!$H$27 -> REGALOS/ CARIDAD | AO42: =Ene!H34 -> 0 | AP42: =AN42&AO42 -> REGALOS/ CARIDAD0 | AQ42: =AP42 -> REGALOS/ CARIDAD0
H43: =E43&F43 | I43: =IFERROR(VLOOKUP(H43,$AP:$AQ,2,FALSE),"Error") -> Error | J43: =IF(H43=I43,"Es correcto","Revisa tu subcategoria") -> Revisa tu subcategoria | AN43: =Ene!$H$27 -> REGALOS/ CARIDAD | AO43: =Ene!H35 -> 0 | AP43: =AN43&AO43 -> REGALOS/ CARIDAD0 | AQ43: =AP43 -> REGALOS/ CARIDAD0
H44: =E44&F44 | I44: =IFERROR(VLOOKUP(H44,$AP:$AQ,2,FALSE),"Error") -> Error | J44: =IF(H44=I44,"Es correcto","Revisa tu subcategoria") -> Revisa tu subcategoria | AN44: =Ene!$B$38 -> CASA | AO44: =Ene!B39 -> Limpieza | AP44: =AN44&AO44 -> CASALimpieza | AQ44: =AP44 -> CASALimpieza
H45: =E45&F45 | I45: =IFERROR(VLOOKUP(H45,$AP:$AQ,2,FALSE),"Error") -> Error | J45: =IF(H45=I45,"Es correcto","Revisa tu subcategoria") -> Revisa tu subcategoria | AN45: =Ene!$B$38 -> CASA | AO45: =Ene!B40 -> Mantenimiento | AP45: =AN45&AO45 -> CASAMantenimiento | AQ45: =AP45 -> CASAMantenimiento
H46: =E46&F46 | I46: =IFERROR(VLOOKUP(H46,$AP:$AQ,2,FALSE),"Error") -> Error | J46: =IF(H46=I46,"Es correcto","Revisa tu subcategoria") -> Revisa tu subcategoria | AN46: =Ene!$B$38 -> CASA | AO46: =Ene!B41 -> Muebles | AP46: =AN46&AO46 -> CASAMuebles | AQ46: =AP46 -> CASAMuebles
H47: =E47&F47 | I47: =IFERROR(VLOOKUP(H47,$AP:$AQ,2,FALSE),"Error") -> Error | J47: =IF(H47=I47,"Es correcto","Revisa tu subcategoria") -> Revisa tu subcategoria | AN47: =Ene!$B$38 -> CASA | AO47: =Ene!B42 -> Impuestos | AP47: =AN47&AO47 -> CASAImpuestos | AQ47: =AP47 -> CASAImpuestos
H48: =E48&F48 | I48: =IFERROR(VLOOKUP(H48,$AP:$AQ,2,FALSE),"Error") -> Error | J48: =IF(H48=I48,"Es correcto","Revisa tu subcategoria") -> Revisa tu subcategoria | AN48: =Ene!$B$38 -> CASA | AO48: =Ene!B43 -> 0 | AP48: =AN48&AO48 -> CASA0 | AQ48: =AP48 -> CASA0
H49: =E49&F49 | I49: =IFERROR(VLOOKUP(H49,$AP:$AQ,2,FALSE),"Error") -> Error | J49: =IF(H49=I49,"Es correcto","Revisa tu subcategoria") -> Revisa tu subcategoria | AN49: =Ene!$B$38 -> CASA | AO49: =Ene!B44 -> 0 | AP49: =AN49&AO49 -> CASA0 | AQ49: =AP49 -> CASA0
H50: =E50&F50 | I50: =IFERROR(VLOOKUP(H50,$AP:$AQ,2,FALSE),"Error") -> Error | J50: =IF(H50=I50,"Es correcto","Revisa tu subcategoria") -> Revisa tu subcategoria | AN50: =Ene!$B$38 -> CASA | AO50: =Ene!B45 -> 0 | AP50: =AN50&AO50 -> CASA0 | AQ50: =AP50 -> CASA0
H51: =E51&F51 | I51: =IFERROR(VLOOKUP(H51,$AP:$AQ,2,FALSE),"Error") -> Error | J51: =IF(H51=I51,"Es correcto","Revisa tu subcategoria") -> Revisa tu subcategoria | AN51: =Ene!$H$38 -> TRANSPORTE | AO51: =Ene!H39 -> Uber/taxi | AP51: =AN51&AO51 -> TRANSPORTEUber/taxi | AQ51: =AP51 -> TRANSPORTEUber/taxi
H52: =E52&F52 | I52: =IFERROR(VLOOKUP(H52,$AP:$AQ,2,FALSE),"Error") -> Error | J52: =IF(H52=I52,"Es correcto","Revisa tu subcategoria") -> Revisa tu subcategoria | AN52: =Ene!$H$38 -> TRANSPORTE | AO52: =Ene!H40 -> Estacionamiento | AP52: =AN52&AO52 -> TRANSPORTEEstacionamiento | AQ52: =AP52 -> TRANSPORTEEstacionamiento
H53: =E53&F53 | I53: =IFERROR(VLOOKUP(H53,$AP:$AQ,2,FALSE),"Error") -> Error | J53: =IF(H53=I53,"Es correcto","Revisa tu subcategoria") -> Revisa tu subcategoria | AN53: =Ene!$H$38 -> TRANSPORTE | AO53: =Ene!H41 -> Mantenimiento | AP53: =AN53&AO53 -> TRANSPORTEMantenimiento | AQ53: =AP53 -> TRANSPORTEMantenimiento
H54: =E54&F54 | I54: =IFERROR(VLOOKUP(H54,$AP:$AQ,2,FALSE),"Error") -> Error | J54: =IF(H54=I54,"Es correcto","Revisa tu subcategoria") -> Revisa tu subcategoria | AN54: =Ene!$H$38 -> TRANSPORTE | AO54: =Ene!H42 -> Impuestos lulo | AP54: =AN54&AO54 -> TRANSPORTEImpuestos lulo | AQ54: =AP54 -> TRANSPORTEImpuestos lulo
H55: =E55&F55 | I55: =IFERROR(VLOOKUP(H55,$AP:$AQ,2,FALSE),"Error") -> Error | J55: =IF(H55=I55,"Es correcto","Revisa tu subcategoria") -> Revisa tu subcategoria | AN55: =Ene!$H$38 -> TRANSPORTE | AO55: =Ene!H43 -> Panapass/Peaje | AP55: =AN55&AO55 -> TRANSPORTEPanapass/Peaje | AQ55: =AP55 -> TRANSPORTEPanapass/Peaje
H56: =E56&F56 | I56: =IFERROR(VLOOKUP(H56,$AP:$AQ,2,FALSE),"Error") -> Error | J56: =IF(H56=I56,"Es correcto","Revisa tu subcategoria") -> Revisa tu subcategoria | AN56: =Ene!$H$38 -> TRANSPORTE | AO56: =Ene!H44 -> 0 | AP56: =AN56&AO56 -> TRANSPORTE0 | AQ56: =AP56 -> TRANSPORTE0
H57: =E57&F57 | I57: =IFERROR(VLOOKUP(H57,$AP:$AQ,2,FALSE),"Error") -> Error | J57: =IF(H57=I57,"Es correcto","Revisa tu subcategoria") -> Revisa tu subcategoria | AN57: =Ene!$H$38 -> TRANSPORTE | AO57: =Ene!H45 -> 0 | AP57: =AN57&AO57 -> TRANSPORTE0 | AQ57: =AP57 -> TRANSPORTE0
H58: =E58&F58 | I58: =IFERROR(VLOOKUP(H58,$AP:$AQ,2,FALSE),"Error") -> Error | J58: =IF(H58=I58,"Es correcto","Revisa tu subcategoria") -> Revisa tu subcategoria | AN58: =Ene!$B$48 -> ALIMENTACIÓN | AO58: =Ene!B49 -> Restaurantes | AP58: =AN58&AO58 -> ALIMENTACIÓNRestaurantes | AQ58: =AP58 -> ALIMENTACIÓNRestaurantes
H59: =E59&F59 | I59: =IFERROR(VLOOKUP(H59,$AP:$AQ,2,FALSE),"Error") -> Error | J59: =IF(H59=I59,"Es correcto","Revisa tu subcategoria") -> Revisa tu subcategoria | AN59: =Ene!$B$48 -> ALIMENTACIÓN | AO59: =Ene!B50 -> Café/ Snacks | AP59: =AN59&AO59 -> ALIMENTACIÓNCafé/ Snacks | AQ59: =AP59 -> ALIMENTACIÓNCafé/ Snacks
H60: =E60&F60 | I60: =IFERROR(VLOOKUP(H60,$AP:$AQ,2,FALSE),"Error") -> Error | J60: =IF(H60=I60,"Es correcto","Revisa tu subcategoria") -> Revisa tu subcategoria | AN60: =Ene!$B$48 -> ALIMENTACIÓN | AO60: =Ene!B51 -> Rappi | AP60: =AN60&AO60 -> ALIMENTACIÓNRappi | AQ60: =AP60 -> ALIMENTACIÓNRappi
H61: =E61&F61 | I61: =IFERROR(VLOOKUP(H61,$AP:$AQ,2,FALSE),"Error") -> Error | J61: =IF(H61=I61,"Es correcto","Revisa tu subcategoria") -> Revisa tu subcategoria | AN61: =Ene!$B$48 -> ALIMENTACIÓN | AO61: =Ene!B52 -> 0 | AP61: =AN61&AO61 -> ALIMENTACIÓN0 | AQ61: =AP61 -> ALIMENTACIÓN0
H62: =E62&F62 | I62: =IFERROR(VLOOKUP(H62,$AP:$AQ,2,FALSE),"Error") -> Error | J62: =IF(H62=I62,"Es correcto","Revisa tu subcategoria") -> Revisa tu subcategoria | AN62: =Ene!$B$48 -> ALIMENTACIÓN | AO62: =Ene!B53 -> 0 | AP62: =AN62&AO62 -> ALIMENTACIÓN0 | AQ62: =AP62 -> ALIMENTACIÓN0
H63: =E63&F63 | I63: =IFERROR(VLOOKUP(H63,$AP:$AQ,2,FALSE),"Error") -> Error | J63: =IF(H63=I63,"Es correcto","Revisa tu subcategoria") -> Revisa tu subcategoria | AN63: =Ene!$B$48 -> ALIMENTACIÓN | AO63: =Ene!B54 -> 0 | AP63: =AN63&AO63 -> ALIMENTACIÓN0 | AQ63: =AP63 -> ALIMENTACIÓN0
H64: =E64&F64 | I64: =IFERROR(VLOOKUP(H64,$AP:$AQ,2,FALSE),"Error") -> Error | J64: =IF(H64=I64,"Es correcto","Revisa tu subcategoria") -> Revisa tu subcategoria | AN64: =Ene!$H$48 -> SEGUROS | AO64: =Ene!H49 -> Carro lulo | AP64: =AN64&AO64 -> SEGUROSCarro lulo | AQ64: =AP64 -> SEGUROSCarro lulo
H65: =E65&F65 | I65: =IFERROR(VLOOKUP(H65,$AP:$AQ,2,FALSE),"Error") -> Error | J65: =IF(H65=I65,"Es correcto","Revisa tu subcategoria") -> Revisa tu subcategoria | AN65: =Ene!$H$48 -> SEGUROS | AO65: =Ene!H50 -> Vida | AP65: =AN65&AO65 -> SEGUROSVida | AQ65: =AP65 -> SEGUROSVida
H66: =E66&F66 | I66: =IFERROR(VLOOKUP(H66,$AP:$AQ,2,FALSE),"Error") -> Error | J66: =IF(H66=I66,"Es correcto","Revisa tu subcategoria") -> Revisa tu subcategoria | AN66: =Ene!$H$48 -> SEGUROS | AO66: =Ene!H51 -> Casa | AP66: =AN66&AO66 -> SEGUROSCasa | AQ66: =AP66 -> SEGUROSCasa
H67: =E67&F67 | I67: =IFERROR(VLOOKUP(H67,$AP:$AQ,2,FALSE),"Error") -> Error | J67: =IF(H67=I67,"Es correcto","Revisa tu subcategoria") -> Revisa tu subcategoria | AN67: =Ene!$H$48 -> SEGUROS | AO67: =Ene!H52 -> Salud | AP67: =AN67&AO67 -> SEGUROSSalud | AQ67: =AP67 -> SEGUROSSalud
H68: =E68&F68 | I68: =IFERROR(VLOOKUP(H68,$AP:$AQ,2,FALSE),"Error") -> Error | J68: =IF(H68=I68,"Es correcto","Revisa tu subcategoria") -> Revisa tu subcategoria | AN68: =Ene!$H$48 -> SEGUROS | AO68: =Ene!H53 -> 0 | AP68: =AN68&AO68 -> SEGUROS0 | AQ68: =AP68 -> SEGUROS0
H69: =E69&F69 | I69: =IFERROR(VLOOKUP(H69,$AP:$AQ,2,FALSE),"Error") -> Error | J69: =IF(H69=I69,"Es correcto","Revisa tu subcategoria") -> Revisa tu subcategoria | AN69: =Ene!$H$48 -> SEGUROS | AO69: =Ene!H54 -> 0 | AP69: =AN69&AO69 -> SEGUROS0 | AQ69: =AP69 -> SEGUROS0
H70: =E70&F70 | I70: =IFERROR(VLOOKUP(H70,$AP:$AQ,2,FALSE),"Error") -> Error | J70: =IF(H70=I70,"Es correcto","Revisa tu subcategoria") -> Revisa tu subcategoria | AN70: =Ene!$B$57 -> SALUD | AO70: =Ene!B58 -> Medicinas | AP70: =AN70&AO70 -> SALUDMedicinas | AQ70: =AP70 -> SALUDMedicinas
H71: =E71&F71 | I71: =IFERROR(VLOOKUP(H71,$AP:$AQ,2,FALSE),"Error") -> Error | J71: =IF(H71=I71,"Es correcto","Revisa tu subcategoria") -> Revisa tu subcategoria | AN71: =Ene!$B$57 -> SALUD | AO71: =Ene!B59 -> Dentista | AP71: =AN71&AO71 -> SALUDDentista | AQ71: =AP71 -> SALUDDentista
H72: =E72&F72 | I72: =IFERROR(VLOOKUP(H72,$AP:$AQ,2,FALSE),"Error") -> Error | J72: =IF(H72=I72,"Es correcto","Revisa tu subcategoria") -> Revisa tu subcategoria | AN72: =Ene!$B$57 -> SALUD | AO72: =Ene!B60 -> Tratamientos | AP72: =AN72&AO72 -> SALUDTratamientos | AQ72: =AP72 -> SALUDTratamientos
H73: =E73&F73 | I73: =IFERROR(VLOOKUP(H73,$AP:$AQ,2,FALSE),"Error") -> Error | J73: =IF(H73=I73,"Es correcto","Revisa tu subcategoria") -> Revisa tu subcategoria | AN73: =Ene!$B$57 -> SALUD | AO73: =Ene!B61 -> 0 | AP73: =AN73&AO73 -> SALUD0 | AQ73: =AP73 -> SALUD0
H74: =E74&F74 | I74: =IFERROR(VLOOKUP(H74,$AP:$AQ,2,FALSE),"Error") -> Error | J74: =IF(H74=I74,"Es correcto","Revisa tu subcategoria") -> Revisa tu subcategoria | AN74: =Ene!$B$57 -> SALUD | AO74: =Ene!B62 -> 0 | AP74: =AN74&AO74 -> SALUD0 | AQ74: =AP74 -> SALUD0
H75: =E75&F75 | I75: =IFERROR(VLOOKUP(H75,$AP:$AQ,2,FALSE),"Error") -> Error | J75: =IF(H75=I75,"Es correcto","Revisa tu subcategoria") -> Revisa tu subcategoria | AN75: =Ene!$B$57 -> SALUD | AO75: =Ene!B63 -> 0 | AP75: =AN75&AO75 -> SALUD0 | AQ75: =AP75 -> SALUD0
H76: =E76&F76 | I76: =IFERROR(VLOOKUP(H76,$AP:$AQ,2,FALSE),"Error") -> Error | J76: =IF(H76=I76,"Es correcto","Revisa tu subcategoria") -> Revisa tu subcategoria | AN76: =Ene!$B$57 -> SALUD | AO76: =Ene!B64 -> 0 | AP76: =AN76&AO76 -> SALUD0 | AQ76: =AP76 -> SALUD0
H77: =E77&F77 | I77: =IFERROR(VLOOKUP(H77,$AP:$AQ,2,FALSE),"Error") -> Error | J77: =IF(H77=I77,"Es correcto","Revisa tu subcategoria") -> Revisa tu subcategoria | AN77: =Ene!$H$57 -> CUIDADO PERSONAL | AO77: =Ene!H58 -> Ropa | AP77: =AN77&AO77 -> CUIDADO PERSONALRopa | AQ77: =AP77 -> CUIDADO PERSONALRopa
H78: =E78&F78 | I78: =IFERROR(VLOOKUP(H78,$AP:$AQ,2,FALSE),"Error") -> Error | J78: =IF(H78=I78,"Es correcto","Revisa tu subcategoria") -> Revisa tu subcategoria | AN78: =Ene!$H$57 -> CUIDADO PERSONAL | AO78: =Ene!H59 -> Belleza | AP78: =AN78&AO78 -> CUIDADO PERSONALBelleza | AQ78: =AP78 -> CUIDADO PERSONALBelleza
H79: =E79&F79 | I79: =IFERROR(VLOOKUP(H79,$AP:$AQ,2,FALSE),"Error") -> Error | J79: =IF(H79=I79,"Es correcto","Revisa tu subcategoria") -> Revisa tu subcategoria | AN79: =Ene!$H$57 -> CUIDADO PERSONAL | AO79: =Ene!H60 -> Peluquería | AP79: =AN79&AO79 -> CUIDADO PERSONALPeluquería | AQ79: =AP79 -> CUIDADO PERSONALPeluquería
H80: =E80&F80 | I80: =IFERROR(VLOOKUP(H80,$AP:$AQ,2,FALSE),"Error") -> Error | J80: =IF(H80=I80,"Es correcto","Revisa tu subcategoria") -> Revisa tu subcategoria | AN80: =Ene!$H$57 -> CUIDADO PERSONAL | AO80: =Ene!H61 -> Sastre | AP80: =AN80&AO80 -> CUIDADO PERSONALSastre | AQ80: =AP80 -> CUIDADO PERSONALSastre
H81: =E81&F81 | I81: =IFERROR(VLOOKUP(H81,$AP:$AQ,2,FALSE),"Error") -> Error | J81: =IF(H81=I81,"Es correcto","Revisa tu subcategoria") -> Revisa tu subcategoria | AN81: =Ene!$H$57 -> CUIDADO PERSONAL | AO81: =Ene!H62 -> Tintorería | AP81: =AN81&AO81 -> CUIDADO PERSONALTintorería | AQ81: =AP81 -> CUIDADO PERSONALTintorería
H82: =E82&F82 | I82: =IFERROR(VLOOKUP(H82,$AP:$AQ,2,FALSE),"Error") -> Error | J82: =IF(H82=I82,"Es correcto","Revisa tu subcategoria") -> Revisa tu subcategoria | AN82: =Ene!$H$57 -> CUIDADO PERSONAL | AO82: =Ene!H63 -> 0 | AP82: =AN82&AO82 -> CUIDADO PERSONAL0 | AQ82: =AP82 -> CUIDADO PERSONAL0
H83: =E83&F83 | I83: =IFERROR(VLOOKUP(H83,$AP:$AQ,2,FALSE),"Error") -> Error | J83: =IF(H83=I83,"Es correcto","Revisa tu subcategoria") -> Revisa tu subcategoria | AN83: =Ene!$H$57 -> CUIDADO PERSONAL | AO83: =Ene!H64 -> 0 | AP83: =AN83&AO83 -> CUIDADO PERSONAL0 | AQ83: =AP83 -> CUIDADO PERSONAL0
H84: =E84&F84 | I84: =IFERROR(VLOOKUP(H84,$AP:$AQ,2,FALSE),"Error") -> Error | J84: =IF(H84=I84,"Es correcto","Revisa tu subcategoria") -> Revisa tu subcategoria | AN84: =Ene!$B$67 -> ENTRETENIMIENTO | AO84: =Ene!B68 -> Vacaciones | AP84: =AN84&AO84 -> ENTRETENIMIENTOVacaciones | AQ84: =AP84 -> ENTRETENIMIENTOVacaciones
H85: =E85&F85 | I85: =IFERROR(VLOOKUP(H85,$AP:$AQ,2,FALSE),"Error") -> Error | J85: =IF(H85=I85,"Es correcto","Revisa tu subcategoria") -> Revisa tu subcategoria | AN85: =Ene!$B$67 -> ENTRETENIMIENTO | AO85: =Ene!B69 -> Rumba | AP85: =AN85&AO85 -> ENTRETENIMIENTORumba | AQ85: =AP85 -> ENTRETENIMIENTORumba
H86: =E86&F86 | I86: =IFERROR(VLOOKUP(H86,$AP:$AQ,2,FALSE),"Error") -> Error | J86: =IF(H86=I86,"Es correcto","Revisa tu subcategoria") -> Revisa tu subcategoria | AN86: =Ene!$B$67 -> ENTRETENIMIENTO | AO86: =Ene!B70 -> Citas | AP86: =AN86&AO86 -> ENTRETENIMIENTOCitas | AQ86: =AP86 -> ENTRETENIMIENTOCitas
H87: =E87&F87 | I87: =IFERROR(VLOOKUP(H87,$AP:$AQ,2,FALSE),"Error") -> Error | J87: =IF(H87=I87,"Es correcto","Revisa tu subcategoria") -> Revisa tu subcategoria | AN87: =Ene!$B$67 -> ENTRETENIMIENTO | AO87: =Ene!B71 -> Cine | AP87: =AN87&AO87 -> ENTRETENIMIENTOCine | AQ87: =AP87 -> ENTRETENIMIENTOCine
H88: =E88&F88 | I88: =IFERROR(VLOOKUP(H88,$AP:$AQ,2,FALSE),"Error") -> Error | J88: =IF(H88=I88,"Es correcto","Revisa tu subcategoria") -> Revisa tu subcategoria | AN88: =Ene!$B$67 -> ENTRETENIMIENTO | AO88: =Ene!B72 -> Deporte | AP88: =AN88&AO88 -> ENTRETENIMIENTODeporte | AQ88: =AP88 -> ENTRETENIMIENTODeporte
H89: =E89&F89 | I89: =IFERROR(VLOOKUP(H89,$AP:$AQ,2,FALSE),"Error") -> Error | J89: =IF(H89=I89,"Es correcto","Revisa tu subcategoria") -> Revisa tu subcategoria | AN89: =Ene!$B$67 -> ENTRETENIMIENTO | AO89: =Ene!B73 -> Netflix | AP89: =AN89&AO89 -> ENTRETENIMIENTONetflix | AQ89: =AP89 -> ENTRETENIMIENTONetflix
H90: =E90&F90 | I90: =IFERROR(VLOOKUP(H90,$AP:$AQ,2,FALSE),"Error") -> Error | J90: =IF(H90=I90,"Es correcto","Revisa tu subcategoria") -> Revisa tu subcategoria | AN90: =Ene!$B$67 -> ENTRETENIMIENTO | AO90: =Ene!B74 -> Spotify | AP90: =AN90&AO90 -> ENTRETENIMIENTOSpotify | AQ90: =AP90 -> ENTRETENIMIENTOSpotify
H91: =E91&F91 | I91: =IFERROR(VLOOKUP(H91,$AP:$AQ,2,FALSE),"Error") -> Error | J91: =IF(H91=I91,"Es correcto","Revisa tu subcategoria") -> Revisa tu subcategoria | AN91: =Ene!$B$67 -> ENTRETENIMIENTO | AO91: =Ene!B75 -> google | AP91: =AN91&AO91 -> ENTRETENIMIENTOgoogle | AQ91: =AP91 -> ENTRETENIMIENTOgoogle
H92: =E92&F92 | I92: =IFERROR(VLOOKUP(H92,$AP:$AQ,2,FALSE),"Error") -> Error | J92: =IF(H92=I92,"Es correcto","Revisa tu subcategoria") -> Revisa tu subcategoria | AN92: =Ene!$B$67 -> ENTRETENIMIENTO | AO92: =Ene!B76 -> hbo | AP92: =AN92&AO92 -> ENTRETENIMIENTOhbo | AQ92: =AP92 -> ENTRETENIMIENTOhbo
H93: =E93&F93 | I93: =IFERROR(VLOOKUP(H93,$AP:$AQ,2,FALSE),"Error") -> Error | J93: =IF(H93=I93,"Es correcto","Revisa tu subcategoria") -> Revisa tu subcategoria | AN93: =Ene!$B$67 -> ENTRETENIMIENTO | AO93: =Ene!B77 -> Apple cloud | AP93: =AN93&AO93 -> ENTRETENIMIENTOApple cloud | AQ93: =AP93 -> ENTRETENIMIENTOApple cloud
H94: =E94&F94 | I94: =IFERROR(VLOOKUP(H94,$AP:$AQ,2,FALSE),"Error") -> Error | J94: =IF(H94=I94,"Es correcto","Revisa tu subcategoria") -> Revisa tu subcategoria | AN94: =Ene!$B$67 -> ENTRETENIMIENTO | AO94: =Ene!B78 -> 0 | AP94: =AN94&AO94 -> ENTRETENIMIENTO0 | AQ94: =AP94 -> ENTRETENIMIENTO0
H95: =E95&F95 | I95: =IFERROR(VLOOKUP(H95,$AP:$AQ,2,FALSE),"Error") -> Error | J95: =IF(H95=I95,"Es correcto","Revisa tu subcategoria") -> Revisa tu subcategoria | AN95: =Ene!$H$67 -> HIJOS | AO95: =Ene!H68 -> Ropa | AP95: =AN95&AO95 -> HIJOSRopa | AQ95: =AP95 -> HIJOSRopa
H96: =E96&F96 | I96: =IFERROR(VLOOKUP(H96,$AP:$AQ,2,FALSE),"Error") -> Error | J96: =IF(H96=I96,"Es correcto","Revisa tu subcategoria") -> Revisa tu subcategoria | AN96: =Ene!$H$67 -> HIJOS | AO96: =Ene!H69 -> Estudio | AP96: =AN96&AO96 -> HIJOSEstudio | AQ96: =AP96 -> HIJOSEstudio
H97: =E97&F97 | I97: =IFERROR(VLOOKUP(H97,$AP:$AQ,2,FALSE),"Error") -> Error | J97: =IF(H97=I97,"Es correcto","Revisa tu subcategoria") -> Revisa tu subcategoria | AN97: =Ene!$H$67 -> HIJOS | AO97: =Ene!H70 -> Utiles Escolares | AP97: =AN97&AO97 -> HIJOSUtiles Escolares | AQ97: =AP97 -> HIJOSUtiles Escolares
H98: =E98&F98 | I98: =IFERROR(VLOOKUP(H98,$AP:$AQ,2,FALSE),"Error") -> Error | J98: =IF(H98=I98,"Es correcto","Revisa tu subcategoria") -> Revisa tu subcategoria | AN98: =Ene!$H$67 -> HIJOS | AO98: =Ene!H71 -> Niñera | AP98: =AN98&AO98 -> HIJOSNiñera | AQ98: =AP98 -> HIJOSNiñera
H99: =E99&F99 | I99: =IFERROR(VLOOKUP(H99,$AP:$AQ,2,FALSE),"Error") -> Error | J99: =IF(H99=I99,"Es correcto","Revisa tu subcategoria") -> Revisa tu subcategoria | AN99: =Ene!$H$67 -> HIJOS | AO99: =Ene!H72 -> 0 | AP99: =AN99&AO99 -> HIJOS0 | AQ99: =AP99 -> HIJOS0
H100: =E100&F100 | I100: =IFERROR(VLOOKUP(H100,$AP:$AQ,2,FALSE),"Error") -> Error | J100: =IF(H100=I100,"Es correcto","Revisa tu subcategoria") -> Revisa tu subcategoria | AN100: =Ene!$H$67 -> HIJOS | AO100: =Ene!H73 -> 0 | AP100: =AN100&AO100 -> HIJOS0 | AQ100: =AP100 -> HIJOS0
H101: =E101&F101 | I101: =IFERROR(VLOOKUP(H101,$AP:$AQ,2,FALSE),"Error") -> Error | J101: =IF(H101=I101,"Es correcto","Revisa tu subcategoria") -> Revisa tu subcategoria | AN101: =Ene!$H$67 -> HIJOS | AO101: =Ene!H74 -> 0 | AP101: =AN101&AO101 -> HIJOS0 | AQ101: =AP101 -> HIJOS0
...

Sheet Feb
U1: =B13 -> Arriendo/Hipoteca
B2: PRESUPUESTO MENSUAL
B4: Ingreso Estimado | C4: Salario
C10: Total Ingreso Mensual | E10: =SUM(E4:E9) -> 0 | H10: Balance (Ingreso vs Presupuesto) | K10: =E10-SUM(D25,D36,D55,D65,D79,D88,D98,J25,J36,J55,J65,J88,J98,D108,J108,D46,J46,J79) -> 0 | M10: =IF(K10=0,"El presupuesto está listo","OJO! TiFeb que sumar cero") -> El presupuesto está listo
B12: NECESIDADES BÁSICAS | C12: Ahorro | D12: Presupuesto | E12: Gasto | F12: Disponible | H12: AHORROS | I12: Ahorro | J12: Presupuesto | K12: Gasto | L12: Disponible
B13: Arriendo/Hipoteca | E13: =SUMIFS('Feb - registro gastos'!$D$3:$D$300,'Feb - registro gastos'!$E$3:$E$300,Feb!$B$12,'Feb - registro gastos'!$F$3:$F$300,Feb!B13) -> 0 | F13: =D13-E13 -> 0 | H13: Fondo de Emergencia | K13: =SUMIFS('Feb - registro gastos'!$D$3:$D$300,'Feb - registro gastos'!$E$3:$E$300,Feb!$H$12,'Feb - registro gastos'!$F$3:$F$300,Feb!H13) -> 0 | L13: =J13-K13 -> 0
B14: Telefono/ Celular | E14: =SUMIFS('Feb - registro gastos'!$D$3:$D$300,'Feb - registro gastos'!$E$3:$E$300,Feb!$B$12,'Feb - registro gastos'!$F$3:$F$300,Feb!B14) -> 0 | F14: =D14-E14 -> 0 | H14: Fondo de Pensión | K14: =SUMIFS('Feb - registro gastos'!$D$3:$D$300,'Feb - registro gastos'!$E$3:$E$300,Feb!$H$12,'Feb - registro gastos'!$F$3:$F$300,Feb!H14) -> 0 | L14: =J14-K14 -> 0
B15: Electricidad | E15: =SUMIFS('Feb - registro gastos'!$D$3:$D$300,'Feb - registro gastos'!$E$3:$E$300,Feb!$B$12,'Feb - registro gastos'!$F$3:$F$300,Feb!B15) -> 0 | F15: =D15-E15 -> 0 | H15: Fondo de Educación | K15: =SUMIFS('Feb - registro gastos'!$D$3:$D$300,'Feb - registro gastos'!$E$3:$E$300,Feb!$H$12,'Feb - registro gastos'!$F$3:$F$300,Feb!H15) -> 0 | L15: =J15-K15 -> 0
B16: Agua | E16: =SUMIFS('Feb - registro gastos'!$D$3:$D$300,'Feb - registro gastos'!$E$3:$E$300,Feb!$B$12,'Feb - registro gastos'!$F$3:$F$300,Feb!B16) -> 0 | F16: =D16-E16 -> 0 | H16: Cuota Inicial Casa | K16: =SUMIFS('Feb - registro gastos'!$D$3:$D$300,'Feb - registro gastos'!$E$3:$E$300,Feb!$H$12,'Feb - registro gastos'!$F$3:$F$300,Feb!H16) -> 0 | L16: =J16-K16 -> 0
B17: Gas | E17: =SUMIFS('Feb - registro gastos'!$D$3:$D$300,'Feb - registro gastos'!$E$3:$E$300,Feb!$B$12,'Feb - registro gastos'!$F$3:$F$300,Feb!B17) -> 0 | F17: =D17-E17 -> 0 | H17: Aporte a Capital | K17: =SUMIFS('Feb - registro gastos'!$D$3:$D$300,'Feb - registro gastos'!$E$3:$E$300,Feb!$H$12,'Feb - registro gastos'!$F$3:$F$300,Feb!H17) -> 0 | L17: =J17-K17 -> 0
B18: Cable/Internet | E18: =SUMIFS('Feb - registro gastos'!$D$3:$D$300,'Feb - registro gastos'!$E$3:$E$300,Feb!$B$12,'Feb - registro gastos'!$F$3:$F$300,Feb!B18) -> 0 | F18: =D18-E18 -> 0 | K18: =SUMIFS('Feb - registro gastos'!$D$3:$D$300,'Feb - registro gastos'!$E$3:$E$300,Feb!$H$12,'Feb - registro gastos'!$F$3:$F$300,Feb!H18) -> 0 | L18: =J18-K18 -> 0
B19: Super Mercado | E19: =SUMIFS('Feb - registro gastos'!$D$3:$D$300,'Feb - registro gastos'!$E$3:$E$300,Feb!$B$12,'Feb - registro gastos'!$F$3:$F$300,Feb!B19) -> 0 | F19: =D19-E19 -> 0 | K19: =SUMIFS('Feb - registro gastos'!$D$3:$D$300,'Feb - registro gastos'!$E$3:$E$300,Feb!$H$12,'Feb - registro gastos'!$F$3:$F$300,Feb!H19) -> 0 | L19: =J19-K19 -> 0
B20: Gasolina | E20: =SUMIFS('Feb - registro gastos'!$D$3:$D$300,'Feb - registro gastos'!$E$3:$E$300,Feb!$B$12,'Feb - registro gastos'!$F$3:$F$300,Feb!B20) -> 0 | F20: =D20-E20 -> 0 | K20: =SUMIFS('Feb - registro gastos'!$D$3:$D$300,'Feb - registro gastos'!$E$3:$E$300,Feb!$H$12,'Feb - registro gastos'!$F$3:$F$300,Feb!H20) -> 0 | L20: =J20-K20 -> 0
B21: Bus | E21: =SUMIFS('Feb - registro gastos'!$D$3:$D$300,'Feb - registro gastos'!$E$3:$E$300,Feb!$B$12,'Feb - registro gastos'!$F$3:$F$300,Feb!B21) -> 0 | F21: =D21-E21 -> 0 | K21: =SUMIFS('Feb - registro gastos'!$D$3:$D$300,'Feb - registro gastos'!$E$3:$E$300,Feb!$H$12,'Feb - registro gastos'!$F$3:$F$300,Feb!H21) -> 0 | L21: =J21-K21 -> 0
E22: =SUMIFS('Feb - registro gastos'!$D$3:$D$300,'Feb - registro gastos'!$E$3:$E$300,Feb!$B$12,'Feb - registro gastos'!$F$3:$F$300,Feb!B22) -> 0 | F22: =D22-E22 -> 0 | K22: =SUMIFS('Feb - registro gastos'!$D$3:$D$300,'Feb - registro gastos'!$E$3:$E$300,Feb!$H$12,'Feb - registro gastos'!$F$3:$F$300,Feb!H22) -> 0 | L22: =J22-K22 -> 0
E23: =SUMIFS('Feb - registro gastos'!$D$3:$D$300,'Feb - registro gastos'!$E$3:$E$300,Feb!$B$12,'Feb - registro gastos'!$F$3:$F$300,Feb!B23) -> 0 | F23: =D23-E23 -> 0 | K23: =SUMIFS('Feb - registro gastos'!$D$3:$D$300,'Feb - registro gastos'!$E$3:$E$300,Feb!$H$12,'Feb - registro gastos'!$F$3:$F$300,Feb!H23) -> 0 | L23: =J23-K23 -> 0
E24: =SUMIFS('Feb - registro gastos'!$D$3:$D$300,'Feb - registro gastos'!$E$3:$E$300,Feb!$B$12,'Feb - registro gastos'!$F$3:$F$300,Feb!B24) -> 0 | F24: =D24-E24 -> 0 | K24: =SUMIFS('Feb - registro gastos'!$D$3:$D$300,'Feb - registro gastos'!$E$3:$E$300,Feb!$H$12,'Feb - registro gastos'!$F$3:$F$300,Feb!H24) -> 0 | L24: =J24-K24 -> 0
B25: Subtotal | D25: =SUM(D13:D24) -> 0 | E25: =SUM(E13:E24) -> 0 | F25: =D25-E25 -> 0 | H25: Subtotal | J25: =SUM(J13:J24) -> 0 | K25: =SUM(K13:K24) -> 0 | L25: =J25-K25 -> 0
B27: DEUDAS | C27: Ahorro | D27: Presupuesto | E27: Gasto | F27: Disponible | H27: REGALOS/ CARIDAD | I27: Ahorro | J27: Presupuesto | K27: Gasto | L27: Disponible
B28: Deuda Carro | E28: =SUMIFS('Feb - registro gastos'!$D$3:$D$300,'Feb - registro gastos'!$E$3:$E$300,Feb!$B$27,'Feb - registro gastos'!$F$3:$F$300,Feb!B28) -> 0 | F28: =D28-E28 -> 0 | H28: Regalos Navidad | K28: =SUMIFS('Feb - registro gastos'!$D$3:$D$300,'Feb - registro gastos'!$E$3:$E$300,Feb!$H$27,'Feb - registro gastos'!$F$3:$F$300,Feb!H28) -> 0 | L28: =J28-K28 -> 0
B29: Deuda tarjeta 1 | E29: =SUMIFS('Feb - registro gastos'!$D$3:$D$300,'Feb - registro gastos'!$E$3:$E$300,Feb!$B$27,'Feb - registro gastos'!$F$3:$F$300,Feb!B29) -> 0 | F29: =D29-E29 -> 0 | H29: Regalos cumpleaños | K29: =SUMIFS('Feb - registro gastos'!$D$3:$D$300,'Feb - registro gastos'!$E$3:$E$300,Feb!$H$27,'Feb - registro gastos'!$F$3:$F$300,Feb!H29) -> 0 | L29: =J29-K29 -> 0
B30: Deuda tarjeta 2 | E30: =SUMIFS('Feb - registro gastos'!$D$3:$D$300,'Feb - registro gastos'!$E$3:$E$300,Feb!$B$27,'Feb - registro gastos'!$F$3:$F$300,Feb!B30) -> 0 | F30: =D30-E30 -> 0 | H30: Caridad | K30: =SUMIFS('Feb - registro gastos'!$D$3:$D$300,'Feb - registro gastos'!$E$3:$E$300,Feb!$H$27,'Feb - registro gastos'!$F$3:$F$300,Feb!H30) -> 0 | L30: =J30-K30 -> 0
B31: Deuda Estudio | E31: =SUMIFS('Feb - registro gastos'!$D$3:$D$300,'Feb - registro gastos'!$E$3:$E$300,Feb!$B$27,'Feb - registro gastos'!$F$3:$F$300,Feb!B31) -> 0 | F31: =D31-E31 -> 0 | K31: =SUMIFS('Feb - registro gastos'!$D$3:$D$300,'Feb - registro gastos'!$E$3:$E$300,Feb!$H$27,'Feb - registro gastos'!$F$3:$F$300,Feb!H31) -> 0 | L31: =J31-K31 -> 0
B32: Carro | E32: =SUMIFS('Feb - registro gastos'!$D$3:$D$300,'Feb - registro gastos'!$E$3:$E$300,Feb!$B$27,'Feb - registro gastos'!$F$3:$F$300,Feb!B32) -> 0 | F32: =D32-E32 -> 0 | K32: =SUMIFS('Feb - registro gastos'!$D$3:$D$300,'Feb - registro gastos'!$E$3:$E$300,Feb!$H$27,'Feb - registro gastos'!$F$3:$F$300,Feb!H32) -> 0 | L32: =J32-K32 -> 0
E33: =SUMIFS('Feb - registro gastos'!$D$3:$D$300,'Feb - registro gastos'!$E$3:$E$300,Feb!$B$27,'Feb - registro gastos'!$F$3:$F$300,Feb!B33) -> 0 | F33: =D33-E33 -> 0 | K33: =SUMIFS('Feb - registro gastos'!$D$3:$D$300,'Feb - registro gastos'!$E$3:$E$300,Feb!$H$27,'Feb - registro gastos'!$F$3:$F$300,Feb!H33) -> 0 | L33: =J33-K33 -> 0
E34: =SUMIFS('Feb - registro gastos'!$D$3:$D$300,'Feb - registro gastos'!$E$3:$E$300,Feb!$B$27,'Feb - registro gastos'!$F$3:$F$300,Feb!B34) -> 0 | F34: =D34-E34 -> 0 | K34: =SUMIFS('Feb - registro gastos'!$D$3:$D$300,'Feb - registro gastos'!$E$3:$E$300,Feb!$H$27,'Feb - registro gastos'!$F$3:$F$300,Feb!H34) -> 0 | L34: =J34-K34 -> 0
E35: =SUMIFS('Feb - registro gastos'!$D$3:$D$300,'Feb - registro gastos'!$E$3:$E$300,Feb!$B$27,'Feb - registro gastos'!$F$3:$F$300,Feb!B35) -> 0 | F35: =D35-E35 -> 0 | K35: =SUMIFS('Feb - registro gastos'!$D$3:$D$300,'Feb - registro gastos'!$E$3:$E$300,Feb!$H$27,'Feb - registro gastos'!$F$3:$F$300,Feb!H35) -> 0 | L35: =J35-K35 -> 0
B36: Subtotal | D36: =SUM(D28:D35) -> 0 | E36: =SUM(E28:E35) -> 0 | F36: =D36-E36 -> 0 | H36: Subtotal | J36: =SUM(J28:J35) -> 0 | K36: =SUM(K28:K35) -> 0 | L36: =J36-K36 -> 0
B38: CASA | C38: Ahorro | D38: Presupuesto | E38: Gasto | F38: Disponible | H38: TRANSPORTE | I38: Ahorro | J38: Presupuesto | K38: Gasto | L38: Disponible
B39: Limpieza | E39: =SUMIFS('Feb - registro gastos'!$D$3:$D$300,'Feb - registro gastos'!$E$3:$E$300,Feb!$B$38,'Feb - registro gastos'!$F$3:$F$300,Feb!B39) -> 0 | F39: =D39-E39 -> 0 | H39: Uber/taxi | K39: =SUMIFS('Feb - registro gastos'!$D$3:$D$300,'Feb - registro gastos'!$E$3:$E$300,Feb!$H$38,'Feb - registro gastos'!$F$3:$F$300,Feb!H39) -> 0 | L39: =J39-K39 -> 0
B40: Mantenimiento | E40: =SUMIFS('Feb - registro gastos'!$D$3:$D$300,'Feb - registro gastos'!$E$3:$E$300,Feb!$B$38,'Feb - registro gastos'!$F$3:$F$300,Feb!B40) -> 0 | F40: =D40-E40 -> 0 | H40: Estacionamiento | K40: =SUMIFS('Feb - registro gastos'!$D$3:$D$300,'Feb - registro gastos'!$E$3:$E$300,Feb!$H$38,'Feb - registro gastos'!$F$3:$F$300,Feb!H40) -> 0 | L40: =J40-K40 -> 0
B41: Muebles | E41: =SUMIFS('Feb - registro gastos'!$D$3:$D$300,'Feb - registro gastos'!$E$3:$E$300,Feb!$B$38,'Feb - registro gastos'!$F$3:$F$300,Feb!B41) -> 0 | F41: =D41-E41 -> 0 | H41: Mantenimiento | K41: =SUMIFS('Feb - registro gastos'!$D$3:$D$300,'Feb - registro gastos'!$E$3:$E$300,Feb!$H$38,'Feb - registro gastos'!$F$3:$F$300,Feb!H41) -> 0 | L41: =J41-K41 -> 0
B42: Impuestos | E42: =SUMIFS('Feb - registro gastos'!$D$3:$D$300,'Feb - registro gastos'!$E$3:$E$300,Feb!$B$38,'Feb - registro gastos'!$F$3:$F$300,Feb!B42) -> 0 | F42: =D42-E42 -> 0 | H42: Impuestos | K42: =SUMIFS('Feb - registro gastos'!$D$3:$D$300,'Feb - registro gastos'!$E$3:$E$300,Feb!$H$38,'Feb - registro gastos'!$F$3:$F$300,Feb!H42) -> 0 | L42: =J42-K42 -> 0
E43: =SUMIFS('Feb - registro gastos'!$D$3:$D$300,'Feb - registro gastos'!$E$3:$E$300,Feb!$B$38,'Feb - registro gastos'!$F$3:$F$300,Feb!B43) -> 0 | F43: =D43-E43 -> 0 | H43: Panapass/Peaje | K43: =SUMIFS('Feb - registro gastos'!$D$3:$D$300,'Feb - registro gastos'!$E$3:$E$300,Feb!$H$38,'Feb - registro gastos'!$F$3:$F$300,Feb!H43) -> 0 | L43: =J43-K43 -> 0
E44: =SUMIFS('Feb - registro gastos'!$D$3:$D$300,'Feb - registro gastos'!$E$3:$E$300,Feb!$B$38,'Feb - registro gastos'!$F$3:$F$300,Feb!B44) -> 0 | F44: =D44-E44 -> 0 | K44: =SUMIFS('Feb - registro gastos'!$D$3:$D$300,'Feb - registro gastos'!$E$3:$E$300,Feb!$H$38,'Feb - registro gastos'!$F$3:$F$300,Feb!H44) -> 0 | L44: =J44-K44 -> 0
E45: =SUMIFS('Feb - registro gastos'!$D$3:$D$300,'Feb - registro gastos'!$E$3:$E$300,Feb!$B$38,'Feb - registro gastos'!$F$3:$F$300,Feb!B45) -> 0 | F45: =D45-E45 -> 0 | K45: =SUMIFS('Feb - registro gastos'!$D$3:$D$300,'Feb - registro gastos'!$E$3:$E$300,Feb!$H$38,'Feb - registro gastos'!$F$3:$F$300,Feb!H45) -> 0 | L45: =J45-K45 -> 0
B46: Subtotal | D46: =SUM(D39:D45) -> 0 | E46: =SUM(E39:E45) -> 0 | F46: =D46-E46 -> 0 | H46: Subtotal | J46: =SUM(J39:J45) -> 0 | K46: =SUM(K39:K45) -> 0 | L46: =J46-K46 -> 0
B48: ALIMENTACIÓN | C48: Ahorro | D48: Presupuesto | E48: Gasto | F48: Disponible | H48: SEGUROS | I48: Ahorro | J48: Presupuesto | K48: Gasto | L48: Disponible
B49: Restaurantes | E49: =SUMIFS('Feb - registro gastos'!$D$3:$D$300,'Feb - registro gastos'!$E$3:$E$300,Feb!$B$48,'Feb - registro gastos'!$F$3:$F$300,Feb!B49) -> 0 | F49: =D49-E49 -> 0 | H49: Carro | K49: =SUMIFS('Feb - registro gastos'!$D$3:$D$300,'Feb - registro gastos'!$E$3:$E$300,Feb!$H$48,'Feb - registro gastos'!$F$3:$F$300,Feb!H49) -> 0 | L49: =J49-K49 -> 0
B50: Café/ Snacks | E50: =SUMIFS('Feb - registro gastos'!$D$3:$D$300,'Feb - registro gastos'!$E$3:$E$300,Feb!$B$48,'Feb - registro gastos'!$F$3:$F$300,Feb!B50) -> 0 | F50: =D50-E50 -> 0 | H50: Vida | K50: =SUMIFS('Feb - registro gastos'!$D$3:$D$300,'Feb - registro gastos'!$E$3:$E$300,Feb!$H$48,'Feb - registro gastos'!$F$3:$F$300,Feb!H50) -> 0 | L50: =J50-K50 -> 0
E51: =SUMIFS('Feb - registro gastos'!$D$3:$D$300,'Feb - registro gastos'!$E$3:$E$300,Feb!$B$48,'Feb - registro gastos'!$F$3:$F$300,Feb!B51) -> 0 | F51: =D51-E51 -> 0 | H51: Casa | K51: =SUMIFS('Feb - registro gastos'!$D$3:$D$300,'Feb - registro gastos'!$E$3:$E$300,Feb!$H$48,'Feb - registro gastos'!$F$3:$F$300,Feb!H51) -> 0 | L51: =J51-K51 -> 0
E52: =SUMIFS('Feb - registro gastos'!$D$3:$D$300,'Feb - registro gastos'!$E$3:$E$300,Feb!$B$48,'Feb - registro gastos'!$F$3:$F$300,Feb!B52) -> 0 | F52: =D52-E52 -> 0 | H52: Salud | K52: =SUMIFS('Feb - registro gastos'!$D$3:$D$300,'Feb - registro gastos'!$E$3:$E$300,Feb!$H$48,'Feb - registro gastos'!$F$3:$F$300,Feb!H52) -> 0 | L52: =J52-K52 -> 0
E53: =SUMIFS('Feb - registro gastos'!$D$3:$D$300,'Feb - registro gastos'!$E$3:$E$300,Feb!$B$48,'Feb - registro gastos'!$F$3:$F$300,Feb!B53) -> 0 | F53: =D53-E53 -> 0 | K53: =SUMIFS('Feb - registro gastos'!$D$3:$D$300,'Feb - registro gastos'!$E$3:$E$300,Feb!$H$48,'Feb - registro gastos'!$F$3:$F$300,Feb!H53) -> 0 | L53: =J53-K53 -> 0
E54: =SUMIFS('Feb - registro gastos'!$D$3:$D$300,'Feb - registro gastos'!$E$3:$E$300,Feb!$B$48,'Feb - registro gastos'!$F$3:$F$300,Feb!B54) -> 0 | F54: =D54-E54 -> 0 | K54: =SUMIFS('Feb - registro gastos'!$D$3:$D$300,'Feb - registro gastos'!$E$3:$E$300,Feb!$H$48,'Feb - registro gastos'!$F$3:$F$300,Feb!H54) -> 0 | L54: =J54-K54 -> 0
B55: Subtotal | D55: =SUM(D49:D54) -> 0 | E55: =SUM(E49:E54) -> 0 | F55: =D55-E55 -> 0 | H55: Subtotal | J55: =SUM(J49:J54) -> 0 | K55: =SUM(K49:K54) -> 0 | L55: =J55-K55 -> 0
B57: SALUD | C57: Ahorro | D57: Presupuesto | E57: Gasto | F57: Disponible | H57: CUIDADO PERSONAL | I57: Ahorro | J57: Presupuesto | K57: Gasto | L57: Disponible
B58: Medicinas | E58: =SUMIFS('Feb - registro gastos'!$D$3:$D$300,'Feb - registro gastos'!$E$3:$E$300,Feb!$B$57,'Feb - registro gastos'!$F$3:$F$300,Feb!B58) -> 0 | F58: =D58-E58 -> 0 | H58: Ropa | K58: =SUMIFS('Feb - registro gastos'!$D$3:$D$300,'Feb - registro gastos'!$E$3:$E$300,Feb!$H$57,'Feb - registro gastos'!$F$3:$F$300,Feb!H58) -> 0 | L58: =J58-K58 -> 0
B59: Dentista | E59: =SUMIFS('Feb - registro gastos'!$D$3:$D$300,'Feb - registro gastos'!$E$3:$E$300,Feb!$B$57,'Feb - registro gastos'!$F$3:$F$300,Feb!B59) -> 0 | F59: =D59-E59 -> 0 | H59: Belleza | K59: =SUMIFS('Feb - registro gastos'!$D$3:$D$300,'Feb - registro gastos'!$E$3:$E$300,Feb!$H$57,'Feb - registro gastos'!$F$3:$F$300,Feb!H59) -> 0 | L59: =J59-K59 -> 0
B60: Tratamientos | E60: =SUMIFS('Feb - registro gastos'!$D$3:$D$300,'Feb - registro gastos'!$E$3:$E$300,Feb!$B$57,'Feb - registro gastos'!$F$3:$F$300,Feb!B60) -> 0 | F60: =D60-E60 -> 0 | H60: Peluquería | K60: =SUMIFS('Feb - registro gastos'!$D$3:$D$300,'Feb - registro gastos'!$E$3:$E$300,Feb!$H$57,'Feb - registro gastos'!$F$3:$F$300,Feb!H60) -> 0 | L60: =J60-K60 -> 0
E61: =SUMIFS('Feb - registro gastos'!$D$3:$D$300,'Feb - registro gastos'!$E$3:$E$300,Feb!$B$57,'Feb - registro gastos'!$F$3:$F$300,Feb!B61) -> 0 | F61: =D61-E61 -> 0 | H61: Sastre | K61: =SUMIFS('Feb - registro gastos'!$D$3:$D$300,'Feb - registro gastos'!$E$3:$E$300,Feb!$H$57,'Feb - registro gastos'!$F$3:$F$300,Feb!H61) -> 0 | L61: =J61-K61 -> 0
E62: =SUMIFS('Feb - registro gastos'!$D$3:$D$300,'Feb - registro gastos'!$E$3:$E$300,Feb!$B$57,'Feb - registro gastos'!$F$3:$F$300,Feb!B62) -> 0 | F62: =D62-E62 -> 0 | H62: Tintorería | K62: =SUMIFS('Feb - registro gastos'!$D$3:$D$300,'Feb - registro gastos'!$E$3:$E$300,Feb!$H$57,'Feb - registro gastos'!$F$3:$F$300,Feb!H62) -> 0 | L62: =J62-K62 -> 0
E63: =SUMIFS('Feb - registro gastos'!$D$3:$D$300,'Feb - registro gastos'!$E$3:$E$300,Feb!$B$57,'Feb - registro gastos'!$F$3:$F$300,Feb!B63) -> 0 | F63: =D63-E63 -> 0 | K63: =SUMIFS('Feb - registro gastos'!$D$3:$D$300,'Feb - registro gastos'!$E$3:$E$300,Feb!$H$57,'Feb - registro gastos'!$F$3:$F$300,Feb!H63) -> 0 | L63: =J63-K63 -> 0
E64: =SUMIFS('Feb - registro gastos'!$D$3:$D$300,'Feb - registro gastos'!$E$3:$E$300,Feb!$B$57,'Feb - registro gastos'!$F$3:$F$300,Feb!B64) -> 0 | F64: =D64-E64 -> 0 | K64: =SUMIFS('Feb - registro gastos'!$D$3:$D$300,'Feb - registro gastos'!$E$3:$E$300,Feb!$H$57,'Feb - registro gastos'!$F$3:$F$300,Feb!H64) -> 0 | L64: =J64-K64 -> 0
B65: Subtotal | D65: =SUM(D58:D64) -> 0 | E65: =SUM(E58:E64) -> 0 | F65: =D65-E65 -> 0 | H65: Subtotal | J65: =SUM(J58:J64) -> 0 | K65: =SUM(K58:K64) -> 0 | L65: =J65-K65 -> 0
B67: ENTRETENIMIENTO | C67: Ahorro | D67: Presupuesto | E67: Gasto | F67: Disponible | H67: HIJOS | I67: Ahorro | J67: Presupuesto | K67: Gasto | L67: Diferencia
B68: Vacaciones | E68: =SUMIFS('Feb - registro gastos'!$D$3:$D$300,'Feb - registro gastos'!$E$3:$E$300,Feb!$B$67,'Feb - registro gastos'!$F$3:$F$300,Feb!B68) -> 0 | F68: =D68-E68 -> 0 | H68: Ropa | K68: =SUMIFS('Feb - registro gastos'!$D$3:$D$300,'Feb - registro gastos'!$E$3:$E$300,Feb!$H$67,'Feb - registro gastos'!$F$3:$F$300,Feb!H68) -> 0 | L68: =J68-K68 -> 0
B69: Rumba | E69: =SUMIFS('Feb - registro gastos'!$D$3:$D$300,'Feb - registro gastos'!$E$3:$E$300,Feb!$B$67,'Feb - registro gastos'!$F$3:$F$300,Feb!B69) -> 0 | F69: =D69-E69 -> 0 | H69: Estudio | K69: =SUMIFS('Feb - registro gastos'!$D$3:$D$300,'Feb - registro gastos'!$E$3:$E$300,Feb!$H$67,'Feb - registro gastos'!$F$3:$F$300,Feb!H69) -> 0 | L69: =J69-K69 -> 0
B70: Citas | E70: =SUMIFS('Feb - registro gastos'!$D$3:$D$300,'Feb - registro gastos'!$E$3:$E$300,Feb!$B$67,'Feb - registro gastos'!$F$3:$F$300,Feb!B70) -> 0 | F70: =D70-E70 -> 0 | H70: Utiles Escolares | K70: =SUMIFS('Feb - registro gastos'!$D$3:$D$300,'Feb - registro gastos'!$E$3:$E$300,Feb!$H$67,'Feb - registro gastos'!$F$3:$F$300,Feb!H70) -> 0 | L70: =J70-K70 -> 0
B71: Cine | E71: =SUMIFS('Feb - registro gastos'!$D$3:$D$300,'Feb - registro gastos'!$E$3:$E$300,Feb!$B$67,'Feb - registro gastos'!$F$3:$F$300,Feb!B71) -> 0 | F71: =D71-E71 -> 0 | H71: Niñera | K71: =SUMIFS('Feb - registro gastos'!$D$3:$D$300,'Feb - registro gastos'!$E$3:$E$300,Feb!$H$67,'Feb - registro gastos'!$F$3:$F$300,Feb!H71) -> 0 | L71: =J71-K71 -> 0
B72: Deporte | E72: =SUMIFS('Feb - registro gastos'!$D$3:$D$300,'Feb - registro gastos'!$E$3:$E$300,Feb!$B$67,'Feb - registro gastos'!$F$3:$F$300,Feb!B72) -> 0 | F72: =D72-E72 -> 0 | K72: =SUMIFS('Feb - registro gastos'!$D$3:$D$300,'Feb - registro gastos'!$E$3:$E$300,Feb!$H$67,'Feb - registro gastos'!$F$3:$F$300,Feb!H72) -> 0 | L72: =J72-K72 -> 0
B73: Netflix | E73: =SUMIFS('Feb - registro gastos'!$D$3:$D$300,'Feb - registro gastos'!$E$3:$E$300,Feb!$B$67,'Feb - registro gastos'!$F$3:$F$300,Feb!B73) -> 0 | F73: =D73-E73 -> 0 | K73: =SUMIFS('Feb - registro gastos'!$D$3:$D$300,'Feb - registro gastos'!$E$3:$E$300,Feb!$H$67,'Feb - registro gastos'!$F$3:$F$300,Feb!H73) -> 0 | L73: =J73-K73 -> 0
B74: Spotify | E74: =SUMIFS('Feb - registro gastos'!$D$3:$D$300,'Feb - registro gastos'!$E$3:$E$300,Feb!$B$67,'Feb - registro gastos'!$F$3:$F$300,Feb!B74) -> 0 | F74: =D74-E74 -> 0 | K74: =SUMIFS('Feb - registro gastos'!$D$3:$D$300,'Feb - registro gastos'!$E$3:$E$300,Feb!$H$67,'Feb - registro gastos'!$F$3:$F$300,Feb!H74) -> 0 | L74: =J74-K74 -> 0
E75: =SUMIFS('Feb - registro gastos'!$D$3:$D$300,'Feb - registro gastos'!$E$3:$E$300,Feb!$B$67,'Feb - registro gastos'!$F$3:$F$300,Feb!B75) -> 0 | F75: =D75-E75 -> 0 | K75: =SUMIFS('Feb - registro gastos'!$D$3:$D$300,'Feb - registro gastos'!$E$3:$E$300,Feb!$H$67,'Feb - registro gastos'!$F$3:$F$300,Feb!H75) -> 0 | L75: =J75-K75 -> 0
E76: =SUMIFS('Feb - registro gastos'!$D$3:$D$300,'Feb - registro gastos'!$E$3:$E$300,Feb!$B$67,'Feb - registro gastos'!$F$3:$F$300,Feb!B76) -> 0 | F76: =D76-E76 -> 0 | K76: =SUMIFS('Feb - registro gastos'!$D$3:$D$300,'Feb - registro gastos'!$E$3:$E$300,Feb!$H$67,'Feb - registro gastos'!$F$3:$F$300,Feb!H76) -> 0 | L76: =J76-K76 -> 0
E77: =SUMIFS('Feb - registro gastos'!$D$3:$D$300,'Feb - registro gastos'!$E$3:$E$300,Feb!$B$67,'Feb - registro gastos'!$F$3:$F$300,Feb!B77) -> 0 | F77: =D77-E77 -> 0 | K77: =SUMIFS('Feb - registro gastos'!$D$3:$D$300,'Feb - registro gastos'!$E$3:$E$300,Feb!$H$67,'Feb - registro gastos'!$F$3:$F$300,Feb!H77) -> 0 | L77: =J77-K77 -> 0
E78: =SUMIFS('Feb - registro gastos'!$D$3:$D$300,'Feb - registro gastos'!$E$3:$E$300,Feb!$B$67,'Feb - registro gastos'!$F$3:$F$300,Feb!B78) -> 0 | F78: =D78-E78 -> 0 | K78: =SUMIFS('Feb - registro gastos'!$D$3:$D$300,'Feb - registro gastos'!$E$3:$E$300,Feb!$H$67,'Feb - registro gastos'!$F$3:$F$300,Feb!H78) -> 0 | L78: =J78-K78 -> 0
B79: Subtotal | D79: =SUM(D68:D78) -> 0 | E79: =SUM(E68:E78) -> 0 | F79: =D79-E79 -> 0 | H79: Subtotal | J79: =SUM(J68:J78) -> 0 | K79: =SUM(K68:K78) -> 0 | L79: =J79-K79 -> 0
B81: MASCOTA | C81: Ahorro | D81: Presupuesto | E81: Gasto | F81: Disponible | H81: OTROS 1 | I81: Ahorro | J81: Presupuesto | K81: Gasto | L81: Disponible
B82: Comida | E82: =SUMIFS('Feb - registro gastos'!$D$3:$D$300,'Feb - registro gastos'!$E$3:$E$300,Feb!$B$81,'Feb - registro gastos'!$F$3:$F$300,Feb!B82) -> 0 | F82: =D82-E82 -> 0 | H82: 1 | K82: =SUMIFS('Feb - registro gastos'!$D$3:$D$300,'Feb - registro gastos'!$E$3:$E$300,Feb!$H$81,'Feb - registro gastos'!$F$3:$F$300,Feb!H82) -> 0 | L82: =J82-K82 -> 0
B83: Veterinario | E83: =SUMIFS('Feb - registro gastos'!$D$3:$D$300,'Feb - registro gastos'!$E$3:$E$300,Feb!$B$81,'Feb - registro gastos'!$F$3:$F$300,Feb!B83) -> 0 | F83: =D83-E83 -> 0 | K83: =SUMIFS('Feb - registro gastos'!$D$3:$D$300,'Feb - registro gastos'!$E$3:$E$300,Feb!$H$81,'Feb - registro gastos'!$F$3:$F$300,Feb!H83) -> 0 | L83: =J83-K83 -> 0
B84: Juguetes | E84: =SUMIFS('Feb - registro gastos'!$D$3:$D$300,'Feb - registro gastos'!$E$3:$E$300,Feb!$B$81,'Feb - registro gastos'!$F$3:$F$300,Feb!B84) -> 0 | F84: =D84-E84 -> 0 | K84: =SUMIFS('Feb - registro gastos'!$D$3:$D$300,'Feb - registro gastos'!$E$3:$E$300,Feb!$H$81,'Feb - registro gastos'!$F$3:$F$300,Feb!H84) -> 0 | L84: =J84-K84 -> 0
B85: Medicinas | E85: =SUMIFS('Feb - registro gastos'!$D$3:$D$300,'Feb - registro gastos'!$E$3:$E$300,Feb!$B$81,'Feb - registro gastos'!$F$3:$F$300,Feb!B85) -> 0 | F85: =D85-E85 -> 0 | K85: =SUMIFS('Feb - registro gastos'!$D$3:$D$300,'Feb - registro gastos'!$E$3:$E$300,Feb!$H$81,'Feb - registro gastos'!$F$3:$F$300,Feb!H85) -> 0 | L85: =J85-K85 -> 0
E86: =SUMIFS('Feb - registro gastos'!$D$3:$D$300,'Feb - registro gastos'!$E$3:$E$300,Feb!$B$81,'Feb - registro gastos'!$F$3:$F$300,Feb!B86) -> 0 | F86: =D86-E86 -> 0 | K86: =SUMIFS('Feb - registro gastos'!$D$3:$D$300,'Feb - registro gastos'!$E$3:$E$300,Feb!$H$81,'Feb - registro gastos'!$F$3:$F$300,Feb!H86) -> 0 | L86: =J86-K86 -> 0
E87: =SUMIFS('Feb - registro gastos'!$D$3:$D$300,'Feb - registro gastos'!$E$3:$E$300,Feb!$B$81,'Feb - registro gastos'!$F$3:$F$300,Feb!B87) -> 0 | F87: =D87-E87 -> 0 | K87: =SUMIFS('Feb - registro gastos'!$D$3:$D$300,'Feb - registro gastos'!$E$3:$E$300,Feb!$H$81,'Feb - registro gastos'!$F$3:$F$300,Feb!H87) -> 0 | L87: =J87-K87 -> 0
B88: Subtotal | D88: =SUM(D82:D87) -> 0 | E88: =SUM(E82:E87) -> 0 | F88: =D88-E88 -> 0 | H88: Subtotal | J88: =SUM(J82:J87) -> 0 | K88: =SUM(K82:K87) -> 0 | L88: =J88-K88 -> 0
B90: OTROS 2 | C90: Ahorro | D90: Presupuesto | E90: Gasto | F90: Disponible | H90: OTROS 3 | I90: Ahorro | J90: Presupuesto | K90: Gasto | L90: Disponible
B91: 2 | E91: =SUMIFS('Feb - registro gastos'!$D$3:$D$300,'Feb - registro gastos'!$E$3:$E$300,Feb!$B$90,'Feb - registro gastos'!$F$3:$F$300,Feb!B91) -> 0 | F91: =D91-E91 -> 0 | H91: 3 | K91: =SUMIFS('Feb - registro gastos'!$D$3:$D$300,'Feb - registro gastos'!$E$3:$E$300,Feb!$H$90,'Feb - registro gastos'!$F$3:$F$300,Feb!H91) -> 0 | L91: =J91-K91 -> 0
E92: =SUMIFS('Feb - registro gastos'!$D$3:$D$300,'Feb - registro gastos'!$E$3:$E$300,Feb!$B$90,'Feb - registro gastos'!$F$3:$F$300,Feb!B92) -> 0 | F92: =D92-E92 -> 0 | K92: =SUMIFS('Feb - registro gastos'!$D$3:$D$300,'Feb - registro gastos'!$E$3:$E$300,Feb!$H$90,'Feb - registro gastos'!$F$3:$F$300,Feb!H92) -> 0 | L92: =J92-K92 -> 0
E93: =SUMIFS('Feb - registro gastos'!$D$3:$D$300,'Feb - registro gastos'!$E$3:$E$300,Feb!$B$90,'Feb - registro gastos'!$F$3:$F$300,Feb!B93) -> 0 | F93: =D93-E93 -> 0 | K93: =SUMIFS('Feb - registro gastos'!$D$3:$D$300,'Feb - registro gastos'!$E$3:$E$300,Feb!$H$90,'Feb - registro gastos'!$F$3:$F$300,Feb!H93) -> 0 | L93: =J93-K93 -> 0
E94: =SUMIFS('Feb - registro gastos'!$D$3:$D$300,'Feb - registro gastos'!$E$3:$E$300,Feb!$B$90,'Feb - registro gastos'!$F$3:$F$300,Feb!B94) -> 0 | F94: =D94-E94 -> 0 | K94: =SUMIFS('Feb - registro gastos'!$D$3:$D$300,'Feb - registro gastos'!$E$3:$E$300,Feb!$H$90,'Feb - registro gastos'!$F$3:$F$300,Feb!H94) -> 0 | L94: =J94-K94 -> 0
E95: =SUMIFS('Feb - registro gastos'!$D$3:$D$300,'Feb - registro gastos'!$E$3:$E$300,Feb!$B$90,'Feb - registro gastos'!$F$3:$F$300,Feb!B95) -> 0 | F95: =D95-E95 -> 0 | K95: =SUMIFS('Feb - registro gastos'!$D$3:$D$300,'Feb - registro gastos'!$E$3:$E$300,Feb!$H$90,'Feb - registro gastos'!$F$3:$F$300,Feb!H95) -> 0 | L95: =J95-K95 -> 0
E96: =SUMIFS('Feb - registro gastos'!$D$3:$D$300,'Feb - registro gastos'!$E$3:$E$300,Feb!$B$90,'Feb - registro gastos'!$F$3:$F$300,Feb!B96) -> 0 | F96: =D96-E96 -> 0 | K96: =SUMIFS('Feb - registro gastos'!$D$3:$D$300,'Feb - registro gastos'!$E$3:$E$300,Feb!$H$90,'Feb - registro gastos'!$F$3:$F$300,Feb!H96) -> 0 | L96: =J96-K96 -> 0
E97: =SUMIFS('Feb - registro gastos'!$D$3:$D$300,'Feb - registro gastos'!$E$3:$E$300,Feb!$B$90,'Feb - registro gastos'!$F$3:$F$300,Feb!B97) -> 0 | F97: =D97-E97 -> 0 | K97: =SUMIFS('Feb - registro gastos'!$D$3:$D$300,'Feb - registro gastos'!$E$3:$E$300,Feb!$H$90,'Feb - registro gastos'!$F$3:$F$300,Feb!H97) -> 0 | L97: =J97-K97 -> 0
B98: Subtotal | D98: =SUM(D91:D97) -> 0 | E98: =SUM(E91:E97) -> 0 | F98: =D98-E98 -> 0 | H98: Subtotal | J98: =SUM(J91:J97) -> 0 | K98: =SUM(K91:K97) -> 0 | L98: =J98-K98 -> 0
B100: OTROS 4 | C100: Ahorro | D100: Presupuesto | E100: Gasto | F100: Disponible | H100: OTROS 5 | I100: Ahorro | J100: Presupuesto | K100: Gasto | L100: Disponible
B101: 4 | E101: =SUMIFS('Feb - registro gastos'!$D$3:$D$300,'Feb - registro gastos'!$E$3:$E$300,Feb!$B$100,'Feb - registro gastos'!$F$3:$F$300,Feb!B101) -> 0 | F101: =D101-E101 -> 0 | H101: 5 | K101: =SUMIFS('Feb - registro gastos'!$D$3:$D$300,'Feb - registro gastos'!$E$3:$E$300,Feb!$H$100,'Feb - registro gastos'!$F$3:$F$300,Feb!H101) -> 0 | L101: =J101-K101 -> 0
E102: =SUMIFS('Feb - registro gastos'!$D$3:$D$300,'Feb - registro gastos'!$E$3:$E$300,Feb!$B$100,'Feb - registro gastos'!$F$3:$F$300,Feb!B102) -> 0 | F102: =D102-E102 -> 0 | K102: =SUMIFS('Feb - registro gastos'!$D$3:$D$300,'Feb - registro gastos'!$E$3:$E$300,Feb!$H$100,'Feb - registro gastos'!$F$3:$F$300,Feb!H102) -> 0 | L102: =J102-K102 -> 0
E103: =SUMIFS('Feb - registro gastos'!$D$3:$D$300,'Feb - registro gastos'!$E$3:$E$300,Feb!$B$100,'Feb - registro gastos'!$F$3:$F$300,Feb!B103) -> 0 | F103: =D103-E103 -> 0 | K103: =SUMIFS('Feb - registro gastos'!$D$3:$D$300,'Feb - registro gastos'!$E$3:$E$300,Feb!$H$100,'Feb - registro gastos'!$F$3:$F$300,Feb!H103) -> 0 | L103: =J103-K103 -> 0
E104: =SUMIFS('Feb - registro gastos'!$D$3:$D$300,'Feb - registro gastos'!$E$3:$E$300,Feb!$B$100,'Feb - registro gastos'!$F$3:$F$300,Feb!B104) -> 0 | F104: =D104-E104 -> 0 | K104: =SUMIFS('Feb - registro gastos'!$D$3:$D$300,'Feb - registro gastos'!$E$3:$E$300,Feb!$H$100,'Feb - registro gastos'!$F$3:$F$300,Feb!H104) -> 0 | L104: =J104-K104 -> 0
E105: =SUMIFS('Feb - registro gastos'!$D$3:$D$300,'Feb - registro gastos'!$E$3:$E$300,Feb!$B$100,'Feb - registro gastos'!$F$3:$F$300,Feb!B105) -> 0 | F105: =D105-E105 -> 0 | K105: =SUMIFS('Feb - registro gastos'!$D$3:$D$300,'Feb - registro gastos'!$E$3:$E$300,Feb!$H$100,'Feb - registro gastos'!$F$3:$F$300,Feb!H105) -> 0 | L105: =J105-K105 -> 0
E106: =SUMIFS('Feb - registro gastos'!$D$3:$D$300,'Feb - registro gastos'!$E$3:$E$300,Feb!$B$100,'Feb - registro gastos'!$F$3:$F$300,Feb!B106) -> 0 | F106: =D106-E106 -> 0 | K106: =SUMIFS('Feb - registro gastos'!$D$3:$D$300,'Feb - registro gastos'!$E$3:$E$300,Feb!$H$100,'Feb - registro gastos'!$F$3:$F$300,Feb!H106) -> 0 | L106: =J106-K106 -> 0
E107: =SUMIFS('Feb - registro gastos'!$D$3:$D$300,'Feb - registro gastos'!$E$3:$E$300,Feb!$B$100,'Feb - registro gastos'!$F$3:$F$300,Feb!B107) -> 0 | F107: =D107-E107 -> 0 | K107: =SUMIFS('Feb - registro gastos'!$D$3:$D$300,'Feb - registro gastos'!$E$3:$E$300,Feb!$H$100,'Feb - registro gastos'!$F$3:$F$300,Feb!H107) -> 0 | L107: =J107-K107 -> 0
B108: Subtotal | D108: =SUM(D101:D107) -> 0 | E108: =SUM(E101:E107) -> 0 | F108: =D108-E108 -> 0 | H108: Subtotal | J108: =SUM(J101:J107) -> 0 | K108: =SUM(K101:K107) -> 0 | L108: =J108-K108 -> 0

Sheet Feb - registro gastos
B2: Fecha | C2: Compra | D2: Valor | E2: Categoría | F2: Sub Categoría | J2: Categoría
H3: =E3&F3 | I3: =IFERROR(VLOOKUP(H3,$AP:$AQ,2,FALSE),"Error") -> Error | J3: =IF(I3="Error","Revisa tu subcategoria",IF(I3=H3,"Es correcto",IF(H3="blanco","",""))) -> Revisa tu subcategoria | AN3: CATEGORÍA | AO3: SUBCATEGORIA
H4: =E4&F4 | I4: =IFERROR(VLOOKUP(H4,$AP:$AQ,2,FALSE),"Error") -> Error | J4: =IF(I4="Error","Revisa tu subcategoria",IF(I4=H4,"Es correcto",IF(H4="blanco","",""))) -> Revisa tu subcategoria | AN4: =Feb!$B$12 -> NECESIDADES BÁSICAS | AO4: =Feb!B13 -> Arriendo/Hipoteca | AP4: =AN4&AO4 -> NECESIDADES BÁSICASArriendo/Hipoteca | AQ4: =AP4 -> NECESIDADES BÁSICASArriendo/Hipoteca
H5: =E5&F5 | I5: =IFERROR(VLOOKUP(H5,$AP:$AQ,2,FALSE),"Error") -> Error | J5: =IF(I5="Error","Revisa tu subcategoria",IF(I5=H5,"Es correcto",IF(H5="blanco","",""))) -> Revisa tu subcategoria | AN5: =Feb!$B$12 -> NECESIDADES BÁSICAS | AO5: =Feb!B14 -> Telefono/ Celular | AP5: =AN5&AO5 -> NECESIDADES BÁSICASTelefono/ Celular | AQ5: =AP5 -> NECESIDADES BÁSICASTelefono/ Celular
H6: =E6&F6 | I6: =IFERROR(VLOOKUP(H6,$AP:$AQ,2,FALSE),"Error") -> Error | J6: =IF(I6="Error","Revisa tu subcategoria",IF(I6=H6,"Es correcto",IF(H6="blanco","",""))) -> Revisa tu subcategoria | AN6: =Feb!$B$12 -> NECESIDADES BÁSICAS | AO6: =Feb!B15 -> Electricidad | AP6: =AN6&AO6 -> NECESIDADES BÁSICASElectricidad | AQ6: =AP6 -> NECESIDADES BÁSICASElectricidad
H7: =E7&F7 | I7: =IFERROR(VLOOKUP(H7,$AP:$AQ,2,FALSE),"Error") -> Error | J7: =IF(I7="Error","Revisa tu subcategoria",IF(I7=H7,"Es correcto",IF(H7="blanco","",""))) -> Revisa tu subcategoria | AN7: =Feb!$B$12 -> NECESIDADES BÁSICAS | AO7: =Feb!B16 -> Agua | AP7: =AN7&AO7 -> NECESIDADES BÁSICASAgua | AQ7: =AP7 -> NECESIDADES BÁSICASAgua
H8: =E8&F8 | I8: =IFERROR(VLOOKUP(H8,$AP:$AQ,2,FALSE),"Error") -> Error | J8: =IF(H8=I8,"Es correcto","Revisa tu subcategoria") -> Revisa tu subcategoria | AN8: =Feb!$B$12 -> NECESIDADES BÁSICAS | AO8: =Feb!B17 -> Gas | AP8: =AN8&AO8 -> NECESIDADES BÁSICASGas | AQ8: =AP8 -> NECESIDADES BÁSICASGas
H9: =E9&F9 | I9: =IFERROR(VLOOKUP(H9,$AP:$AQ,2,FALSE),"Error") -> Error | J9: =IF(H9=I9,"Es correcto","Revisa tu subcategoria") -> Revisa tu subcategoria | AN9: =Feb!$B$12 -> NECESIDADES BÁSICAS | AO9: =Feb!B18 -> Cable/Internet | AP9: =AN9&AO9 -> NECESIDADES BÁSICASCable/Internet | AQ9: =AP9 -> NECESIDADES BÁSICASCable/Internet
H10: =E10&F10 | I10: =IFERROR(VLOOKUP(H10,$AP:$AQ,2,FALSE),"Error") -> Error | J10: =IF(H10=I10,"Es correcto","Revisa tu subcategoria") -> Revisa tu subcategoria | AN10: =Feb!$B$12 -> NECESIDADES BÁSICAS | AO10: =Feb!B19 -> Super Mercado | AP10: =AN10&AO10 -> NECESIDADES BÁSICASSuper Mercado | AQ10: =AP10 -> NECESIDADES BÁSICASSuper Mercado
H11: =E11&F11 | I11: =IFERROR(VLOOKUP(H11,$AP:$AQ,2,FALSE),"Error") -> Error | J11: =IF(H11=I11,"Es correcto","Revisa tu subcategoria") -> Revisa tu subcategoria | AN11: =Feb!$B$12 -> NECESIDADES BÁSICAS | AO11: =Feb!B20 -> Gasolina | AP11: =AN11&AO11 -> NECESIDADES BÁSICASGasolina | AQ11: =AP11 -> NECESIDADES BÁSICASGasolina
H12: =E12&F12 | I12: =IFERROR(VLOOKUP(H12,$AP:$AQ,2,FALSE),"Error") -> Error | J12: =IF(H12=I12,"Es correcto","Revisa tu subcategoria") -> Revisa tu subcategoria | AN12: =Feb!$B$12 -> NECESIDADES BÁSICAS | AO12: =Feb!B21 -> Bus | AP12: =AN12&AO12 -> NECESIDADES BÁSICASBus | AQ12: =AP12 -> NECESIDADES BÁSICASBus
H13: =E13&F13 | I13: =IFERROR(VLOOKUP(H13,$AP:$AQ,2,FALSE),"Error") -> Error | J13: =IF(H13=I13,"Es correcto","Revisa tu subcategoria") -> Revisa tu subcategoria | AN13: =Feb!$B$12 -> NECESIDADES BÁSICAS | AO13: =Feb!B22 -> 0 | AP13: =AN13&AO13 -> NECESIDADES BÁSICAS0 | AQ13: =AP13 -> NECESIDADES BÁSICAS0
H14: =E14&F14 | I14: =IFERROR(VLOOKUP(H14,$AP:$AQ,2,FALSE),"Error") -> Error | J14: =IF(H14=I14,"Es correcto","Revisa tu subcategoria") -> Revisa tu subcategoria | AN14: =Feb!$B$12 -> NECESIDADES BÁSICAS | AO14: =Feb!B23 -> 0 | AP14: =AN14&AO14 -> NECESIDADES BÁSICAS0 | AQ14: =AP14 -> NECESIDADES BÁSICAS0
H15: =E15&F15 | I15: =IFERROR(VLOOKUP(H15,$AP:$AQ,2,FALSE),"Error") -> Error | J15: =IF(H15=I15,"Es correcto","Revisa tu subcategoria") -> Revisa tu subcategoria | AN15: =Feb!$B$12 -> NECESIDADES BÁSICAS | AO15: =Feb!B24 -> 0 | AP15: =AN15&AO15 -> NECESIDADES BÁSICAS0 | AQ15: =AP15 -> NECESIDADES BÁSICAS0
H16: =E16&F16 | I16: =IFERROR(VLOOKUP(H16,$AP:$AQ,2,FALSE),"Error") -> Error | J16: =IF(H16=I16,"Es correcto","Revisa tu subcategoria") -> Revisa tu subcategoria | AN16: =Feb!$H$12 -> AHORROS | AO16: =Feb!H13 -> Fondo de Emergencia | AP16: =AN16&AO16 -> AHORROSFondo de Emergencia | AQ16: =AP16 -> AHORROSFondo de Emergencia
H17: =E17&F17 | I17: =IFERROR(VLOOKUP(H17,$AP:$AQ,2,FALSE),"Error") -> Error | J17: =IF(H17=I17,"Es correcto","Revisa tu subcategoria") -> Revisa tu subcategoria | AN17: =Feb!$H$12 -> AHORROS | AO17: =Feb!H14 -> Fondo de Pensión | AP17: =AN17&AO17 -> AHORROSFondo de Pensión | AQ17: =AP17 -> AHORROSFondo de Pensión
H18: =E18&F18 | I18: =IFERROR(VLOOKUP(H18,$AP:$AQ,2,FALSE),"Error") -> Error | J18: =IF(H18=I18,"Es correcto","Revisa tu subcategoria") -> Revisa tu subcategoria | AN18: =Feb!$H$12 -> AHORROS | AO18: =Feb!H15 -> Fondo de Educación | AP18: =AN18&AO18 -> AHORROSFondo de Educación | AQ18: =AP18 -> AHORROSFondo de Educación
H19: =E19&F19 | I19: =IFERROR(VLOOKUP(H19,$AP:$AQ,2,FALSE),"Error") -> Error | J19: =IF(H19=I19,"Es correcto","Revisa tu subcategoria") -> Revisa tu subcategoria | AN19: =Feb!$H$12 -> AHORROS | AO19: =Feb!H16 -> Cuota Inicial Casa | AP19: =AN19&AO19 -> AHORROSCuota Inicial Casa | AQ19: =AP19 -> AHORROSCuota Inicial Casa
H20: =E20&F20 | I20: =IFERROR(VLOOKUP(H20,$AP:$AQ,2,FALSE),"Error") -> Error | J20: =IF(H20=I20,"Es correcto","Revisa tu subcategoria") -> Revisa tu subcategoria | AN20: =Feb!$H$12 -> AHORROS | AO20: =Feb!H17 -> Aporte a Capital | AP20: =AN20&AO20 -> AHORROSAporte a Capital | AQ20: =AP20 -> AHORROSAporte a Capital
H21: =E21&F21 | I21: =IFERROR(VLOOKUP(H21,$AP:$AQ,2,FALSE),"Error") -> Error | J21: =IF(H21=I21,"Es correcto","Revisa tu subcategoria") -> Revisa tu subcategoria | AN21: =Feb!$H$12 -> AHORROS | AO21: =Feb!H18 -> 0 | AP21: =AN21&AO21 -> AHORROS0 | AQ21: =AP21 -> AHORROS0
H22: =E22&F22 | I22: =IFERROR(VLOOKUP(H22,$AP:$AQ,2,FALSE),"Error") -> Error | J22: =IF(H22=I22,"Es correcto","Revisa tu subcategoria") -> Revisa tu subcategoria | AN22: =Feb!$H$12 -> AHORROS | AO22: =Feb!H19 -> 0 | AP22: =AN22&AO22 -> AHORROS0 | AQ22: =AP22 -> AHORROS0
H23: =E23&F23 | I23: =IFERROR(VLOOKUP(H23,$AP:$AQ,2,FALSE),"Error") -> Error | J23: =IF(H23=I23,"Es correcto","Revisa tu subcategoria") -> Revisa tu subcategoria | AN23: =Feb!$H$12 -> AHORROS | AO23: =Feb!H20 -> 0 | AP23: =AN23&AO23 -> AHORROS0 | AQ23: =AP23 -> AHORROS0
H24: =E24&F24 | I24: =IFERROR(VLOOKUP(H24,$AP:$AQ,2,FALSE),"Error") -> Error | J24: =IF(H24=I24,"Es correcto","Revisa tu subcategoria") -> Revisa tu subcategoria | AN24: =Feb!$H$12 -> AHORROS | AO24: =Feb!H21 -> 0 | AP24: =AN24&AO24 -> AHORROS0 | AQ24: =AP24 -> AHORROS0
H25: =E25&F25 | I25: =IFERROR(VLOOKUP(H25,$AP:$AQ,2,FALSE),"Error") -> Error | J25: =IF(H25=I25,"Es correcto","Revisa tu subcategoria") -> Revisa tu subcategoria | AN25: =Feb!$H$12 -> AHORROS | AO25: =Feb!H22 -> 0 | AP25: =AN25&AO25 -> AHORROS0 | AQ25: =AP25 -> AHORROS0
H26: =E26&F26 | I26: =IFERROR(VLOOKUP(H26,$AP:$AQ,2,FALSE),"Error") -> Error | J26: =IF(H26=I26,"Es correcto","Revisa tu subcategoria") -> Revisa tu subcategoria | AN26: =Feb!$H$12 -> AHORROS | AO26: =Feb!H23 -> 0 | AP26: =AN26&AO26 -> AHORROS0 | AQ26: =AP26 -> AHORROS0
H27: =E27&F27 | I27: =IFERROR(VLOOKUP(H27,$AP:$AQ,2,FALSE),"Error") -> Error | J27: =IF(H27=I27,"Es correcto","Revisa tu subcategoria") -> Revisa tu subcategoria | AN27: =Feb!$H$12 -> AHORROS | AO27: =Feb!H24 -> 0 | AP27: =AN27&AO27 -> AHORROS0 | AQ27: =AP27 -> AHORROS0
H28: =E28&F28 | I28: =IFERROR(VLOOKUP(H28,$AP:$AQ,2,FALSE),"Error") -> Error | J28: =IF(H28=I28,"Es correcto","Revisa tu subcategoria") -> Revisa tu subcategoria | AN28: =Feb!$B$27 -> DEUDAS | AO28: =Feb!B28 -> Deuda Carro | AP28: =AN28&AO28 -> DEUDASDeuda Carro | AQ28: =AP28 -> DEUDASDeuda Carro
H29: =E29&F29 | I29: =IFERROR(VLOOKUP(H29,$AP:$AQ,2,FALSE),"Error") -> Error | J29: =IF(H29=I29,"Es correcto","Revisa tu subcategoria") -> Revisa tu subcategoria | AN29: =Feb!$B$27 -> DEUDAS | AO29: =Feb!B29 -> Deuda tarjeta 1 | AP29: =AN29&AO29 -> DEUDASDeuda tarjeta 1 | AQ29: =AP29 -> DEUDASDeuda tarjeta 1
H30: =E30&F30 | I30: =IFERROR(VLOOKUP(H30,$AP:$AQ,2,FALSE),"Error") -> Error | J30: =IF(H30=I30,"Es correcto","Revisa tu subcategoria") -> Revisa tu subcategoria | AN30: =Feb!$B$27 -> DEUDAS | AO30: =Feb!B30 -> Deuda tarjeta 2 | AP30: =AN30&AO30 -> DEUDASDeuda tarjeta 2 | AQ30: =AP30 -> DEUDASDeuda tarjeta 2
H31: =E31&F31 | I31: =IFERROR(VLOOKUP(H31,$AP:$AQ,2,FALSE),"Error") -> Error | J31: =IF(H31=I31,"Es correcto","Revisa tu subcategoria") -> Revisa tu subcategoria | AN31: =Feb!$B$27 -> DEUDAS | AO31: =Feb!B31 -> Deuda Estudio | AP31: =AN31&AO31 -> DEUDASDeuda Estudio | AQ31: =AP31 -> DEUDASDeuda Estudio
H32: =E32&F32 | I32: =IFERROR(VLOOKUP(H32,$AP:$AQ,2,FALSE),"Error") -> Error | J32: =IF(H32=I32,"Es correcto","Revisa tu subcategoria") -> Revisa tu subcategoria | AN32: =Feb!$B$27 -> DEUDAS | AO32: =Feb!B32 -> Carro | AP32: =AN32&AO32 -> DEUDASCarro | AQ32: =AP32 -> DEUDASCarro
H33: =E33&F33 | I33: =IFERROR(VLOOKUP(H33,$AP:$AQ,2,FALSE),"Error") -> Error | J33: =IF(H33=I33,"Es correcto","Revisa tu subcategoria") -> Revisa tu subcategoria | AN33: =Feb!$B$27 -> DEUDAS | AO33: =Feb!B33 -> 0 | AP33: =AN33&AO33 -> DEUDAS0 | AQ33: =AP33 -> DEUDAS0
H34: =E34&F34 | I34: =IFERROR(VLOOKUP(H34,$AP:$AQ,2,FALSE),"Error") -> Error | J34: =IF(H34=I34,"Es correcto","Revisa tu subcategoria") -> Revisa tu subcategoria | AN34: =Feb!$B$27 -> DEUDAS | AO34: =Feb!B34 -> 0 | AP34: =AN34&AO34 -> DEUDAS0 | AQ34: =AP34 -> DEUDAS0
H35: =E35&F35 | I35: =IFERROR(VLOOKUP(H35,$AP:$AQ,2,FALSE),"Error") -> Error | J35: =IF(H35=I35,"Es correcto","Revisa tu subcategoria") -> Revisa tu subcategoria | AN35: =Feb!$B$27 -> DEUDAS | AO35: =Feb!B35 -> 0 | AP35: =AN35&AO35 -> DEUDAS0 | AQ35: =AP35 -> DEUDAS0
H36: =E36&F36 | I36: =IFERROR(VLOOKUP(H36,$AP:$AQ,2,FALSE),"Error") -> Error | J36: =IF(H36=I36,"Es correcto","Revisa tu subcategoria") -> Revisa tu subcategoria | AN36: =Feb!$H$27 -> REGALOS/ CARIDAD | AO36: =Feb!H28 -> Regalos Navidad | AP36: =AN36&AO36 -> REGALOS/ CARIDADRegalos Navidad | AQ36: =AP36 -> REGALOS/ CARIDADRegalos Navidad
H37: =E37&F37 | I37: =IFERROR(VLOOKUP(H37,$AP:$AQ,2,FALSE),"Error") -> Error | J37: =IF(H37=I37,"Es correcto","Revisa tu subcategoria") -> Revisa tu subcategoria | AN37: =Feb!$H$27 -> REGALOS/ CARIDAD | AO37: =Feb!H29 -> Regalos cumpleaños | AP37: =AN37&AO37 -> REGALOS/ CARIDADRegalos cumpleaños | AQ37: =AP37 -> REGALOS/ CARIDADRegalos cumpleaños
H38: =E38&F38 | I38: =IFERROR(VLOOKUP(H38,$AP:$AQ,2,FALSE),"Error") -> Error | J38: =IF(H38=I38,"Es correcto","Revisa tu subcategoria") -> Revisa tu subcategoria | AN38: =Feb!$H$27 -> REGALOS/ CARIDAD | AO38: =Feb!H30 -> Caridad | AP38: =AN38&AO38 -> REGALOS/ CARIDADCaridad | AQ38: =AP38 -> REGALOS/ CARIDADCaridad
H39: =E39&F39 | I39: =IFERROR(VLOOKUP(H39,$AP:$AQ,2,FALSE),"Error") -> Error | J39: =IF(H39=I39,"Es correcto","Revisa tu subcategoria") -> Revisa tu subcategoria | AN39: =Feb!$H$27 -> REGALOS/ CARIDAD | AO39: =Feb!H31 -> 0 | AP39: =AN39&AO39 -> REGALOS/ CARIDAD0 | AQ39: =AP39 -> REGALOS/ CARIDAD0
H40: =E40&F40 | I40: =IFERROR(VLOOKUP(H40,$AP:$AQ,2,FALSE),"Error") -> Error | J40: =IF(H40=I40,"Es correcto","Revisa tu subcategoria") -> Revisa tu subcategoria | AN40: =Feb!$H$27 -> REGALOS/ CARIDAD | AO40: =Feb!H32 -> 0 | AP40: =AN40&AO40 -> REGALOS/ CARIDAD0 | AQ40: =AP40 -> REGALOS/ CARIDAD0
H41: =E41&F41 | I41: =IFERROR(VLOOKUP(H41,$AP:$AQ,2,FALSE),"Error") -> Error | J41: =IF(H41=I41,"Es correcto","Revisa tu subcategoria") -> Revisa tu subcategoria | AN41: =Feb!$H$27 -> REGALOS/ CARIDAD | AO41: =Feb!H33 -> 0 | AP41: =AN41&AO41 -> REGALOS/ CARIDAD0 | AQ41: =AP41 -> REGALOS/ CARIDAD0
H42: =E42&F42 | I42: =IFERROR(VLOOKUP(H42,$AP:$AQ,2,FALSE),"Error") -> Error | J42: =IF(H42=I42,"Es correcto","Revisa tu subcategoria") -> Revisa tu subcategoria | AN42: =Feb!$H$27 -> REGALOS/ CARIDAD | AO42: =Feb!H34 -> 0 | AP42: =AN42&AO42 -> REGALOS/ CARIDAD0 | AQ42: =AP42 -> REGALOS/ CARIDAD0
H43: =E43&F43 | I43: =IFERROR(VLOOKUP(H43,$AP:$AQ,2,FALSE),"Error") -> Error | J43: =IF(H43=I43,"Es correcto","Revisa tu subcategoria") -> Revisa tu subcategoria | AN43: =Feb!$H$27 -> REGALOS/ CARIDAD | AO43: =Feb!H35 -> 0 | AP43: =AN43&AO43 -> REGALOS/ CARIDAD0 | AQ43: =AP43 -> REGALOS/ CARIDAD0
H44: =E44&F44 | I44: =IFERROR(VLOOKUP(H44,$AP:$AQ,2,FALSE),"Error") -> Error | J44: =IF(H44=I44,"Es correcto","Revisa tu subcategoria") -> Revisa tu subcategoria | AN44: =Feb!$B$38 -> CASA | AO44: =Feb!B39 -> Limpieza | AP44: =AN44&AO44 -> CASALimpieza | AQ44: =AP44 -> CASALimpieza
H45: =E45&F45 | I45: =IFERROR(VLOOKUP(H45,$AP:$AQ,2,FALSE),"Error") -> Error | J45: =IF(H45=I45,"Es correcto","Revisa tu subcategoria") -> Revisa tu subcategoria | AN45: =Feb!$B$38 -> CASA | AO45: =Feb!B40 -> Mantenimiento | AP45: =AN45&AO45 -> CASAMantenimiento | AQ45: =AP45 -> CASAMantenimiento
H46: =E46&F46 | I46: =IFERROR(VLOOKUP(H46,$AP:$AQ,2,FALSE),"Error") -> Error | J46: =IF(H46=I46,"Es correcto","Revisa tu subcategoria") -> Revisa tu subcategoria | AN46: =Feb!$B$38 -> CASA | AO46: =Feb!B41 -> Muebles | AP46: =AN46&AO46 -> CASAMuebles | AQ46: =AP46 -> CASAMuebles
H47: =E47&F47 | I47: =IFERROR(VLOOKUP(H47,$AP:$AQ,2,FALSE),"Error") -> Error | J47: =IF(H47=I47,"Es correcto","Revisa tu subcategoria") -> Revisa tu subcategoria | AN47: =Feb!$B$38 -> CASA | AO47: =Feb!B42 -> Impuestos | AP47: =AN47&AO47 -> CASAImpuestos | AQ47: =AP47 -> CASAImpuestos
H48: =E48&F48 | I48: =IFERROR(VLOOKUP(H48,$AP:$AQ,2,FALSE),"Error") -> Error | J48: =IF(H48=I48,"Es correcto","Revisa tu subcategoria") -> Revisa tu subcategoria | AN48: =Feb!$B$38 -> CASA | AO48: =Feb!B43 -> 0 | AP48: =AN48&AO48 -> CASA0 | AQ48: =AP48 -> CASA0
H49: =E49&F49 | I49: =IFERROR(VLOOKUP(H49,$AP:$AQ,2,FALSE),"Error") -> Error | J49: =IF(H49=I49,"Es correcto","Revisa tu subcategoria") -> Revisa tu subcategoria | AN49: =Feb!$B$38 -> CASA | AO49: =Feb!B44 -> 0 | AP49: =AN49&AO49 -> CASA0 | AQ49: =AP49 -> CASA0
H50: =E50&F50 | I50: =IFERROR(VLOOKUP(H50,$AP:$AQ,2,FALSE),"Error") -> Error | J50: =IF(H50=I50,"Es correcto","Revisa tu subcategoria") -> Revisa tu subcategoria | AN50: =Feb!$B$38 -> CASA | AO50: =Feb!B45 -> 0 | AP50: =AN50&AO50 -> CASA0 | AQ50: =AP50 -> CASA0
H51: =E51&F51 | I51: =IFERROR(VLOOKUP(H51,$AP:$AQ,2,FALSE),"Error") -> Error | J51: =IF(H51=I51,"Es correcto","Revisa tu subcategoria") -> Revisa tu subcategoria | AN51: =Feb!$H$38 -> TRANSPORTE | AO51: =Feb!H39 -> Uber/taxi | AP51: =AN51&AO51 -> TRANSPORTEUber/taxi | AQ51: =AP51 -> TRANSPORTEUber/taxi
H52: =E52&F52 | I52: =IFERROR(VLOOKUP(H52,$AP:$AQ,2,FALSE),"Error") -> Error | J52: =IF(H52=I52,"Es correcto","Revisa tu subcategoria") -> Revisa tu subcategoria | AN52: =Feb!$H$38 -> TRANSPORTE | AO52: =Feb!H40 -> Estacionamiento | AP52: =AN52&AO52 -> TRANSPORTEEstacionamiento | AQ52: =AP52 -> TRANSPORTEEstacionamiento
H53: =E53&F53 | I53: =IFERROR(VLOOKUP(H53,$AP:$AQ,2,FALSE),"Error") -> Error | J53: =IF(H53=I53,"Es correcto","Revisa tu subcategoria") -> Revisa tu subcategoria | AN53: =Feb!$H$38 -> TRANSPORTE | AO53: =Feb!H41 -> Mantenimiento | AP53: =AN53&AO53 -> TRANSPORTEMantenimiento | AQ53: =AP53 -> TRANSPORTEMantenimiento
H54: =E54&F54 | I54: =IFERROR(VLOOKUP(H54,$AP:$AQ,2,FALSE),"Error") -> Error | J54: =IF(H54=I54,"Es correcto","Revisa tu subcategoria") -> Revisa tu subcategoria | AN54: =Feb!$H$38 -> TRANSPORTE | AO54: =Feb!H42 -> Impuestos | AP54: =AN54&AO54 -> TRANSPORTEImpuestos | AQ54: =AP54 -> TRANSPORTEImpuestos
H55: =E55&F55 | I55: =IFERROR(VLOOKUP(H55,$AP:$AQ,2,FALSE),"Error") -> Error | J55: =IF(H55=I55,"Es correcto","Revisa tu subcategoria") -> Revisa tu subcategoria | AN55: =Feb!$H$38 -> TRANSPORTE | AO55: =Feb!H43 -> Panapass/Peaje | AP55: =AN55&AO55 -> TRANSPORTEPanapass/Peaje | AQ55: =AP55 -> TRANSPORTEPanapass/Peaje
H56: =E56&F56 | I56: =IFERROR(VLOOKUP(H56,$AP:$AQ,2,FALSE),"Error") -> Error | J56: =IF(H56=I56,"Es correcto","Revisa tu subcategoria") -> Revisa tu subcategoria | AN56: =Feb!$H$38 -> TRANSPORTE | AO56: =Feb!H44 -> 0 | AP56: =AN56&AO56 -> TRANSPORTE0 | AQ56: =AP56 -> TRANSPORTE0
H57: =E57&F57 | I57: =IFERROR(VLOOKUP(H57,$AP:$AQ,2,FALSE),"Error") -> Error | J57: =IF(H57=I57,"Es correcto","Revisa tu subcategoria") -> Revisa tu subcategoria | AN57: =Feb!$H$38 -> TRANSPORTE | AO57: =Feb!H45 -> 0 | AP57: =AN57&AO57 -> TRANSPORTE0 | AQ57: =AP57 -> TRANSPORTE0
H58: =E58&F58 | I58: =IFERROR(VLOOKUP(H58,$AP:$AQ,2,FALSE),"Error") -> Error | J58: =IF(H58=I58,"Es correcto","Revisa tu subcategoria") -> Revisa tu subcategoria | AN58: =Feb!$B$48 -> ALIMENTACIÓN | AO58: =Feb!B49 -> Restaurantes | AP58: =AN58&AO58 -> ALIMENTACIÓNRestaurantes | AQ58: =AP58 -> ALIMENTACIÓNRestaurantes
H59: =E59&F59 | I59: =IFERROR(VLOOKUP(H59,$AP:$AQ,2,FALSE),"Error") -> Error | J59: =IF(H59=I59,"Es correcto","Revisa tu subcategoria") -> Revisa tu subcategoria | AN59: =Feb!$B$48 -> ALIMENTACIÓN | AO59: =Feb!B50 -> Café/ Snacks | AP59: =AN59&AO59 -> ALIMENTACIÓNCafé/ Snacks | AQ59: =AP59 -> ALIMENTACIÓNCafé/ Snacks
H60: =E60&F60 | I60: =IFERROR(VLOOKUP(H60,$AP:$AQ,2,FALSE),"Error") -> Error | J60: =IF(H60=I60,"Es correcto","Revisa tu subcategoria") -> Revisa tu subcategoria | AN60: =Feb!$B$48 -> ALIMENTACIÓN | AO60: =Feb!B51 -> 0 | AP60: =AN60&AO60 -> ALIMENTACIÓN0 | AQ60: =AP60 -> ALIMENTACIÓN0
H61: =E61&F61 | I61: =IFERROR(VLOOKUP(H61,$AP:$AQ,2,FALSE),"Error") -> Error | J61: =IF(H61=I61,"Es correcto","Revisa tu subcategoria") -> Revisa tu subcategoria | AN61: =Feb!$B$48 -> ALIMENTACIÓN | AO61: =Feb!B52 -> 0 | AP61: =AN61&AO61 -> ALIMENTACIÓN0 | AQ61: =AP61 -> ALIMENTACIÓN0
H62: =E62&F62 | I62: =IFERROR(VLOOKUP(H62,$AP:$AQ,2,FALSE),"Error") -> Error | J62: =IF(H62=I62,"Es correcto","Revisa tu subcategoria") -> Revisa tu subcategoria | AN62: =Feb!$B$48 -> ALIMENTACIÓN | AO62: =Feb!B53 -> 0 | AP62: =AN62&AO62 -> ALIMENTACIÓN0 | AQ62: =AP62 -> ALIMENTACIÓN0
H63: =E63&F63 | I63: =IFERROR(VLOOKUP(H63,$AP:$AQ,2,FALSE),"Error") -> Error | J63: =IF(H63=I63,"Es correcto","Revisa tu subcategoria") -> Revisa tu subcategoria | AN63: =Feb!$B$48 -> ALIMENTACIÓN | AO63: =Feb!B54 -> 0 | AP63: =AN63&AO63 -> ALIMENTACIÓN0 | AQ63: =AP63 -> ALIMENTACIÓN0
H64: =E64&F64 | I64: =IFERROR(VLOOKUP(H64,$AP:$AQ,2,FALSE),"Error") -> Error | J64: =IF(H64=I64,"Es correcto","Revisa tu subcategoria") -> Revisa tu subcategoria | AN64: =Feb!$H$48 -> SEGUROS | AO64: =Feb!H49 -> Carro | AP64: =AN64&AO64 -> SEGUROSCarro | AQ64: =AP64 -> SEGUROSCarro
H65: =E65&F65 | I65: =IFERROR(VLOOKUP(H65,$AP:$AQ,2,FALSE),"Error") -> Error | J65: =IF(H65=I65,"Es correcto","Revisa tu subcategoria") -> Revisa tu subcategoria | AN65: =Feb!$H$48 -> SEGUROS | AO65: =Feb!H50 -> Vida | AP65: =AN65&AO65 -> SEGUROSVida | AQ65: =AP65 -> SEGUROSVida
H66: =E66&F66 | I66: =IFERROR(VLOOKUP(H66,$AP:$AQ,2,FALSE),"Error") -> Error | J66: =IF(H66=I66,"Es correcto","Revisa tu subcategoria") -> Revisa tu subcategoria | AN66: =Feb!$H$48 -> SEGUROS | AO66: =Feb!H51 -> Casa | AP66: =AN66&AO66 -> SEGUROSCasa | AQ66: =AP66 -> SEGUROSCasa
H67: =E67&F67 | I67: =IFERROR(VLOOKUP(H67,$AP:$AQ,2,FALSE),"Error") -> Error | J67: =IF(H67=I67,"Es correcto","Revisa tu subcategoria") -> Revisa tu subcategoria | AN67: =Feb!$H$48 -> SEGUROS | AO67: =Feb!H52 -> Salud | AP67: =AN67&AO67 -> SEGUROSSalud | AQ67: =AP67 -> SEGUROSSalud
H68: =E68&F68 | I68: =IFERROR(VLOOKUP(H68,$AP:$AQ,2,FALSE),"Error") -> Error | J68: =IF(H68=I68,"Es correcto","Revisa tu subcategoria") -> Revisa tu subcategoria | AN68: =Feb!$H$48 -> SEGUROS | AO68: =Feb!H53 -> 0 | AP68: =AN68&AO68 -> SEGUROS0 | AQ68: =AP68 -> SEGUROS0
H69: =E69&F69 | I69: =IFERROR(VLOOKUP(H69,$AP:$AQ,2,FALSE),"Error") -> Error | J69: =IF(H69=I69,"Es correcto","Revisa tu subcategoria") -> Revisa tu subcategoria | AN69: =Feb!$H$48 -> SEGUROS | AO69: =Feb!H54 -> 0 | AP69: =AN69&AO69 -> SEGUROS0 | AQ69: =AP69 -> SEGUROS0
H70: =E70&F70 | I70: =IFERROR(VLOOKUP(H70,$AP:$AQ,2,FALSE),"Error") -> Error | J70: =IF(H70=I70,"Es correcto","Revisa tu subcategoria") -> Revisa tu subcategoria | AN70: =Feb!$B$57 -> SALUD | AO70: =Feb!B58 -> Medicinas | AP70: =AN70&AO70 -> SALUDMedicinas | AQ70: =AP70 -> SALUDMedicinas
H71: =E71&F71 | I71: =IFERROR(VLOOKUP(H71,$AP:$AQ,2,FALSE),"Error") -> Error | J71: =IF(H71=I71,"Es correcto","Revisa tu subcategoria") -> Revisa tu subcategoria | AN71: =Feb!$B$57 -> SALUD | AO71: =Feb!B59 -> Dentista | AP71: =AN71&AO71 -> SALUDDentista | AQ71: =AP71 -> SALUDDentista
H72: =E72&F72 | I72: =IFERROR(VLOOKUP(H72,$AP:$AQ,2,FALSE),"Error") -> Error | J72: =IF(H72=I72,"Es correcto","Revisa tu subcategoria") -> Revisa tu subcategoria | AN72: =Feb!$B$57 -> SALUD | AO72: =Feb!B60 -> Tratamientos | AP72: =AN72&AO72 -> SALUDTratamientos | AQ72: =AP72 -> SALUDTratamientos
H73: =E73&F73 | I73: =IFERROR(VLOOKUP(H73,$AP:$AQ,2,FALSE),"Error") -> Error | J73: =IF(H73=I73,"Es correcto","Revisa tu subcategoria") -> Revisa tu subcategoria | AN73: =Feb!$B$57 -> SALUD | AO73: =Feb!B61 -> 0 | AP73: =AN73&AO73 -> SALUD0 | AQ73: =AP73 -> SALUD0
H74: =E74&F74 | I74: =IFERROR(VLOOKUP(H74,$AP:$AQ,2,FALSE),"Error") -> Error | J74: =IF(H74=I74,"Es correcto","Revisa tu subcategoria") -> Revisa tu subcategoria | AN74: =Feb!$B$57 -> SALUD | AO74: =Feb!B62 -> 0 | AP74: =AN74&AO74 -> SALUD0 | AQ74: =AP74 -> SALUD0
H75: =E75&F75 | I75: =IFERROR(VLOOKUP(H75,$AP:$AQ,2,FALSE),"Error") -> Error | J75: =IF(H75=I75,"Es correcto","Revisa tu subcategoria") -> Revisa tu subcategoria | AN75: =Feb!$B$57 -> SALUD | AO75: =Feb!B63 -> 0 | AP75: =AN75&AO75 -> SALUD0 | AQ75: =AP75 -> SALUD0
H76: =E76&F76 | I76: =IFERROR(VLOOKUP(H76,$AP:$AQ,2,FALSE),"Error") -> Error | J76: =IF(H76=I76,"Es correcto","Revisa tu subcategoria") -> Revisa tu subcategoria | AN76: =Feb!$B$57 -> SALUD | AO76: =Feb!B64 -> 0 | AP76: =AN76&AO76 -> SALUD0 | AQ76: =AP76 -> SALUD0
H77: =E77&F77 | I77: =IFERROR(VLOOKUP(H77,$AP:$AQ,2,FALSE),"Error") -> Error | J77: =IF(H77=I77,"Es correcto","Revisa tu subcategoria") -> Revisa tu subcategoria | AN77: =Feb!$H$57 -> CUIDADO PERSONAL | AO77: =Feb!H58 -> Ropa | AP77: =AN77&AO77 -> CUIDADO PERSONALRopa | AQ77: =AP77 -> CUIDADO PERSONALRopa
H78: =E78&F78 | I78: =IFERROR(VLOOKUP(H78,$AP:$AQ,2,FALSE),"Error") -> Error | J78: =IF(H78=I78,"Es correcto","Revisa tu subcategoria") -> Revisa tu subcategoria | AN78: =Feb!$H$57 -> CUIDADO PERSONAL | AO78: =Feb!H59 -> Belleza | AP78: =AN78&AO78 -> CUIDADO PERSONALBelleza | AQ78: =AP78 -> CUIDADO PERSONALBelleza
H79: =E79&F79 | I79: =IFERROR(VLOOKUP(H79,$AP:$AQ,2,FALSE),"Error") -> Error | J79: =IF(H79=I79,"Es correcto","Revisa tu subcategoria") -> Revisa tu subcategoria | AN79: =Feb!$H$57 -> CUIDADO PERSONAL | AO79: =Feb!H60 -> Peluquería | AP79: =AN79&AO79 -> CUIDADO PERSONALPeluquería | AQ79: =AP79 -> CUIDADO PERSONALPeluquería
H80: =E80&F80 | I80: =IFERROR(VLOOKUP(H80,$AP:$AQ,2,FALSE),"Error") -> Error | J80: =IF(H80=I80,"Es correcto","Revisa tu subcategoria") -> Revisa tu subcategoria | AN80: =Feb!$H$57 -> CUIDADO PERSONAL | AO80: =Feb!H61 -> Sastre | AP80: =AN80&AO80 -> CUIDADO PERSONALSastre | AQ80: =AP80 -> CUIDADO PERSONALSastre
H81: =E81&F81 | I81: =IFERROR(VLOOKUP(H81,$AP:$AQ,2,FALSE),"Error") -> Error | J81: =IF(H81=I81,"Es correcto","Revisa tu subcategoria") -> Revisa tu subcategoria | AN81: =Feb!$H$57 -> CUIDADO PERSONAL | AO81: =Feb!H62 -> Tintorería | AP81: =AN81&AO81 -> CUIDADO PERSONALTintorería | AQ81: =AP81 -> CUIDADO PERSONALTintorería
H82: =E82&F82 | I82: =IFERROR(VLOOKUP(H82,$AP:$AQ,2,FALSE),"Error") -> Error | J82: =IF(H82=I82,"Es correcto","Revisa tu subcategoria") -> Revisa tu subcategoria | AN82: =Feb!$H$57 -> CUIDADO PERSONAL | AO82: =Feb!H63 -> 0 | AP82: =AN82&AO82 -> CUIDADO PERSONAL0 | AQ82: =AP82 -> CUIDADO PERSONAL0
H83: =E83&F83 | I83: =IFERROR(VLOOKUP(H83,$AP:$AQ,2,FALSE),"Error") -> Error | J83: =IF(H83=I83,"Es correcto","Revisa tu subcategoria") -> Revisa tu subcategoria | AN83: =Feb!$H$57 -> CUIDADO PERSONAL | AO83: =Feb!H64 -> 0 | AP83: =AN83&AO83 -> CUIDADO PERSONAL0 | AQ83: =AP83 -> CUIDADO PERSONAL0
H84: =E84&F84 | I84: =IFERROR(VLOOKUP(H84,$AP:$AQ,2,FALSE),"Error") -> Error | J84: =IF(H84=I84,"Es correcto","Revisa tu subcategoria") -> Revisa tu subcategoria | AN84: =Feb!$B$67 -> ENTRETENIMIENTO | AO84: =Feb!B68 -> Vacaciones | AP84: =AN84&AO84 -> ENTRETENIMIENTOVacaciones | AQ84: =AP84 -> ENTRETENIMIENTOVacaciones
H85: =E85&F85 | I85: =IFERROR(VLOOKUP(H85,$AP:$AQ,2,FALSE),"Error") -> Error | J85: =IF(H85=I85,"Es correcto","Revisa tu subcategoria") -> Revisa tu subcategoria | AN85: =Feb!$B$67 -> ENTRETENIMIENTO | AO85: =Feb!B69 -> Rumba | AP85: =AN85&AO85 -> ENTRETENIMIENTORumba | AQ85: =AP85 -> ENTRETENIMIENTORumba
H86: =E86&F86 | I86: =IFERROR(VLOOKUP(H86,$AP:$AQ,2,FALSE),"Error") -> Error | J86: =IF(H86=I86,"Es correcto","Revisa tu subcategoria") -> Revisa tu subcategoria | AN86: =Feb!$B$67 -> ENTRETENIMIENTO | AO86: =Feb!B70 -> Citas | AP86: =AN86&AO86 -> ENTRETENIMIENTOCitas | AQ86: =AP86 -> ENTRETENIMIENTOCitas
H87: =E87&F87 | I87: =IFERROR(VLOOKUP(H87,$AP:$AQ,2,FALSE),"Error") -> Error | J87: =IF(H87=I87,"Es correcto","Revisa tu subcategoria") -> Revisa tu subcategoria | AN87: =Feb!$B$67 -> ENTRETENIMIENTO | AO87: =Feb!B71 -> Cine | AP87: =AN87&AO87 -> ENTRETENIMIENTOCine | AQ87: =AP87 -> ENTRETENIMIENTOCine
H88: =E88&F88 | I88: =IFERROR(VLOOKUP(H88,$AP:$AQ,2,FALSE),"Error") -> Error | J88: =IF(H88=I88,"Es correcto","Revisa tu subcategoria") -> Revisa tu subcategoria | AN88: =Feb!$B$67 -> ENTRETENIMIENTO | AO88: =Feb!B72 -> Deporte | AP88: =AN88&AO88 -> ENTRETENIMIENTODeporte | AQ88: =AP88 -> ENTRETENIMIENTODeporte
H89: =E89&F89 | I89: =IFERROR(VLOOKUP(H89,$AP:$AQ,2,FALSE),"Error") -> Error | J89: =IF(H89=I89,"Es correcto","Revisa tu subcategoria") -> Revisa tu subcategoria | AN89: =Feb!$B$67 -> ENTRETENIMIENTO | AO89: =Feb!B73 -> Netflix | AP89: =AN89&AO89 -> ENTRETENIMIENTONetflix | AQ89: =AP89 -> ENTRETENIMIENTONetflix
H90: =E90&F90 | I90: =IFERROR(VLOOKUP(H90,$AP:$AQ,2,FALSE),"Error") -> Error | J90: =IF(H90=I90,"Es correcto","Revisa tu subcategoria") -> Revisa tu subcategoria | AN90: =Feb!$B$67 -> ENTRETENIMIENTO | AO90: =Feb!B74 -> Spotify | AP90: =AN90&AO90 -> ENTRETENIMIENTOSpotify | AQ90: =AP90 -> ENTRETENIMIENTOSpotify
H91: =E91&F91 | I91: =IFERROR(VLOOKUP(H91,$AP:$AQ,2,FALSE),"Error") -> Error | J91: =IF(H91=I91,"Es correcto","Revisa tu subcategoria") -> Revisa tu subcategoria | AN91: =Feb!$B$67 -> ENTRETENIMIENTO | AO91: =Feb!B75 -> 0 | AP91: =AN91&AO91 -> ENTRETENIMIENTO0 | AQ91: =AP91 -> ENTRETENIMIENTO0
H92: =E92&F92 | I92: =IFERROR(VLOOKUP(H92,$AP:$AQ,2,FALSE),"Error") -> Error | J92: =IF(H92=I92,"Es correcto","Revisa tu subcategoria") -> Revisa tu subcategoria | AN92: =Feb!$B$67 -> ENTRETENIMIENTO | AO92: =Feb!B76 -> 0 | AP92: =AN92&AO92 -> ENTRETENIMIENTO0 | AQ92: =AP92 -> ENTRETENIMIENTO0
H93: =E93&F93 | I93: =IFERROR(VLOOKUP(H93,$AP:$AQ,2,FALSE),"Error") -> Error | J93: =IF(H93=I93,"Es correcto","Revisa tu subcategoria") -> Revisa tu subcategoria | AN93: =Feb!$B$67 -> ENTRETENIMIENTO | AO93: =Feb!B77 -> 0 | AP93: =AN93&AO93 -> ENTRETENIMIENTO0 | AQ93: =AP93 -> ENTRETENIMIENTO0
H94: =E94&F94 | I94: =IFERROR(VLOOKUP(H94,$AP:$AQ,2,FALSE),"Error") -> Error | J94: =IF(H94=I94,"Es correcto","Revisa tu subcategoria") -> Revisa tu subcategoria | AN94: =Feb!$B$67 -> ENTRETENIMIENTO | AO94: =Feb!B78 -> 0 | AP94: =AN94&AO94 -> ENTRETENIMIENTO0 | AQ94: =AP94 -> ENTRETENIMIENTO0
H95: =E95&F95 | I95: =IFERROR(VLOOKUP(H95,$AP:$AQ,2,FALSE),"Error") -> Error | J95: =IF(H95=I95,"Es correcto","Revisa tu subcategoria") -> Revisa tu subcategoria | AN95: =Feb!$H$67 -> HIJOS | AO95: =Feb!H68 -> Ropa | AP95: =AN95&AO95 -> HIJOSRopa | AQ95: =AP95 -> HIJOSRopa
H96: =E96&F96 | I96: =IFERROR(VLOOKUP(H96,$AP:$AQ,2,FALSE),"Error") -> Error | J96: =IF(H96=I96,"Es correcto","Revisa tu subcategoria") -> Revisa tu subcategoria | AN96: =Feb!$H$67 -> HIJOS | AO96: =Feb!H69 -> Estudio | AP96: =AN96&AO96 -> HIJOSEstudio | AQ96: =AP96 -> HIJOSEstudio
H97: =E97&F97 | I97: =IFERROR(VLOOKUP(H97,$AP:$AQ,2,FALSE),"Error") -> Error | J97: =IF(H97=I97,"Es correcto","Revisa tu subcategoria") -> Revisa tu subcategoria | AN97: =Feb!$H$67 -> HIJOS | AO97: =Feb!H70 -> Utiles Escolares | AP97: =AN97&AO97 -> HIJOSUtiles Escolares | AQ97: =AP97 -> HIJOSUtiles Escolares
H98: =E98&F98 | I98: =IFERROR(VLOOKUP(H98,$AP:$AQ,2,FALSE),"Error") -> Error | J98: =IF(H98=I98,"Es correcto","Revisa tu subcategoria") -> Revisa tu subcategoria | AN98: =Feb!$H$67 -> HIJOS | AO98: =Feb!H71 -> Niñera | AP98: =AN98&AO98 -> HIJOSNiñera | AQ98: =AP98 -> HIJOSNiñera
H99: =E99&F99 | I99: =IFERROR(VLOOKUP(H99,$AP:$AQ,2,FALSE),"Error") -> Error | J99: =IF(H99=I99,"Es correcto","Revisa tu subcategoria") -> Revisa tu subcategoria | AN99: =Feb!$H$67 -> HIJOS | AO99: =Feb!H72 -> 0 | AP99: =AN99&AO99 -> HIJOS0 | AQ99: =AP99 -> HIJOS0
H100: =E100&F100 | I100: =IFERROR(VLOOKUP(H100,$AP:$AQ,2,FALSE),"Error") -> Error | J100: =IF(H100=I100,"Es correcto","Revisa tu subcategoria") -> Revisa tu subcategoria | AN100: =Feb!$H$67 -> HIJOS | AO100: =Feb!H73 -> 0 | AP100: =AN100&AO100 -> HIJOS0 | AQ100: =AP100 -> HIJOS0
H101: =E101&F101 | I101: =IFERROR(VLOOKUP(H101,$AP:$AQ,2,FALSE),"Error") -> Error | J101: =IF(H101=I101,"Es correcto","Revisa tu subcategoria") -> Revisa tu subcategoria | AN101: =Feb!$H$67 -> HIJOS | AO101: =Feb!H74 -> 0 | AP101: =AN101&AO101 -> HIJOS0 | AQ101: =AP101 -> HIJOS0
...

Sheet Mar
U1: =B13 -> Arriendo/Hipoteca
B2: PRESUPUESTO MENSUAL
B4: Ingreso Estimado | C4: Salario
C10: Total Ingreso Mensual | E10: =SUM(E4:E9) -> 0 | H10: Balance (Ingreso vs Presupuesto) | K10: =E10-SUM(D25,D36,D55,D65,D79,D88,D98,J25,J36,J55,J65,J88,J98,D108,J108,D46,J46,J79) -> 0 | M10: =IF(K10=0,"El presupuesto está listo","OJO! Tiene que sumar cero") -> El presupuesto está listo
B12: NECESIDADES BÁSICAS | C12: Ahorro | D12: Presupuesto | E12: Gasto | F12: Disponible | H12: AHORROS | I12: Ahorro | J12: Presupuesto | K12: Gasto | L12: Disponible
B13: Arriendo/Hipoteca | E13: =SUMIFS('Mar - registro gastos'!$D$3:$D$300,'Mar - registro gastos'!$E$3:$E$300,Mar!$B$12,'Mar - registro gastos'!$F$3:$F$300,Mar!B13) -> 0 | F13: =D13-E13 -> 0 | H13: Fondo de Emergencia | K13: =SUMIFS('Mar - registro gastos'!$D$3:$D$300,'Mar - registro gastos'!$E$3:$E$300,Mar!$H$12,'Mar - registro gastos'!$F$3:$F$300,Mar!H13) -> 0 | L13: =J13-K13 -> 0
B14: Telefono/ Celular | E14: =SUMIFS('Mar - registro gastos'!$D$3:$D$300,'Mar - registro gastos'!$E$3:$E$300,Mar!$B$12,'Mar - registro gastos'!$F$3:$F$300,Mar!B14) -> 0 | F14: =D14-E14 -> 0 | H14: Fondo de Pensión | K14: =SUMIFS('Mar - registro gastos'!$D$3:$D$300,'Mar - registro gastos'!$E$3:$E$300,Mar!$H$12,'Mar - registro gastos'!$F$3:$F$300,Mar!H14) -> 0 | L14: =J14-K14 -> 0
B15: Electricidad | E15: =SUMIFS('Mar - registro gastos'!$D$3:$D$300,'Mar - registro gastos'!$E$3:$E$300,Mar!$B$12,'Mar - registro gastos'!$F$3:$F$300,Mar!B15) -> 0 | F15: =D15-E15 -> 0 | H15: Fondo de Educación | K15: =SUMIFS('Mar - registro gastos'!$D$3:$D$300,'Mar - registro gastos'!$E$3:$E$300,Mar!$H$12,'Mar - registro gastos'!$F$3:$F$300,Mar!H15) -> 0 | L15: =J15-K15 -> 0
B16: Agua | E16: =SUMIFS('Mar - registro gastos'!$D$3:$D$300,'Mar - registro gastos'!$E$3:$E$300,Mar!$B$12,'Mar - registro gastos'!$F$3:$F$300,Mar!B16) -> 0 | F16: =D16-E16 -> 0 | H16: Cuota Inicial Casa | K16: =SUMIFS('Mar - registro gastos'!$D$3:$D$300,'Mar - registro gastos'!$E$3:$E$300,Mar!$H$12,'Mar - registro gastos'!$F$3:$F$300,Mar!H16) -> 0 | L16: =J16-K16 -> 0
B17: Gas | E17: =SUMIFS('Mar - registro gastos'!$D$3:$D$300,'Mar - registro gastos'!$E$3:$E$300,Mar!$B$12,'Mar - registro gastos'!$F$3:$F$300,Mar!B17) -> 0 | F17: =D17-E17 -> 0 | H17: Aporte a Capital | K17: =SUMIFS('Mar - registro gastos'!$D$3:$D$300,'Mar - registro gastos'!$E$3:$E$300,Mar!$H$12,'Mar - registro gastos'!$F$3:$F$300,Mar!H17) -> 0 | L17: =J17-K17 -> 0
B18: Cable/Internet | E18: =SUMIFS('Mar - registro gastos'!$D$3:$D$300,'Mar - registro gastos'!$E$3:$E$300,Mar!$B$12,'Mar - registro gastos'!$F$3:$F$300,Mar!B18) -> 0 | F18: =D18-E18 -> 0 | K18: =SUMIFS('Mar - registro gastos'!$D$3:$D$300,'Mar - registro gastos'!$E$3:$E$300,Mar!$H$12,'Mar - registro gastos'!$F$3:$F$300,Mar!H18) -> 0 | L18: =J18-K18 -> 0
B19: Super Mercado | E19: =SUMIFS('Mar - registro gastos'!$D$3:$D$300,'Mar - registro gastos'!$E$3:$E$300,Mar!$B$12,'Mar - registro gastos'!$F$3:$F$300,Mar!B19) -> 0 | F19: =D19-E19 -> 0 | K19: =SUMIFS('Mar - registro gastos'!$D$3:$D$300,'Mar - registro gastos'!$E$3:$E$300,Mar!$H$12,'Mar - registro gastos'!$F$3:$F$300,Mar!H19) -> 0 | L19: =J19-K19 -> 0
B20: Gasolina | E20: =SUMIFS('Mar - registro gastos'!$D$3:$D$300,'Mar - registro gastos'!$E$3:$E$300,Mar!$B$12,'Mar - registro gastos'!$F$3:$F$300,Mar!B20) -> 0 | F20: =D20-E20 -> 0 | K20: =SUMIFS('Mar - registro gastos'!$D$3:$D$300,'Mar - registro gastos'!$E$3:$E$300,Mar!$H$12,'Mar - registro gastos'!$F$3:$F$300,Mar!H20) -> 0 | L20: =J20-K20 -> 0
B21: Bus | E21: =SUMIFS('Mar - registro gastos'!$D$3:$D$300,'Mar - registro gastos'!$E$3:$E$300,Mar!$B$12,'Mar - registro gastos'!$F$3:$F$300,Mar!B21) -> 0 | F21: =D21-E21 -> 0 | K21: =SUMIFS('Mar - registro gastos'!$D$3:$D$300,'Mar - registro gastos'!$E$3:$E$300,Mar!$H$12,'Mar - registro gastos'!$F$3:$F$300,Mar!H21) -> 0 | L21: =J21-K21 -> 0
E22: =SUMIFS('Mar - registro gastos'!$D$3:$D$300,'Mar - registro gastos'!$E$3:$E$300,Mar!$B$12,'Mar - registro gastos'!$F$3:$F$300,Mar!B22) -> 0 | F22: =D22-E22 -> 0 | K22: =SUMIFS('Mar - registro gastos'!$D$3:$D$300,'Mar - registro gastos'!$E$3:$E$300,Mar!$H$12,'Mar - registro gastos'!$F$3:$F$300,Mar!H22) -> 0 | L22: =J22-K22 -> 0
E23: =SUMIFS('Mar - registro gastos'!$D$3:$D$300,'Mar - registro gastos'!$E$3:$E$300,Mar!$B$12,'Mar - registro gastos'!$F$3:$F$300,Mar!B23) -> 0 | F23: =D23-E23 -> 0 | K23: =SUMIFS('Mar - registro gastos'!$D$3:$D$300,'Mar - registro gastos'!$E$3:$E$300,Mar!$H$12,'Mar - registro gastos'!$F$3:$F$300,Mar!H23) -> 0 | L23: =J23-K23 -> 0
E24: =SUMIFS('Mar - registro gastos'!$D$3:$D$300,'Mar - registro gastos'!$E$3:$E$300,Mar!$B$12,'Mar - registro gastos'!$F$3:$F$300,Mar!B24) -> 0 | F24: =D24-E24 -> 0 | K24: =SUMIFS('Mar - registro gastos'!$D$3:$D$300,'Mar - registro gastos'!$E$3:$E$300,Mar!$H$12,'Mar - registro gastos'!$F$3:$F$300,Mar!H24) -> 0 | L24: =J24-K24 -> 0
B25: Subtotal | D25: =SUM(D13:D24) -> 0 | E25: =SUM(E13:E24) -> 0 | F25: =D25-E25 -> 0 | H25: Subtotal | J25: =SUM(J13:J24) -> 0 | K25: =SUM(K13:K24) -> 0 | L25: =J25-K25 -> 0
B27: DEUDAS | C27: Ahorro | D27: Presupuesto | E27: Gasto | F27: Disponible | H27: REGALOS/ CARIDAD | I27: Ahorro | J27: Presupuesto | K27: Gasto | L27: Disponible
B28: Deuda Carro | E28: =SUMIFS('Mar - registro gastos'!$D$3:$D$300,'Mar - registro gastos'!$E$3:$E$300,Mar!$B$27,'Mar - registro gastos'!$F$3:$F$300,Mar!B28) -> 0 | F28: =D28-E28 -> 0 | H28: Regalos Navidad | K28: =SUMIFS('Mar - registro gastos'!$D$3:$D$300,'Mar - registro gastos'!$E$3:$E$300,Mar!$H$27,'Mar - registro gastos'!$F$3:$F$300,Mar!H28) -> 0 | L28: =J28-K28 -> 0
B29: Deuda tarjeta 1 | E29: =SUMIFS('Mar - registro gastos'!$D$3:$D$300,'Mar - registro gastos'!$E$3:$E$300,Mar!$B$27,'Mar - registro gastos'!$F$3:$F$300,Mar!B29) -> 0 | F29: =D29-E29 -> 0 | H29: Regalos cumpleaños | K29: =SUMIFS('Mar - registro gastos'!$D$3:$D$300,'Mar - registro gastos'!$E$3:$E$300,Mar!$H$27,'Mar - registro gastos'!$F$3:$F$300,Mar!H29) -> 0 | L29: =J29-K29 -> 0
B30: Deuda tarjeta 2 | E30: =SUMIFS('Mar - registro gastos'!$D$3:$D$300,'Mar - registro gastos'!$E$3:$E$300,Mar!$B$27,'Mar - registro gastos'!$F$3:$F$300,Mar!B30) -> 0 | F30: =D30-E30 -> 0 | H30: Caridad | K30: =SUMIFS('Mar - registro gastos'!$D$3:$D$300,'Mar - registro gastos'!$E$3:$E$300,Mar!$H$27,'Mar - registro gastos'!$F$3:$F$300,Mar!H30) -> 0 | L30: =J30-K30 -> 0
B31: Deuda Estudio | E31: =SUMIFS('Mar - registro gastos'!$D$3:$D$300,'Mar - registro gastos'!$E$3:$E$300,Mar!$B$27,'Mar - registro gastos'!$F$3:$F$300,Mar!B31) -> 0 | F31: =D31-E31 -> 0 | K31: =SUMIFS('Mar - registro gastos'!$D$3:$D$300,'Mar - registro gastos'!$E$3:$E$300,Mar!$H$27,'Mar - registro gastos'!$F$3:$F$300,Mar!H31) -> 0 | L31: =J31-K31 -> 0
B32: Carro | E32: =SUMIFS('Mar - registro gastos'!$D$3:$D$300,'Mar - registro gastos'!$E$3:$E$300,Mar!$B$27,'Mar - registro gastos'!$F$3:$F$300,Mar!B32) -> 0 | F32: =D32-E32 -> 0 | K32: =SUMIFS('Mar - registro gastos'!$D$3:$D$300,'Mar - registro gastos'!$E$3:$E$300,Mar!$H$27,'Mar - registro gastos'!$F$3:$F$300,Mar!H32) -> 0 | L32: =J32-K32 -> 0
E33: =SUMIFS('Mar - registro gastos'!$D$3:$D$300,'Mar - registro gastos'!$E$3:$E$300,Mar!$B$27,'Mar - registro gastos'!$F$3:$F$300,Mar!B33) -> 0 | F33: =D33-E33 -> 0 | K33: =SUMIFS('Mar - registro gastos'!$D$3:$D$300,'Mar - registro gastos'!$E$3:$E$300,Mar!$H$27,'Mar - registro gastos'!$F$3:$F$300,Mar!H33) -> 0 | L33: =J33-K33 -> 0
E34: =SUMIFS('Mar - registro gastos'!$D$3:$D$300,'Mar - registro gastos'!$E$3:$E$300,Mar!$B$27,'Mar - registro gastos'!$F$3:$F$300,Mar!B34) -> 0 | F34: =D34-E34 -> 0 | K34: =SUMIFS('Mar - registro gastos'!$D$3:$D$300,'Mar - registro gastos'!$E$3:$E$300,Mar!$H$27,'Mar - registro gastos'!$F$3:$F$300,Mar!H34) -> 0 | L34: =J34-K34 -> 0
E35: =SUMIFS('Mar - registro gastos'!$D$3:$D$300,'Mar - registro gastos'!$E$3:$E$300,Mar!$B$27,'Mar - registro gastos'!$F$3:$F$300,Mar!B35) -> 0 | F35: =D35-E35 -> 0 | K35: =SUMIFS('Mar - registro gastos'!$D$3:$D$300,'Mar - registro gastos'!$E$3:$E$300,Mar!$H$27,'Mar - registro gastos'!$F$3:$F$300,Mar!H35) -> 0 | L35: =J35-K35 -> 0
B36: Subtotal | D36: =SUM(D28:D35) -> 0 | E36: =SUM(E28:E35) -> 0 | F36: =D36-E36 -> 0 | H36: Subtotal | J36: =SUM(J28:J35) -> 0 | K36: =SUM(K28:K35) -> 0 | L36: =J36-K36 -> 0
B38: CASA | C38: Ahorro | D38: Presupuesto | E38: Gasto | F38: Disponible | H38: TRANSPORTE | I38: Ahorro | J38: Presupuesto | K38: Gasto | L38: Disponible
B39: Limpieza | E39: =SUMIFS('Mar - registro gastos'!$D$3:$D$300,'Mar - registro gastos'!$E$3:$E$300,Mar!$B$38,'Mar - registro gastos'!$F$3:$F$300,Mar!B39) -> 0 | F39: =D39-E39 -> 0 | H39: Uber/taxi | K39: =SUMIFS('Mar - registro gastos'!$D$3:$D$300,'Mar - registro gastos'!$E$3:$E$300,Mar!$H$38,'Mar - registro gastos'!$F$3:$F$300,Mar!H39) -> 0 | L39: =J39-K39 -> 0
B40: Mantenimiento | E40: =SUMIFS('Mar - registro gastos'!$D$3:$D$300,'Mar - registro gastos'!$E$3:$E$300,Mar!$B$38,'Mar - registro gastos'!$F$3:$F$300,Mar!B40) -> 0 | F40: =D40-E40 -> 0 | H40: Estacionamiento | K40: =SUMIFS('Mar - registro gastos'!$D$3:$D$300,'Mar - registro gastos'!$E$3:$E$300,Mar!$H$38,'Mar - registro gastos'!$F$3:$F$300,Mar!H40) -> 0 | L40: =J40-K40 -> 0
B41: Muebles | E41: =SUMIFS('Mar - registro gastos'!$D$3:$D$300,'Mar - registro gastos'!$E$3:$E$300,Mar!$B$38,'Mar - registro gastos'!$F$3:$F$300,Mar!B41) -> 0 | F41: =D41-E41 -> 0 | H41: Mantenimiento | K41: =SUMIFS('Mar - registro gastos'!$D$3:$D$300,'Mar - registro gastos'!$E$3:$E$300,Mar!$H$38,'Mar - registro gastos'!$F$3:$F$300,Mar!H41) -> 0 | L41: =J41-K41 -> 0
B42: Impuestos | E42: =SUMIFS('Mar - registro gastos'!$D$3:$D$300,'Mar - registro gastos'!$E$3:$E$300,Mar!$B$38,'Mar - registro gastos'!$F$3:$F$300,Mar!B42) -> 0 | F42: =D42-E42 -> 0 | H42: Impuestos | K42: =SUMIFS('Mar - registro gastos'!$D$3:$D$300,'Mar - registro gastos'!$E$3:$E$300,Mar!$H$38,'Mar - registro gastos'!$F$3:$F$300,Mar!H42) -> 0 | L42: =J42-K42 -> 0
E43: =SUMIFS('Mar - registro gastos'!$D$3:$D$300,'Mar - registro gastos'!$E$3:$E$300,Mar!$B$38,'Mar - registro gastos'!$F$3:$F$300,Mar!B43) -> 0 | F43: =D43-E43 -> 0 | H43: Panapass/Peaje | K43: =SUMIFS('Mar - registro gastos'!$D$3:$D$300,'Mar - registro gastos'!$E$3:$E$300,Mar!$H$38,'Mar - registro gastos'!$F$3:$F$300,Mar!H43) -> 0 | L43: =J43-K43 -> 0
E44: =SUMIFS('Mar - registro gastos'!$D$3:$D$300,'Mar - registro gastos'!$E$3:$E$300,Mar!$B$38,'Mar - registro gastos'!$F$3:$F$300,Mar!B44) -> 0 | F44: =D44-E44 -> 0 | K44: =SUMIFS('Mar - registro gastos'!$D$3:$D$300,'Mar - registro gastos'!$E$3:$E$300,Mar!$H$38,'Mar - registro gastos'!$F$3:$F$300,Mar!H44) -> 0 | L44: =J44-K44 -> 0
E45: =SUMIFS('Mar - registro gastos'!$D$3:$D$300,'Mar - registro gastos'!$E$3:$E$300,Mar!$B$38,'Mar - registro gastos'!$F$3:$F$300,Mar!B45) -> 0 | F45: =D45-E45 -> 0 | K45: =SUMIFS('Mar - registro gastos'!$D$3:$D$300,'Mar - registro gastos'!$E$3:$E$300,Mar!$H$38,'Mar - registro gastos'!$F$3:$F$300,Mar!H45) -> 0 | L45: =J45-K45 -> 0
B46: Subtotal | D46: =SUM(D39:D45) -> 0 | E46: =SUM(E39:E45) -> 0 | F46: =D46-E46 -> 0 | H46: Subtotal | J46: =SUM(J39:J45) -> 0 | K46: =SUM(K39:K45) -> 0 | L46: =J46-K46 -> 0
B48: ALIMENTACIÓN | C48: Ahorro | D48: Presupuesto | E48: Gasto | F48: Disponible | H48: SEGUROS | I48: Ahorro | J48: Presupuesto | K48: Gasto | L48: Disponible
B49: Restaurantes | E49: =SUMIFS('Mar - registro gastos'!$D$3:$D$300,'Mar - registro gastos'!$E$3:$E$300,Mar!$B$48,'Mar - registro gastos'!$F$3:$F$300,Mar!B49) -> 0 | F49: =D49-E49 -> 0 | H49: Carro | K49: =SUMIFS('Mar - registro gastos'!$D$3:$D$300,'Mar - registro gastos'!$E$3:$E$300,Mar!$H$48,'Mar - registro gastos'!$F$3:$F$300,Mar!H49) -> 0 | L49: =J49-K49 -> 0
B50: Café/ Snacks | E50: =SUMIFS('Mar - registro gastos'!$D$3:$D$300,'Mar - registro gastos'!$E$3:$E$300,Mar!$B$48,'Mar - registro gastos'!$F$3:$F$300,Mar!B50) -> 0 | F50: =D50-E50 -> 0 | H50: Vida | K50: =SUMIFS('Mar - registro gastos'!$D$3:$D$300,'Mar - registro gastos'!$E$3:$E$300,Mar!$H$48,'Mar - registro gastos'!$F$3:$F$300,Mar!H50) -> 0 | L50: =J50-K50 -> 0
E51: =SUMIFS('Mar - registro gastos'!$D$3:$D$300,'Mar - registro gastos'!$E$3:$E$300,Mar!$B$48,'Mar - registro gastos'!$F$3:$F$300,Mar!B51) -> 0 | F51: =D51-E51 -> 0 | H51: Casa | K51: =SUMIFS('Mar - registro gastos'!$D$3:$D$300,'Mar - registro gastos'!$E$3:$E$300,Mar!$H$48,'Mar - registro gastos'!$F$3:$F$300,Mar!H51) -> 0 | L51: =J51-K51 -> 0
E52: =SUMIFS('Mar - registro gastos'!$D$3:$D$300,'Mar - registro gastos'!$E$3:$E$300,Mar!$B$48,'Mar - registro gastos'!$F$3:$F$300,Mar!B52) -> 0 | F52: =D52-E52 -> 0 | H52: Salud | K52: =SUMIFS('Mar - registro gastos'!$D$3:$D$300,'Mar - registro gastos'!$E$3:$E$300,Mar!$H$48,'Mar - registro gastos'!$F$3:$F$300,Mar!H52) -> 0 | L52: =J52-K52 -> 0
E53: =SUMIFS('Mar - registro gastos'!$D$3:$D$300,'Mar - registro gastos'!$E$3:$E$300,Mar!$B$48,'Mar - registro gastos'!$F$3:$F$300,Mar!B53) -> 0 | F53: =D53-E53 -> 0 | K53: =SUMIFS('Mar - registro gastos'!$D$3:$D$300,'Mar - registro gastos'!$E$3:$E$300,Mar!$H$48,'Mar - registro gastos'!$F$3:$F$300,Mar!H53) -> 0 | L53: =J53-K53 -> 0
E54: =SUMIFS('Mar - registro gastos'!$D$3:$D$300,'Mar - registro gastos'!$E$3:$E$300,Mar!$B$48,'Mar - registro gastos'!$F$3:$F$300,Mar!B54) -> 0 | F54: =D54-E54 -> 0 | K54: =SUMIFS('Mar - registro gastos'!$D$3:$D$300,'Mar - registro gastos'!$E$3:$E$300,Mar!$H$48,'Mar - registro gastos'!$F$3:$F$300,Mar!H54) -> 0 | L54: =J54-K54 -> 0
B55: Subtotal | D55: =SUM(D49:D54) -> 0 | E55: =SUM(E49:E54) -> 0 | F55: =D55-E55 -> 0 | H55: Subtotal | J55: =SUM(J49:J54) -> 0 | K55: =SUM(K49:K54) -> 0 | L55: =J55-K55 -> 0
B57: SALUD | C57: Ahorro | D57: Presupuesto | E57: Gasto | F57: Disponible | H57: CUIDADO PERSONAL | I57: Ahorro | J57: Presupuesto | K57: Gasto | L57: Disponible
B58: Medicinas | E58: =SUMIFS('Mar - registro gastos'!$D$3:$D$300,'Mar - registro gastos'!$E$3:$E$300,Mar!$B$57,'Mar - registro gastos'!$F$3:$F$300,Mar!B58) -> 0 | F58: =D58-E58 -> 0 | H58: Ropa | K58: =SUMIFS('Mar - registro gastos'!$D$3:$D$300,'Mar - registro gastos'!$E$3:$E$300,Mar!$H$57,'Mar - registro gastos'!$F$3:$F$300,Mar!H58) -> 0 | L58: =J58-K58 -> 0
B59: Dentista | E59: =SUMIFS('Mar - registro gastos'!$D$3:$D$300,'Mar - registro gastos'!$E$3:$E$300,Mar!$B$57,'Mar - registro gastos'!$F$3:$F$300,Mar!B59) -> 0 | F59: =D59-E59 -> 0 | H59: Belleza | K59: =SUMIFS('Mar - registro gastos'!$D$3:$D$300,'Mar - registro gastos'!$E$3:$E$300,Mar!$H$57,'Mar - registro gastos'!$F$3:$F$300,Mar!H59) -> 0 | L59: =J59-K59 -> 0
B60: Tratamientos | E60: =SUMIFS('Mar - registro gastos'!$D$3:$D$300,'Mar - registro gastos'!$E$3:$E$300,Mar!$B$57,'Mar - registro gastos'!$F$3:$F$300,Mar!B60) -> 0 | F60: =D60-E60 -> 0 | H60: Peluquería | K60: =SUMIFS('Mar - registro gastos'!$D$3:$D$300,'Mar - registro gastos'!$E$3:$E$300,Mar!$H$57,'Mar - registro gastos'!$F$3:$F$300,Mar!H60) -> 0 | L60: =J60-K60 -> 0
E61: =SUMIFS('Mar - registro gastos'!$D$3:$D$300,'Mar - registro gastos'!$E$3:$E$300,Mar!$B$57,'Mar - registro gastos'!$F$3:$F$300,Mar!B61) -> 0 | F61: =D61-E61 -> 0 | H61: Sastre | K61: =SUMIFS('Mar - registro gastos'!$D$3:$D$300,'Mar - registro gastos'!$E$3:$E$300,Mar!$H$57,'Mar - registro gastos'!$F$3:$F$300,Mar!H61) -> 0 | L61: =J61-K61 -> 0
E62: =SUMIFS('Mar - registro gastos'!$D$3:$D$300,'Mar - registro gastos'!$E$3:$E$300,Mar!$B$57,'Mar - registro gastos'!$F$3:$F$300,Mar!B62) -> 0 | F62: =D62-E62 -> 0 | H62: Tintorería | K62: =SUMIFS('Mar - registro gastos'!$D$3:$D$300,'Mar - registro gastos'!$E$3:$E$300,Mar!$H$57,'Mar - registro gastos'!$F$3:$F$300,Mar!H62) -> 0 | L62: =J62-K62 -> 0
E63: =SUMIFS('Mar - registro gastos'!$D$3:$D$300,'Mar - registro gastos'!$E$3:$E$300,Mar!$B$57,'Mar - registro gastos'!$F$3:$F$300,Mar!B63) -> 0 | F63: =D63-E63 -> 0 | K63: =SUMIFS('Mar - registro gastos'!$D$3:$D$300,'Mar - registro gastos'!$E$3:$E$300,Mar!$H$57,'Mar - registro gastos'!$F$3:$F$300,Mar!H63) -> 0 | L63: =J63-K63 -> 0
E64: =SUMIFS('Mar - registro gastos'!$D$3:$D$300,'Mar - registro gastos'!$E$3:$E$300,Mar!$B$57,'Mar - registro gastos'!$F$3:$F$300,Mar!B64) -> 0 | F64: =D64-E64 -> 0 | K64: =SUMIFS('Mar - registro gastos'!$D$3:$D$300,'Mar - registro gastos'!$E$3:$E$300,Mar!$H$57,'Mar - registro gastos'!$F$3:$F$300,Mar!H64) -> 0 | L64: =J64-K64 -> 0
B65: Subtotal | D65: =SUM(D58:D64) -> 0 | E65: =SUM(E58:E64) -> 0 | F65: =D65-E65 -> 0 | H65: Subtotal | J65: =SUM(J58:J64) -> 0 | K65: =SUM(K58:K64) -> 0 | L65: =J65-K65 -> 0
B67: ENTRETENIMIENTO | C67: Ahorro | D67: Presupuesto | E67: Gasto | F67: Disponible | H67: HIJOS | I67: Ahorro | J67: Presupuesto | K67: Gasto | L67: Diferencia
B68: Vacaciones | E68: =SUMIFS('Mar - registro gastos'!$D$3:$D$300,'Mar - registro gastos'!$E$3:$E$300,Mar!$B$67,'Mar - registro gastos'!$F$3:$F$300,Mar!B68) -> 0 | F68: =D68-E68 -> 0 | H68: Ropa | K68: =SUMIFS('Mar - registro gastos'!$D$3:$D$300,'Mar - registro gastos'!$E$3:$E$300,Mar!$H$67,'Mar - registro gastos'!$F$3:$F$300,Mar!H68) -> 0 | L68: =J68-K68 -> 0
B69: Rumba | E69: =SUMIFS('Mar - registro gastos'!$D$3:$D$300,'Mar - registro gastos'!$E$3:$E$300,Mar!$B$67,'Mar - registro gastos'!$F$3:$F$300,Mar!B69) -> 0 | F69: =D69-E69 -> 0 | H69: Estudio | K69: =SUMIFS('Mar - registro gastos'!$D$3:$D$300,'Mar - registro gastos'!$E$3:$E$300,Mar!$H$67,'Mar - registro gastos'!$F$3:$F$300,Mar!H69) -> 0 | L69: =J69-K69 -> 0
B70: Citas | E70: =SUMIFS('Mar - registro gastos'!$D$3:$D$300,'Mar - registro gastos'!$E$3:$E$300,Mar!$B$67,'Mar - registro gastos'!$F$3:$F$300,Mar!B70) -> 0 | F70: =D70-E70 -> 0 | H70: Utiles Escolares | K70: =SUMIFS('Mar - registro gastos'!$D$3:$D$300,'Mar - registro gastos'!$E$3:$E$300,Mar!$H$67,'Mar - registro gastos'!$F$3:$F$300,Mar!H70) -> 0 | L70: =J70-K70 -> 0
B71: Cine | E71: =SUMIFS('Mar - registro gastos'!$D$3:$D$300,'Mar - registro gastos'!$E$3:$E$300,Mar!$B$67,'Mar - registro gastos'!$F$3:$F$300,Mar!B71) -> 0 | F71: =D71-E71 -> 0 | H71: Niñera | K71: =SUMIFS('Mar - registro gastos'!$D$3:$D$300,'Mar - registro gastos'!$E$3:$E$300,Mar!$H$67,'Mar - registro gastos'!$F$3:$F$300,Mar!H71) -> 0 | L71: =J71-K71 -> 0
B72: Deporte | E72: =SUMIFS('Mar - registro gastos'!$D$3:$D$300,'Mar - registro gastos'!$E$3:$E$300,Mar!$B$67,'Mar - registro gastos'!$F$3:$F$300,Mar!B72) -> 0 | F72: =D72-E72 -> 0 | K72: =SUMIFS('Mar - registro gastos'!$D$3:$D$300,'Mar - registro gastos'!$E$3:$E$300,Mar!$H$67,'Mar - registro gastos'!$F$3:$F$300,Mar!H72) -> 0 | L72: =J72-K72 -> 0
B73: Netflix | E73: =SUMIFS('Mar - registro gastos'!$D$3:$D$300,'Mar - registro gastos'!$E$3:$E$300,Mar!$B$67,'Mar - registro gastos'!$F$3:$F$300,Mar!B73) -> 0 | F73: =D73-E73 -> 0 | K73: =SUMIFS('Mar - registro gastos'!$D$3:$D$300,'Mar - registro gastos'!$E$3:$E$300,Mar!$H$67,'Mar - registro gastos'!$F$3:$F$300,Mar!H73) -> 0 | L73: =J73-K73 -> 0
B74: Spotify | E74: =SUMIFS('Mar - registro gastos'!$D$3:$D$300,'Mar - registro gastos'!$E$3:$E$300,Mar!$B$67,'Mar - registro gastos'!$F$3:$F$300,Mar!B74) -> 0 | F74: =D74-E74 -> 0 | K74: =SUMIFS('Mar - registro gastos'!$D$3:$D$300,'Mar - registro gastos'!$E$3:$E$300,Mar!$H$67,'Mar - registro gastos'!$F$3:$F$300,Mar!H74) -> 0 | L74: =J74-K74 -> 0
E75: =SUMIFS('Mar - registro gastos'!$D$3:$D$300,'Mar - registro gastos'!$E$3:$E$300,Mar!$B$67,'Mar - registro gastos'!$F$3:$F$300,Mar!B75) -> 0 | F75: =D75-E75 -> 0 | K75: =SUMIFS('Mar - registro gastos'!$D$3:$D$300,'Mar - registro gastos'!$E$3:$E$300,Mar!$H$67,'Mar - registro gastos'!$F$3:$F$300,Mar!H75) -> 0 | L75: =J75-K75 -> 0
E76: =SUMIFS('Mar - registro gastos'!$D$3:$D$300,'Mar - registro gastos'!$E$3:$E$300,Mar!$B$67,'Mar - registro gastos'!$F$3:$F$300,Mar!B76) -> 0 | F76: =D76-E76 -> 0 | K76: =SUMIFS('Mar - registro gastos'!$D$3:$D$300,'Mar - registro gastos'!$E$3:$E$300,Mar!$H$67,'Mar - registro gastos'!$F$3:$F$300,Mar!H76) -> 0 | L76: =J76-K76 -> 0
E77: =SUMIFS('Mar - registro gastos'!$D$3:$D$300,'Mar - registro gastos'!$E$3:$E$300,Mar!$B$67,'Mar - registro gastos'!$F$3:$F$300,Mar!B77) -> 0 | F77: =D77-E77 -> 0 | K77: =SUMIFS('Mar - registro gastos'!$D$3:$D$300,'Mar - registro gastos'!$E$3:$E$300,Mar!$H$67,'Mar - registro gastos'!$F$3:$F$300,Mar!H77) -> 0 | L77: =J77-K77 -> 0
E78: =SUMIFS('Mar - registro gastos'!$D$3:$D$300,'Mar - registro gastos'!$E$3:$E$300,Mar!$B$67,'Mar - registro gastos'!$F$3:$F$300,Mar!B78) -> 0 | F78: =D78-E78 -> 0 | K78: =SUMIFS('Mar - registro gastos'!$D$3:$D$300,'Mar - registro gastos'!$E$3:$E$300,Mar!$H$67,'Mar - registro gastos'!$F$3:$F$300,Mar!H78) -> 0 | L78: =J78-K78 -> 0
B79: Subtotal | D79: =SUM(D68:D78) -> 0 | E79: =SUM(E68:E78) -> 0 | F79: =D79-E79 -> 0 | H79: Subtotal | J79: =SUM(J68:J78) -> 0 | K79: =SUM(K68:K78) -> 0 | L79: =J79-K79 -> 0
B81: MASCOTA | C81: Ahorro | D81: Presupuesto | E81: Gasto | F81: Disponible | H81: OTROS 1 | I81: Ahorro | J81: Presupuesto | K81: Gasto | L81: Disponible
B82: Comida | E82: =SUMIFS('Mar - registro gastos'!$D$3:$D$300,'Mar - registro gastos'!$E$3:$E$300,Mar!$B$81,'Mar - registro gastos'!$F$3:$F$300,Mar!B82) -> 0 | F82: =D82-E82 -> 0 | H82: 1 | K82: =SUMIFS('Mar - registro gastos'!$D$3:$D$300,'Mar - registro gastos'!$E$3:$E$300,Mar!$H$81,'Mar - registro gastos'!$F$3:$F$300,Mar!H82) -> 0 | L82: =J82-K82 -> 0
B83: Veterinario | E83: =SUMIFS('Mar - registro gastos'!$D$3:$D$300,'Mar - registro gastos'!$E$3:$E$300,Mar!$B$81,'Mar - registro gastos'!$F$3:$F$300,Mar!B83) -> 0 | F83: =D83-E83 -> 0 | K83: =SUMIFS('Mar - registro gastos'!$D$3:$D$300,'Mar - registro gastos'!$E$3:$E$300,Mar!$H$81,'Mar - registro gastos'!$F$3:$F$300,Mar!H83) -> 0 | L83: =J83-K83 -> 0
B84: Juguetes | E84: =SUMIFS('Mar - registro gastos'!$D$3:$D$300,'Mar - registro gastos'!$E$3:$E$300,Mar!$B$81,'Mar - registro gastos'!$F$3:$F$300,Mar!B84) -> 0 | F84: =D84-E84 -> 0 | K84: =SUMIFS('Mar - registro gastos'!$D$3:$D$300,'Mar - registro gastos'!$E$3:$E$300,Mar!$H$81,'Mar - registro gastos'!$F$3:$F$300,Mar!H84) -> 0 | L84: =J84-K84 -> 0
B85: Medicinas | E85: =SUMIFS('Mar - registro gastos'!$D$3:$D$300,'Mar - registro gastos'!$E$3:$E$300,Mar!$B$81,'Mar - registro gastos'!$F$3:$F$300,Mar!B85) -> 0 | F85: =D85-E85 -> 0 | K85: =SUMIFS('Mar - registro gastos'!$D$3:$D$300,'Mar - registro gastos'!$E$3:$E$300,Mar!$H$81,'Mar - registro gastos'!$F$3:$F$300,Mar!H85) -> 0 | L85: =J85-K85 -> 0
E86: =SUMIFS('Mar - registro gastos'!$D$3:$D$300,'Mar - registro gastos'!$E$3:$E$300,Mar!$B$81,'Mar - registro gastos'!$F$3:$F$300,Mar!B86) -> 0 | F86: =D86-E86 -> 0 | K86: =SUMIFS('Mar - registro gastos'!$D$3:$D$300,'Mar - registro gastos'!$E$3:$E$300,Mar!$H$81,'Mar - registro gastos'!$F$3:$F$300,Mar!H86) -> 0 | L86: =J86-K86 -> 0
E87: =SUMIFS('Mar - registro gastos'!$D$3:$D$300,'Mar - registro gastos'!$E$3:$E$300,Mar!$B$81,'Mar - registro gastos'!$F$3:$F$300,Mar!B87) -> 0 | F87: =D87-E87 -> 0 | K87: =SUMIFS('Mar - registro gastos'!$D$3:$D$300,'Mar - registro gastos'!$E$3:$E$300,Mar!$H$81,'Mar - registro gastos'!$F$3:$F$300,Mar!H87) -> 0 | L87: =J87-K87 -> 0
B88: Subtotal | D88: =SUM(D82:D87) -> 0 | E88: =SUM(E82:E87) -> 0 | F88: =D88-E88 -> 0 | H88: Subtotal | J88: =SUM(J82:J87) -> 0 | K88: =SUM(K82:K87) -> 0 | L88: =J88-K88 -> 0
B90: OTROS 2 | C90: Ahorro | D90: Presupuesto | E90: Gasto | F90: Disponible | H90: OTROS 3 | I90: Ahorro | J90: Presupuesto | K90: Gasto | L90: Disponible
B91: 2 | E91: =SUMIFS('Mar - registro gastos'!$D$3:$D$300,'Mar - registro gastos'!$E$3:$E$300,Mar!$B$90,'Mar - registro gastos'!$F$3:$F$300,Mar!B91) -> 0 | F91: =D91-E91 -> 0 | H91: 3 | K91: =SUMIFS('Mar - registro gastos'!$D$3:$D$300,'Mar - registro gastos'!$E$3:$E$300,Mar!$H$90,'Mar - registro gastos'!$F$3:$F$300,Mar!H91) -> 0 | L91: =J91-K91 -> 0
E92: =SUMIFS('Mar - registro gastos'!$D$3:$D$300,'Mar - registro gastos'!$E$3:$E$300,Mar!$B$90,'Mar - registro gastos'!$F$3:$F$300,Mar!B92) -> 0 | F92: =D92-E92 -> 0 | K92: =SUMIFS('Mar - registro gastos'!$D$3:$D$300,'Mar - registro gastos'!$E$3:$E$300,Mar!$H$90,'Mar - registro gastos'!$F$3:$F$300,Mar!H92) -> 0 | L92: =J92-K92 -> 0
E93: =SUMIFS('Mar - registro gastos'!$D$3:$D$300,'Mar - registro gastos'!$E$3:$E$300,Mar!$B$90,'Mar - registro gastos'!$F$3:$F$300,Mar!B93) -> 0 | F93: =D93-E93 -> 0 | K93: =SUMIFS('Mar - registro gastos'!$D$3:$D$300,'Mar - registro gastos'!$E$3:$E$300,Mar!$H$90,'Mar - registro gastos'!$F$3:$F$300,Mar!H93) -> 0 | L93: =J93-K93 -> 0
E94: =SUMIFS('Mar - registro gastos'!$D$3:$D$300,'Mar - registro gastos'!$E$3:$E$300,Mar!$B$90,'Mar - registro gastos'!$F$3:$F$300,Mar!B94) -> 0 | F94: =D94-E94 -> 0 | K94: =SUMIFS('Mar - registro gastos'!$D$3:$D$300,'Mar - registro gastos'!$E$3:$E$300,Mar!$H$90,'Mar - registro gastos'!$F$3:$F$300,Mar!H94) -> 0 | L94: =J94-K94 -> 0
E95: =SUMIFS('Mar - registro gastos'!$D$3:$D$300,'Mar - registro gastos'!$E$3:$E$300,Mar!$B$90,'Mar - registro gastos'!$F$3:$F$300,Mar!B95) -> 0 | F95: =D95-E95 -> 0 | K95: =SUMIFS('Mar - registro gastos'!$D$3:$D$300,'Mar - registro gastos'!$E$3:$E$300,Mar!$H$90,'Mar - registro gastos'!$F$3:$F$300,Mar!H95) -> 0 | L95: =J95-K95 -> 0
E96: =SUMIFS('Mar - registro gastos'!$D$3:$D$300,'Mar - registro gastos'!$E$3:$E$300,Mar!$B$90,'Mar - registro gastos'!$F$3:$F$300,Mar!B96) -> 0 | F96: =D96-E96 -> 0 | K96: =SUMIFS('Mar - registro gastos'!$D$3:$D$300,'Mar - registro gastos'!$E$3:$E$300,Mar!$H$90,'Mar - registro gastos'!$F$3:$F$300,Mar!H96) -> 0 | L96: =J96-K96 -> 0
E97: =SUMIFS('Mar - registro gastos'!$D$3:$D$300,'Mar - registro gastos'!$E$3:$E$300,Mar!$B$90,'Mar - registro gastos'!$F$3:$F$300,Mar!B97) -> 0 | F97: =D97-E97 -> 0 | K97: =SUMIFS('Mar - registro gastos'!$D$3:$D$300,'Mar - registro gastos'!$E$3:$E$300,Mar!$H$90,'Mar - registro gastos'!$F$3:$F$300,Mar!H97) -> 0 | L97: =J97-K97 -> 0
B98: Subtotal | D98: =SUM(D91:D97) -> 0 | E98: =SUM(E91:E97) -> 0 | F98: =D98-E98 -> 0 | H98: Subtotal | J98: =SUM(J91:J97) -> 0 | K98: =SUM(K91:K97) -> 0 | L98: =J98-K98 -> 0
B100: OTROS 4 | C100: Ahorro | D100: Presupuesto | E100: Gasto | F100: Disponible | H100: OTROS 5 | I100: Ahorro | J100: Presupuesto | K100: Gasto | L100: Disponible
B101: 4 | E101: =SUMIFS('Mar - registro gastos'!$D$3:$D$300,'Mar - registro gastos'!$E$3:$E$300,Mar!$B$100,'Mar - registro gastos'!$F$3:$F$300,Mar!B101) -> 0 | F101: =D101-E101 -> 0 | H101: 5 | K101: =SUMIFS('Mar - registro gastos'!$D$3:$D$300,'Mar - registro gastos'!$E$3:$E$300,Mar!$H$100,'Mar - registro gastos'!$F$3:$F$300,Mar!H101) -> 0 | L101: =J101-K101 -> 0
E102: =SUMIFS('Mar - registro gastos'!$D$3:$D$300,'Mar - registro gastos'!$E$3:$E$300,Mar!$B$100,'Mar - registro gastos'!$F$3:$F$300,Mar!B102) -> 0 | F102: =D102-E102 -> 0 | K102: =SUMIFS('Mar - registro gastos'!$D$3:$D$300,'Mar - registro gastos'!$E$3:$E$300,Mar!$H$100,'Mar - registro gastos'!$F$3:$F$300,Mar!H102) -> 0 | L102: =J102-K102 -> 0
E103: =SUMIFS('Mar - registro gastos'!$D$3:$D$300,'Mar - registro gastos'!$E$3:$E$300,Mar!$B$100,'Mar - registro gastos'!$F$3:$F$300,Mar!B103) -> 0 | F103: =D103-E103 -> 0 | K103: =SUMIFS('Mar - registro gastos'!$D$3:$D$300,'Mar - registro gastos'!$E$3:$E$300,Mar!$H$100,'Mar - registro gastos'!$F$3:$F$300,Mar!H103) -> 0 | L103: =J103-K103 -> 0
E104: =SUMIFS('Mar - registro gastos'!$D$3:$D$300,'Mar - registro gastos'!$E$3:$E$300,Mar!$B$100,'Mar - registro gastos'!$F$3:$F$300,Mar!B104) -> 0 | F104: =D104-E104 -> 0 | K104: =SUMIFS('Mar - registro gastos'!$D$3:$D$300,'Mar - registro gastos'!$E$3:$E$300,Mar!$H$100,'Mar - registro gastos'!$F$3:$F$300,Mar!H104) -> 0 | L104: =J104-K104 -> 0
E105: =SUMIFS('Mar - registro gastos'!$D$3:$D$300,'Mar - registro gastos'!$E$3:$E$300,Mar!$B$100,'Mar - registro gastos'!$F$3:$F$300,Mar!B105) -> 0 | F105: =D105-E105 -> 0 | K105: =SUMIFS('Mar - registro gastos'!$D$3:$D$300,'Mar - registro gastos'!$E$3:$E$300,Mar!$H$100,'Mar - registro gastos'!$F$3:$F$300,Mar!H105) -> 0 | L105: =J105-K105 -> 0
E106: =SUMIFS('Mar - registro gastos'!$D$3:$D$300,'Mar - registro gastos'!$E$3:$E$300,Mar!$B$100,'Mar - registro gastos'!$F$3:$F$300,Mar!B106) -> 0 | F106: =D106-E106 -> 0 | K106: =SUMIFS('Mar - registro gastos'!$D$3:$D$300,'Mar - registro gastos'!$E$3:$E$300,Mar!$H$100,'Mar - registro gastos'!$F$3:$F$300,Mar!H106) -> 0 | L106: =J106-K106 -> 0
E107: =SUMIFS('Mar - registro gastos'!$D$3:$D$300,'Mar - registro gastos'!$E$3:$E$300,Mar!$B$100,'Mar - registro gastos'!$F$3:$F$300,Mar!B107) -> 0 | F107: =D107-E107 -> 0 | K107: =SUMIFS('Mar - registro gastos'!$D$3:$D$300,'Mar - registro gastos'!$E$3:$E$300,Mar!$H$100,'Mar - registro gastos'!$F$3:$F$300,Mar!H107) -> 0 | L107: =J107-K107 -> 0
B108: Subtotal | D108: =SUM(D101:D107) -> 0 | E108: =SUM(E101:E107) -> 0 | F108: =D108-E108 -> 0 | H108: Subtotal | J108: =SUM(J101:J107) -> 0 | K108: =SUM(K101:K107) -> 0 | L108: =J108-K108 -> 0

Sheet Mar - registro gastos
B2: Fecha | C2: Compra | D2: Valor | E2: Categoría | F2: Sub Categoría | J2: Categoría
H3: =E3&F3 | I3: =IFERROR(VLOOKUP(H3,$AP:$AQ,2,FALSE),"Error") -> Error | J3: =IF(I3="Error","Revisa tu subcategoria",IF(I3=H3,"Es correcto",IF(H3="blanco","",""))) -> Revisa tu subcategoria | AN3: CATEGORÍA | AO3: SUBCATEGORIA
H4: =E4&F4 | I4: =IFERROR(VLOOKUP(H4,$AP:$AQ,2,FALSE),"Error") -> Error | J4: =IF(I4="Error","Revisa tu subcategoria",IF(I4=H4,"Es correcto",IF(H4="blanco","",""))) -> Revisa tu subcategoria | AN4: =Mar!$B$12 -> NECESIDADES BÁSICAS | AO4: =Mar!B13 -> Arriendo/Hipoteca | AP4: =AN4&AO4 -> NECESIDADES BÁSICASArriendo/Hipoteca | AQ4: =AP4 -> NECESIDADES BÁSICASArriendo/Hipoteca
H5: =E5&F5 | I5: =IFERROR(VLOOKUP(H5,$AP:$AQ,2,FALSE),"Error") -> Error | J5: =IF(I5="Error","Revisa tu subcategoria",IF(I5=H5,"Es correcto",IF(H5="blanco","",""))) -> Revisa tu subcategoria | AN5: =Mar!$B$12 -> NECESIDADES BÁSICAS | AO5: =Mar!B14 -> Telefono/ Celular | AP5: =AN5&AO5 -> NECESIDADES BÁSICASTelefono/ Celular | AQ5: =AP5 -> NECESIDADES BÁSICASTelefono/ Celular
H6: =E6&F6 | I6: =IFERROR(VLOOKUP(H6,$AP:$AQ,2,FALSE),"Error") -> Error | J6: =IF(I6="Error","Revisa tu subcategoria",IF(I6=H6,"Es correcto",IF(H6="blanco","",""))) -> Revisa tu subcategoria | AN6: =Mar!$B$12 -> NECESIDADES BÁSICAS | AO6: =Mar!B15 -> Electricidad | AP6: =AN6&AO6 -> NECESIDADES BÁSICASElectricidad | AQ6: =AP6 -> NECESIDADES BÁSICASElectricidad
H7: =E7&F7 | I7: =IFERROR(VLOOKUP(H7,$AP:$AQ,2,FALSE),"Error") -> Error | J7: =IF(I7="Error","Revisa tu subcategoria",IF(I7=H7,"Es correcto",IF(H7="blanco","",""))) -> Revisa tu subcategoria | AN7: =Mar!$B$12 -> NECESIDADES BÁSICAS | AO7: =Mar!B16 -> Agua | AP7: =AN7&AO7 -> NECESIDADES BÁSICASAgua | AQ7: =AP7 -> NECESIDADES BÁSICASAgua
